Workbook

Sheet Index
A1: =Assumptions!B2 -> Infosys Limited
B3: 📥 INPUTS
B5: Assumptions
B6: P&L Input
B7: BS Input
B8: CF Input
B9: Market Data
B10: Equity Beta
B11: Comps Data
B14: 📊Calculation & Analysis
B16: Common Sizing
B17: Revenue Build-up
B18: Working Capital
... B27: FAS

Sheet Assumptions
B2: Infosys Limited
B6: Company Description | C6: Infosys Limited
B7: ISIN Code | C7: INE009A01021
B8: Sector Name | C8: Information Technology
B9: Industry | C9: Computers - Software & Consulting
B10: Exchange Name | C10: BSE: 500209, NSE: INFY
B11: Website | C11: https://www.infosys.com
B12: Company Description | C12: Infosys Limited is a global leader in AI-first business consulting and technology services. Established in 1981, Infosys helps enterprises across 59 countries navigate digital transformation through AI, cloud, digital services, consulting and technology solutions. With over 3.25 lakh employees and 1,965 active clients, the company focuses on enterprise transformation, AI-first services, cloud capabilities and digital innovation.
B13: Current Market Price | C13: 1161.2
B16: Scenario | D16: Case
B17: Base case | D17: =IF(B17="Best case",1,IF(B17="Base case",2,3)) -> 2
B20: Company data
B21: Particulars | D21: Amount
B22: No of Outstanding shares | C22: Nos | D22: 4038289901
B23: Face Value per share | C23: Rs. | D23: 5
B24: Current Market Price | C24: Rs. | D24: =C13 -> 1161.2
B25: Market Capitalisation | C25: INR in Crs | D25: =D22*D24/10^7 -> 468926.22
B28: Assumptions
B29: Perpetual Growth rate | C29: % | D29: 0.04
B30: 10 year Bond yield rate | C30: % | D30: 0.07077
B31: Interest rate | C31: % | D31: ='Cost Buildup'!G35*(1-'Cost Buildup'!G37) -> 0.033409756
B32: Bull Case Tapering Rate (p.a.) | C32: % | D32: 0.01
I33: Revenue in Crs
B34: Company Revenue by Geography
B35: Year | C35: ='Revenue Buildup'!B38 -> North America | E35: ='Revenue Buildup'!B44 -> Europe | G35: ='Revenue Buildup'!B50 -> India | I35: Rest of the World
B36: 2022 | C36: ='Revenue Buildup'!C38 -> 75058 | E36: ='Revenue Buildup'!C44 -> 30129 | G36: ='Revenue Buildup'!C50 -> 3585 | I36: ='Revenue Buildup'!C56 -> 12869
B37: =B36+1 -> 2023 | C37: ='Revenue Buildup'!D38 -> 90724 | E37: ='Revenue Buildup'!D44 -> 37675 | G37: ='Revenue Buildup'!D50 -> 3861 | I37: ='Revenue Buildup'!D56 -> 14507
B38: =B37+1 -> 2024 | C38: ='Revenue Buildup'!E38 -> 92411 | E38: ='Revenue Buildup'!E44 -> 42267 | G38: ='Revenue Buildup'!E50 -> 3881 | I38: ='Revenue Buildup'!E56 -> 15111
B39: =B38+1 -> 2025 | C39: ='Revenue Buildup'!F38 -> 94397 | E39: ='Revenue Buildup'!F44 -> 48595 | G39: ='Revenue Buildup'!F50 -> 5014 | I39: ='Revenue Buildup'!F56 -> 14984
B40: =B39+1 -> 2026 | C40: ='Revenue Buildup'!G38 -> 100167 | E40: ='Revenue Buildup'!G44 -> 57454 | G40: ='Revenue Buildup'!G50 -> 5102 | I40: ='Revenue Buildup'!G56 -> 15927
B46: Headings | C46: Reference | D46: Assumptions
B47: Revenue Buildup | C47: H15:Q15 | D47: Revenue is forecast using the historical average growth rate as the base assumption. The Bull Case assumes a higher growth rate than the Base Case, while the Bear Case assumes a lower growth rate. The growth rate under the scenarios is tapered by 1% annually to reflect a gradual moderation in growth over the forecast period.
C48: H18:Q18 H22:Q22 | D48: Other Income is forecast at 2% of Revenue from Operations based on the historical trend. Exceptional Items were reported only in FY2026 at approximately 1% of Revenue from Operations. For the forecast period, Exceptional Items are assumed at 0.25% of Revenue from Operations to reflect a lower impact compared with FY2026.
B49: Cost Buildup | C49: H13:Q13 H31:Q31 | D49: Employee Cost and other operating expenses are forecast as a percentage of Revenue from Operations using the historical average ratio. The average historical cost-to-revenue ratio is applied consistently throughout the forecast period.
C50: H34:Q34 | D50: Finance Cost is forecast as a percentage of period-end Lease Liabilities. The historical Finance Cost-to-Lease Liabilities ratio is calculated for the past five years, and the average historical ratio of approximately 4% is applied throughout the forecast period.
C51: H37:Q37 | D51: The Effective Tax Rate is forecast based on the historical tax rate, with an annual increase of 0.3 percentage points from FY2027 onwards. The FY2027 tax rate is derived by adding 0.3% to the FY2026 rate, and the same incremental approach is followed throughout the forecast period.
B52: FAS | C52: H173:Q173 | D52: Figures of the year 2025 are used to forecast the additions, disposals and depreciation of Fixed assets, Intangibles and ROU assets with 4% growth rate for the 1st projected year and for every 3 years.
C53: H165:Q165 | D53: Capital WIP for FY2027 is based on the average historical increase in Capital WIP. From FY2028 onwards, the annual increase in Capital WIP is grown by 0.5% each year.
B54: BS Items | C54: I13:R13 I54:R54 | D54: Balance Sheet line items are forecast as a percentage of Revenue from Operations using their respective five-year historical average ratios.
B55: Working Capital | C55: H11:Q11 H12:Q12 | D55: Trade Receivables and Trade Payables are projected as a fixed percentage of revenue, based on the average proportions observed over the last five audited years.
B56: Income Statement | C56: H53:Q53 | D56: Total Dividend payments have been projected based on the five-year average of Dividend Payout as percentage of net profit. This average growth rate has been applied to estimate future dividends, and it is assumed to remain constant throughout the forecast period (2027–2036).
B57: Balance Sheet | C57: H33:Q33 | D57: Cash and Cash equivalents are taken as the Balancing Figure

Sheet P&L Input
B2: Infosys Limited
F6: (INR in Crores)
B7: P&L Input
B8: Particulars | C8: 2022 | D8: =C8+1 -> 2023 | E8: =D8+1 -> 2024 | F8: =E8+1 -> 2025 | G8: =F8+1 -> 2026
C9: Audited | D9: Audited | E9: Audited | F9: Audited | G9: Audited
B11: Revenue from Operations | C11: 121641 | D11: 146767 | E11: 153670 | F11: 162990 | G11: 178650
B12: Other Income, net | C12: 2295 | D12: 2701 | E12: 4711 | F12: 3600 | G12: 4322
B14: Total Income | C14: =SUM(C11:C12) -> 123936 | D14: =SUM(D11:D12) -> 149468 | E14: =SUM(E11:E12) -> 158381 | F14: =SUM(F11:F12) -> 166590 | G14: =SUM(G11:G12) -> 182972
B16: Expenses
B17: Employee benefit expenses | C17: 63986 | D17: 78359 | E17: 82620 | F17: 85950 | G17: 95094
B18: Cost of technical sub-contractors | C18: 12606 | D18: 14062 | E18: 12232 | F18: 12937 | G18: 15421
B19: Travel expenses | C19: 827 | D19: 1525 | E19: 1759 | F19: 1894 | G19: 2097
B20: Cost of software packages and others | C20: 6811 | D20: 10902 | E20: 13515 | F20: 15911 | G20: 15722
B21: Communication expenses | C21: 611 | D21: 713 | E21: 677 | F21: 620 | G21: 603
B22: Consultancy and professional charges | C22: 1885 | D22: 1684 | E22: 1726 | F22: 1655 | G22: 2090
B23: Other expenses | C23: 3424 | D23: 4392 | E23: 4716 | F23: 4787 | G23: 5343
B24: Total Expenses | C24: =SUM(C17:C23) -> 90150 | D24: =SUM(D17:D23) -> 111637 | E24: =SUM(E17:E23) -> 117245 | F24: =SUM(F17:F23) -> 123754 | G24: =SUM(G17:G23) -> 136370
B26: EBITDA | C26: =C14-C24 -> 33786 | D26: =D14-D24 -> 37831 | E26: =E14-E24 -> 41136 | F26: =F14-F24 -> 42836 | G26: =G14-G24 -> 46602
B28: Depreciation and Amortisation Expenses | C28: 3476 | D28: 4225 | E28: 4678 | F28: 4812 | G28: 4902
B30: EBIT | C30: =C26-C28 -> 30310 | D30: =D26-D28 -> 33606 | E30: =E26-E28 -> 36458 | F30: =F26-F28 -> 38024 | G30: =G26-G28 -> 41700
B32: Finance Costs | C32: 200 | D32: 284 | E32: 470 | F32: 416 | G32: 416
B34: Profit before exceptional items | C34: =C30-C32 -> 30110 | D34: =D30-D32 -> 33322 | E34: =E30-E32 -> 35988 | F34: =F30-F32 -> 37608 | G34: =G30-G32 -> 41284
B36: Exceptional items | C36: 0 | D36: 0 | E36: 0 | F36: 0 | G36: 1289
B38: Profit before Tax | C38: =C34-C36 -> 30110 | D38: =D34-D36 -> 33322 | E38: =E34-E36 -> 35988 | F38: =F34-F36 -> 37608 | G38: =G34-G36 -> 39995
B40: Taxes (Current + Deferred) | C40: 7964 | D40: 9214 | E40: 9740 | F40: 10858 | G40: 10521
B42: Net Profit | C42: =C38-C40 -> 22146 | D42: =D38-D40 -> 24108 | E42: =E38-E40 -> 26248 | F42: =F38-F40 -> 26750 | G42: =G38-G40 -> 29474
B45: KPIs
B46: Revenue % (y-o-y) | C46: - | D46: =D11/C11-1 -> 0.20655864 | E46: =E11/D11-1 -> 0.047033734 | F46: =F11/E11-1 -> 0.060649444 | G46: =G11/F11-1 -> 0.096079514
B47: EBITDA% | C47: =C26/C14 -> 0.27260844 | D47: =D26/D14 -> 0.25310434 | E47: =E26/E14 -> 0.25972812 | F47: =F26/F14 -> 0.25713428 | G47: =G26/G14 -> 0.25469471
B48: EBIT % | C48: =C30/C14 -> 0.24456171 | D48: =D30/D14 -> 0.22483742 | E48: =E30/E14 -> 0.23019175 | F48: =F30/F14 -> 0.22824899 | G48: =G30/G14 -> 0.22790372
B49: NP % | C49: =C42/C14 -> 0.178689 | D49: =D42/D14 -> 0.16129205 | E49: =E42/E14 -> 0.16572695 | F49: =F42/F14 -> 0.16057386 | G49: =G42/G14 -> 0.16108476
B50: ROA | C50: 0.18786105 | D50: 0.19161315 | E50: 0.1904596 | F50: 0.17964715 | G50: 0.18897587
B51: Asset Turnover | C51: 1.0318616 | D51: 1.166521 | E51: 1.1150536 | F51: 1.0946052 | G51: 1.1454346
B52: Assets / Equity | C52: 1.5565253 | D52: 1.6599512 | E52: 1.5579069 | F52: 1.5478 | G52: 1.6717258
B53: ROE | C53: =C49*C51*C52 -> 0.28699573 | D53: =D49*D51*D52 -> 0.31232074 | E53: =E49*E51*E52 -> 0.28789252 | F53: =F49*F51*F52 -> 0.27204904 | G53: =G49*G51*G52 -> 0.30845356

Sheet BS Input
B2: Infosys Limited
B6: Balance Sheet Input
B7: Particulars | D7: 2022 | E7: =D7+1 -> 2023 | F7: =E7+1 -> 2024 | G7: =F7+1 -> 2025 | H7: =G7+1 -> 2026
D8: Audited | E8: Audited | F8: Audited | G8: Audited | H8: Audited
B9: ASSETS
B11: Non-Current Assets
C12: PPE | D12: 13075 | E12: 13346 | F12: 12370 | G12: 11778 | H12: 12651
C13: ROU Assets | D13: 4823 | E13: 6882 | F13: 6552 | G13: 6311 | H13: 6177
C14: Capital WIP | D14: 416 | E14: 288 | F14: 293 | G14: 814 | H14: 526
C15: Goodwill | D15: 6195 | E15: 7248 | F15: 7303 | G15: 10106 | H15: 12117
C16: Other Intangible assets | D16: 1707 | E16: 1749 | F16: 1397 | G16: 2766 | H16: 2825
C17: Financial Assets
C18: Investments | D18: 13651 | E18: 12569 | F18: 11708 | G18: 11059 | H18: 8930
C19: Loans | D19: 34 | E19: 39 | F19: 34 | G19: 16 | H19: 6
C20: Other financial assets | D20: 1460 | E20: 2798 | F20: 3105 | G20: 3511 | H20: 2776
C21: Deferred Tax Assets(net) | D21: 1212 | E21: 1245 | F21: 454 | G21: 1108 | H21: 2264
C22: Income tax assets (net) | D22: 6098 | E22: 6453 | F22: 3045 | G22: 1622 | H22: 666
C23: Other non-current assets | D23: 2029 | E23: 2318 | F23: 2121 | G23: 2713 | H23: 3540
B25: Total Non-current assets | D25: =SUM(D12:D16,D18:D23) -> 50700 | E25: =SUM(E12:E16,E18:E23) -> 54935 | F25: =SUM(F12:F16,F18:F23) -> 48382 | G25: =SUM(G12:G16,G18:G23) -> 51804 | H25: =SUM(H12:H16,H18:H23) -> 52478
B27: Current Assets
C28: Financial Assets
C29: Investments | D29: 6673 | E29: 6909 | F29: 12915 | G29: 12482 | H29: 12950
C30: Trade Receivables | D30: 22698 | E30: 25424 | F30: 30193 | G30: 31158 | H30: 35234
C31: Cash & Cash Equivalents | D31: 17472 | E31: 12173 | F31: 14786 | G31: 24455 | H31: 22201
C32: Loans | D32: 248 | E32: 289 | F32: 248 | G32: 249 | H32: 234
C33: Other financial assets | D33: 8727 | E33: 11604 | F33: 12085 | G33: 13840 | H33: 15890
C34: Income tax assets (net) | D34: 54 | E34: 6 | F34: 6397 | G34: 2975 | H34: 1835
C35: Other current assets | D35: 11313 | E35: 14476 | F35: 12808 | G35: 11940 | H35: 15145
B37: Total Current Assets | D37: =SUM(D29:D35) -> 67185 | E37: =SUM(E29:E35) -> 70881 | F37: =SUM(F29:F35) -> 89432 | G37: =SUM(G29:G35) -> 97099 | H37: =SUM(H29:H35) -> 103489
B39: TOTAL | D39: =D25+D37 -> 117885 | E39: =E25+E37 -> 125816 | F39: =F25+F37 -> 137814 | G39: =G25+G37 -> 148903 | H39: =H25+H37 -> 155967
B41: EQUITY AND LIABILITIES
B43: Shareholder Funds
C44: Equity Share Capital | D44: 2098 | E44: 2069 | F44: 2071 | G44: 2073 | H44: 2024
C45: Other Equity | D45: 73252 | E45: 73338 | F45: 86045 | G45: 93745 | H45: 90828
C46: Non-Controlling Interest | D46: 386 | E46: 388 | F46: 345 | G46: 385 | H46: 445
B48: Total Equity | D48: =SUM(D44:D46) -> 75736 | E48: =SUM(E44:E46) -> 75795 | F48: =SUM(F44:F46) -> 88461 | G48: =SUM(G44:G46) -> 96203 | H48: =SUM(H44:H46) -> 93297
B50: Non-current liabilities
C51: Financial Liabilities
C52: Lease Liabilities | D52: 4602 | E52: 7057 | F52: 6400 | G52: 5772 | H52: 6016
C53: Other financial liabilities | D53: 2337 | E53: 2058 | F53: 2130 | G53: 2141 | H53: 2092
C54: Other non current liabilities | D54: 451 | E54: 500 | F54: 235 | G54: 215 | H54: 561
C55: Deferred Tax Liability(net) | D55: 1156 | E55: 1220 | F55: 1794 | G55: 1722 | H55: 1679
B57: Total Non-Current liabilities | D57: =SUM(D52:D55) -> 8546 | E57: =SUM(E52:E55) -> 10835 | F57: =SUM(F52:F55) -> 10559 | G57: =SUM(G52:G55) -> 9850 | H57: =SUM(H52:H55) -> 10348
B59: Current Liabilities
C60: Financial Liabilities
C61: Lease liabilities | D61: 872 | E61: 1242 | F61: 1959 | G61: 2455 | H61: 3160
C62: Trade Payables | D62: 4134 | E62: 3865 | F62: 3956 | G62: 4164 | H62: 4744
C63: Other Financial liabilities | D63: 15837 | E63: 18558 | F63: 16959 | G63: 18138 | H63: 21483
C64: Other current liabilities | D64: 9178 | E64: 10830 | F64: 10539 | G64: 11765 | H64: 15779
C65: Provisions | D65: 975 | E65: 1307 | F65: 1796 | G65: 1475 | H65: 1512
C66: Income Tax Liabilities(net) | D66: 2607 | E66: 3384 | F66: 3585 | G66: 4853 | H66: 5644
B68: Total Current liabilities | D68: =SUM(D61:D67) -> 33603 | E68: =SUM(E61:E67) -> 39186 | F68: =SUM(F61:F67) -> 38794 | G68: =SUM(G61:G67) -> 42850 | H68: =SUM(H61:H67) -> 52322
B70: TOTAL | D70: =D68+D57+D48 -> 117885 | E70: =E68+E57+E48 -> 125816 | F70: =F68+F57+F48 -> 137814 | G70: =G68+G57+G48 -> 148903 | H70: =H68+H57+H48 -> 155967
D71: =D70-D39 -> 0 | E71: =E70-E39 -> 0 | F71: =F70-F39 -> 0 | G71: =G70-G39 -> 0 | H71: =H70-H39 -> 0
C73: KPIs
C74: Liquidity ratios
C75: Current ratio | D75: =D37/D68 -> 1.9993751 | E75: =E37/E68 -> 1.8088348 | F75: =F37/F68 -> 2.3053049 | G75: =G37/G68 -> 2.266021 | H75: =H37/H68 -> 1.9779252
C76: Quick ratio | D76: =(D30+D31)/D68 -> 1.195429 | E76: =(E30+E31)/E68 -> 0.9594498 | F76: =(F30+F31)/F68 -> 1.1594319 | G76: =(G30+G31)/G68 -> 1.297853 | H76: =(H30+H31)/H68 -> 1.0977218
C77: Cash ratio | D77: =(D31)/D68 -> 0.51995358 | E77: =(E31)/E68 -> 0.31064666 | F77: =(F31)/F68 -> 0.38114141 | G77: =(G31)/G68 -> 0.57071179 | H77: =(H31)/H68 -> 0.42431482
C78: Solvency ratios
C79: Interest coverage ratio | D79: ='P&L Input'!C26/'P&L Input'!C30 -> 1.1146816 | E79: ='P&L Input'!D26/'P&L Input'!D30 -> 1.1257216 | F79: ='P&L Input'!E26/'P&L Input'!E30 -> 1.128312 | G79: ='P&L Input'!F26/'P&L Input'!F30 -> 1.1265517 | H79: ='P&L Input'!G26/'P&L Input'!G30 -> 1.117554

Sheet CF Input
B2: Infosys Limited
G6: (INR in Crores)
B7: Cash Flow Input
B8: Particulars | D8: ='BS Input'!D7 -> 2022 | E8: ='BS Input'!E7 -> 2023 | F8: ='BS Input'!F7 -> 2024 | G8: ='BS Input'!G7 -> 2025 | H8: ='BS Input'!H7 -> 2026
D9: Audited | E9: Audited | F9: Audited | G9: Audited | H9: Audited
B11: Cash flow from operating activities
C12: Profit for the year | D12: 22146 | E12: 24108 | F12: 26248 | G12: 26750 | H12: 29474
C13: Adjustments to reconcile net profit to net cash provided by operating activities:
C14: – Income tax expense | D14: 7964 | E14: 9214 | F14: 9740 | G14: 10858 | H14: 10521
C15: – Depreciation and amortization | D15: 3476 | E15: 4225 | F15: 4678 | G15: 4812 | H15: 4902
C16: – Interest and dividend income | D16: -1645 | E16: -1817 | F16: -2067 | G16: -2570 | H16: -2630
C17: – Finance cost | D17: 200 | E17: 284 | F17: 470 | G17: 416 | H17: 416
C18: – Impairment loss recognized / (reversed) under expected credit loss model | D18: 170 | E18: 283 | F18: 121 | G18: 48 | H18: 33
C19: – Exchange differences on translation of assets and liabilities, net | D19: 119 | E19: 161 | F19: 76 | G19: 79 | H19: 954
C20: – Stock compensation expense | D20: 415 | E20: 519 | F20: 652 | G20: 802 | H20: 952
C21: – Interest receivable on income tax refund | D21: 0 | E21: 0 | F21: -1934 | G21: -327 | H21: -63
C22: – Provision for post-sales client support | D22: 0 | E22: 0 | F22: 75 | G22: -110 | H22: -167
C23: – Other adjustments | D23: 76 | E23: 628 | F23: 1464 | G23: 833 | H23: 881
B25: Changes in assets and liabilities
C26: – Trade receivables and unbilled revenue | D26: -7937 | E26: -7076 | F26: -2667 | G26: -1769 | H26: -5177
C27: – Loans, other financial assets and other assets | D27: -1914 | E27: -3108 | F27: -1172 | G27: -1024 | H27: -2645
C28: – Trade payables | D28: 1489 | E28: -279 | F28: 91 | G28: 176 | H28: -26
C29: – Other financial liabilities, other liabilities and provisions | D29: 6938 | E29: 4119 | F29: -1334 | G29: 2322 | H29: 5209
B31: Cash generated from operations | D31: =SUM(D12:D29) -> 31497 | E31: =SUM(E12:E29) -> 31261 | F31: =SUM(F12:F29) -> 34441 | G31: =SUM(G12:G29) -> 41296 | H31: =SUM(H12:H29) -> 42634
C32: – Income taxes paid | D32: -7612 | E32: -8794 | F32: -9231 | G32: -5602 | H32: -8648
B34: Net cash generated by operating activities | D34: =D31+D32 -> 23885 | E34: =E31+E32 -> 22467 | F34: =F31+F32 -> 25210 | G34: =G31+G32 -> 35694 | H34: =H31+H32 -> 33986
B36: Cash flows from investing activities
C37: – Expenditure on property, plant and equipment and intangibles | D37: -2161 | E37: -2579 | F37: -2201 | G37: -2237 | H37: -2727
C38: – Deposits placed with corporation | D38: -906 | E38: -996 | F38: -847 | G38: -1225 | H38: -944
C39: – Redemption of deposits placed with corporation | D39: 753 | E39: 762 | F39: 710 | G39: 776 | H39: 725
C40: – Interest and dividend received | D40: 1898 | E40: 1525 | F40: 1768 | G40: 2040 | H40: 2713
C41: – Payment towards acquisition of business, net of cash acquired | D41: 0 | E41: -910 | F41: 0 | G41: -3155 | H41: -637
C42: – Payment of contingent consideration pertaining to acquisition of business | D42: -53 | E42: -60 | F42: -101 | G42: 0 | H42: -13
C43: – Escrow and other deposits pertaining to buyback | D43: -420 | E43: -483 | F43: 0 | G43: 0 | H43: -1815
C44: – Redemption of escrow and other deposits pertaining to buyback | D44: 420 | E44: 483 | F44: 0 | G44: 0 | H44: 1815
C45: – Other receipts | D45: 67 | E45: 71 | F45: 128 | G45: 10 | H45: 15
C46: – Other payments | D46: -22 | E46: 0 | F46: 0 | G46: 0 | H46: 0
C48: Payments to acquire investments:
C49: Tax-free bonds and government bonds | D49: 0 | E49: -27 | F49: 0 | G49: -2 | H49: -153
C50: mutual fund units | D50: -54064 | E50: -70631 | F50: -66191 | G50: -73048 | H50: -72878
C51: Target maturity fund | D51: 0 | E51: -400 | F51: 0 | G51: 0 | H51: 0
C52: Certificates of deposit | D52: -4184 | E52: -10348 | F52: -8509 | G52: -6978 | H52: -14035
C53: Commercial paper | D53: 0 | E53: -3003 | F53: -10387 | G53: -6403 | H53: -3255
C54: Non-convertible debentures | D54: -1609 | E54: -249 | F54: -1526 | G54: -3240 | H54: -3438
C55: Government securities | D55: -4254 | E55: -1569 | F55: 0 | G55: 0 | H55: -2859
C56: Other investments | D56: -24 | E56: -20 | F56: -14 | G56: -60 | H56: -38
C58: Proceeds on sale of investments:
C59: Tax-free bonds and government bonds | D59: 20 | E59: 221 | F59: 150 | G59: 109 | H59: 1378
C60: mutual funds units | D60: 53669 | E60: 71851 | F60: 64767 | G60: 73987 | H60: 72682
C61: Target maturity funds | D61: 0 | E61: 0 | F61: 0 | G61: 0 | H61: 487
C62: Certificates of deposit | D62: 787 | E62: 10404 | F62: 9205 | G62: 6688 | H62: 9767
C63: Commercial paper | D63: 0 | E63: 2298 | F63: 6479 | G63: 7735 | H63: 5810
C64: Non-convertible debentures | D64: 2201 | E64: 470 | F64: 1230 | G64: 2591 | H64: 4083
C65: Government securities | D65: 1457 | E65: 1882 | F65: 304 | G65: 455 | H65: 5259
C66: Equity and preference securities | D66: 0 | E66: 99 | F66: 26 | G66: 0 | H66: 0
C67: Other investments | D67: 9 | E67: 0 | F67: 0 | G67: 11 | H67: 4
B69: Net cash (used in) / generated from investing activities | D69: =SUM(D37:D67) -> -6416 | E69: =SUM(E37:E67) -> -1209 | F69: =SUM(F37:F67) -> -5009 | G69: =SUM(G37:G67) -> -1946 | H69: =SUM(H37:H67) -> 1946
B71: Cash flows from financing activities
C72: – Payment of lease liabilities | D72: -915 | E72: -1231 | F72: -2024 | G72: -2355 | H72: -2824
C73: – Payment of dividends | D73: -12652 | E73: -13631 | F73: -14692 | G73: -20287 | H73: -18653
C74: – Loan repayment of in-tech Holding GmbH | D74: 0 | E74: 0 | F74: 0 | G74: -985 | H74: 0
C75: – Payment of dividend to non-controlling interest of subsidiary | D75: -79 | E75: -22 | F75: -39 | G75: -2 | H75: -3
C76: – Payment towards purchase of non-controlling interest | D76: -2 | E76: 0 | F76: 0 | G76: 0 | H76: 0
C77: – Payment towards buyback of shares pertaining to non-controlling interest of subsidiary | D77: 0 | E77: 0 | F77: -18 | G77: 0 | H77: 0
C78: – Shares issued on exercise of employee stock options | D78: 21 | E78: 35 | F78: 5 | G78: 6 | H78: 2
C79: – Other receipts | D79: 236 | E79: 132 | F79: 0 | G79: 0 | H79: 0
C80: – Other payments | D80: -126 | E80: -479 | F80: -736 | G80: -538 | H80: -250
C81: – Buyback of equity shares including transaction cost and tax on buyback | D81: -11125 | E81: -11499 | F81: 0 | G81: 0 | H81: -18058
B83: Net cash used in financing activities | D83: =SUM(D72:D81) -> -24642 | E83: =SUM(E72:E81) -> -26695 | F83: =SUM(F72:F81) -> -17504 | G83: =SUM(G72:G81) -> -24161 | H83: =SUM(H72:H81) -> -39786
B85: Net increase / (decrease) in cash and cash equivalents | D85: =D34+D69+D83 -> -7173 | E85: =E34+E69+E83 -> -5437 | F85: =F34+F69+F83 -> 2697 | G85: =G34+G69+G83 -> 9587 | H85: =H34+H69+H83 -> -3854
C86: – Effect of exchange rate changes on cash and cash equivalents | D86: -69 | E86: 138 | F86: -84 | G86: 82 | H86: 1600
C87: – Cash and cash equivalents at the beginning of the period | D87: 24714 | E87: =D89 -> 17472 | F87: =E89 -> 12173 | G87: =F89 -> 14786 | H87: =G89 -> 24455
B89: Cash and cash equivalents at the end of the period | D89: =D85+D86+D87 -> 17472 | E89: =E85+E86+E87 -> 12173 | F89: =F85+F86+F87 -> 14786 | G89: =G85+G86+G87 -> 24455 | H89: =H85+H86+H87 -> 22201

Sheet Common Sizing
B2: Infosys Limited
B7: Common Sizing
B8: Particulars | D8: ='BS Input'!D7 -> 2022 | E8: ='BS Input'!E7 -> 2023 | F8: ='BS Input'!F7 -> 2024 | G8: ='BS Input'!G7 -> 2025 | H8: ='BS Input'!H7 -> 2026
D9: Audited | E9: Audited | F9: Audited | G9: Audited | H9: Audited
C11: Revenue from Operations | D11: ='P&L Input'!C11/'P&L Input'!C$14 -> 0.98148238 | E11: ='P&L Input'!D11/'P&L Input'!D$14 -> 0.98192924 | F11: ='P&L Input'!E11/'P&L Input'!E$14 -> 0.97025527 | G11: ='P&L Input'!F11/'P&L Input'!F$14 -> 0.97839006 | H11: ='P&L Input'!G11/'P&L Input'!G$14 -> 0.9763789
C12: Other Operating Revenues | D12: ='P&L Input'!C12/'P&L Input'!C$14 -> 0.018517622 | E12: ='P&L Input'!D12/'P&L Input'!D$14 -> 0.018070758 | F12: ='P&L Input'!E12/'P&L Input'!E$14 -> 0.029744729 | G12: ='P&L Input'!F12/'P&L Input'!F$14 -> 0.021609941 | H12: ='P&L Input'!G12/'P&L Input'!G$14 -> 0.0236211
B14: Total Income | D14: ='P&L Input'!C14/'P&L Input'!C$14 -> 1 | E14: ='P&L Input'!D14/'P&L Input'!D$14 -> 1 | F14: ='P&L Input'!E14/'P&L Input'!E$14 -> 1 | G14: ='P&L Input'!F14/'P&L Input'!F$14 -> 1 | H14: ='P&L Input'!G14/'P&L Input'!G$14 -> 1
C16: Expenses
C17: Employee Benefit Expenses | D17: ='P&L Input'!C17/'P&L Input'!C$14 -> 0.5162826 | E17: ='P&L Input'!D17/'P&L Input'!D$14 -> 0.52425268 | F17: ='P&L Input'!E17/'P&L Input'!E$14 -> 0.52165348 | G17: ='P&L Input'!F17/'P&L Input'!F$14 -> 0.51593733 | H17: ='P&L Input'!G17/'P&L Input'!G$14 -> 0.51971886
C18: Other expenses | D18: ='P&L Input'!C18/'P&L Input'!C$14 -> 0.10171379 | E18: ='P&L Input'!D18/'P&L Input'!D$14 -> 0.094080338 | F18: ='P&L Input'!E18/'P&L Input'!E$14 -> 0.077231486 | G18: ='P&L Input'!F18/'P&L Input'!F$14 -> 0.077657723 | H18: ='P&L Input'!G18/'P&L Input'!G$14 -> 0.084280655
B20: Total Expenses | D20: ='P&L Input'!C20/'P&L Input'!C$14 -> 0.054955784 | E20: ='P&L Input'!D20/'P&L Input'!D$14 -> 0.072938689 | F20: ='P&L Input'!E20/'P&L Input'!E$14 -> 0.085332205 | G20: ='P&L Input'!F20/'P&L Input'!F$14 -> 0.095509935 | H20: ='P&L Input'!G20/'P&L Input'!G$14 -> 0.085925715
C22: EBITDA | D22: ='P&L Input'!C22/'P&L Input'!C$14 -> 0.015209463 | E22: ='P&L Input'!D22/'P&L Input'!D$14 -> 0.011266626 | F22: ='P&L Input'!E22/'P&L Input'!E$14 -> 0.010897772 | G22: ='P&L Input'!F22/'P&L Input'!F$14 -> 0.0099345699 | H22: ='P&L Input'!G22/'P&L Input'!G$14 -> 0.011422513
C23: Depreciation & Amortisation | D23: ='P&L Input'!C24/'P&L Input'!C$14 -> 0.72739156 | E23: ='P&L Input'!D24/'P&L Input'!D$14 -> 0.74689566 | F23: ='P&L Input'!E24/'P&L Input'!E$14 -> 0.74027188 | G23: ='P&L Input'!F24/'P&L Input'!F$14 -> 0.74286572 | H23: ='P&L Input'!G24/'P&L Input'!G$14 -> 0.74530529
C24: EBIT | D24: ='P&L Input'!C26/'P&L Input'!C$14 -> 0.27260844 | E24: ='P&L Input'!D26/'P&L Input'!D$14 -> 0.25310434 | F24: ='P&L Input'!E26/'P&L Input'!E$14 -> 0.25972812 | G24: ='P&L Input'!F26/'P&L Input'!F$14 -> 0.25713428 | H24: ='P&L Input'!G26/'P&L Input'!G$14 -> 0.25469471
C25: Other Income | D25: ='P&L Input'!C28/'P&L Input'!C$14 -> 0.028046734 | E25: ='P&L Input'!D28/'P&L Input'!D$14 -> 0.02826692 | F25: ='P&L Input'!E28/'P&L Input'!E$14 -> 0.029536371 | G25: ='P&L Input'!F28/'P&L Input'!F$14 -> 0.028885287 | H25: ='P&L Input'!G28/'P&L Input'!G$14 -> 0.026790984
C26: Finance Costs | D26: ='P&L Input'!C30/'P&L Input'!C$14 -> 0.24456171 | E26: ='P&L Input'!D30/'P&L Input'!D$14 -> 0.22483742 | F26: ='P&L Input'!E30/'P&L Input'!E$14 -> 0.23019175 | G26: ='P&L Input'!F30/'P&L Input'!F$14 -> 0.22824899 | H26: ='P&L Input'!G30/'P&L Input'!G$14 -> 0.22790372
C28: Profit before Tax
C29: Taxes | D29: ='P&L Input'!C40/'P&L Input'!C$14 -> 0.064258972 | E29: ='P&L Input'!D40/'P&L Input'!D$14 -> 0.061645302 | F29: ='P&L Input'!E40/'P&L Input'!E$14 -> 0.061497276 | G29: ='P&L Input'!F40/'P&L Input'!F$14 -> 0.065177982 | H29: ='P&L Input'!G40/'P&L Input'!G$14 -> 0.057500601
B30: Net Profit | D30: ='P&L Input'!C42/'P&L Input'!C$14 -> 0.178689 | E30: ='P&L Input'!D42/'P&L Input'!D$14 -> 0.16129205 | F30: ='P&L Input'!E42/'P&L Input'!E$14 -> 0.16572695 | G30: ='P&L Input'!F42/'P&L Input'!F$14 -> 0.16057386 | H30: ='P&L Input'!G42/'P&L Input'!G$14 -> 0.16108476
B34: ASSETS
B36: Non-Current Assets
C37: PPE | D37: ='BS Input'!D12/'BS Input'!D$39 -> 0.11091318 | E37: ='BS Input'!E12/'BS Input'!E$39 -> 0.10607554 | F37: ='BS Input'!F12/'BS Input'!F$39 -> 0.08975866 | G37: ='BS Input'!G12/'BS Input'!G$39 -> 0.079098474 | H37: ='BS Input'!H12/'BS Input'!H$39 -> 0.081113312
C38: ROU Assets | D38: ='BS Input'!D13/'BS Input'!D$39 -> 0.040912754 | E38: ='BS Input'!E13/'BS Input'!E$39 -> 0.054698925 | F38: ='BS Input'!F13/'BS Input'!F$39 -> 0.04754234 | G38: ='BS Input'!G13/'BS Input'!G$39 -> 0.042383297 | H38: ='BS Input'!H13/'BS Input'!H$39 -> 0.039604532
C39: Capital WIP | D39: ='BS Input'!D14/'BS Input'!D$39 -> 0.0035288629 | E39: ='BS Input'!E14/'BS Input'!E$39 -> 0.002289057 | F39: ='BS Input'!F14/'BS Input'!F$39 -> 0.002126054 | G39: ='BS Input'!G14/'BS Input'!G$39 -> 0.0054666461 | H39: ='BS Input'!H14/'BS Input'!H$39 -> 0.0033725083
C40: Goodwill | D40: ='BS Input'!D15/'BS Input'!D$39 -> 0.052551215 | E40: ='BS Input'!E15/'BS Input'!E$39 -> 0.057607935 | F40: ='BS Input'!F15/'BS Input'!F$39 -> 0.052991713 | G40: ='BS Input'!G15/'BS Input'!G$39 -> 0.067869687 | H40: ='BS Input'!H15/'BS Input'!H$39 -> 0.077689511
C41: Other Intangible assets | D41: ='BS Input'!D16/'BS Input'!D$39 -> 0.014480214 | E41: ='BS Input'!E16/'BS Input'!E$39 -> 0.013901253 | F41: ='BS Input'!F16/'BS Input'!F$39 -> 0.010136851 | G41: ='BS Input'!G16/'BS Input'!G$39 -> 0.018575851 | H41: ='BS Input'!H16/'BS Input'!H$39 -> 0.018112806
C42: Financial Assets
C43: Investments | D43: ='BS Input'!D18/'BS Input'!D$39 -> 0.1157993 | E43: ='BS Input'!E18/'BS Input'!E$39 -> 0.099899854 | F43: ='BS Input'!F18/'BS Input'!F$39 -> 0.084955084 | G43: ='BS Input'!G18/'BS Input'!G$39 -> 0.074269827 | H43: ='BS Input'!H18/'BS Input'!H$39 -> 0.057255702
C44: Other financial assets | D44: ='BS Input'!D20/'BS Input'!D$39 -> 0.012384951 | E44: ='BS Input'!E20/'BS Input'!E$39 -> 0.022238825 | F44: ='BS Input'!F20/'BS Input'!F$39 -> 0.022530367 | G44: ='BS Input'!G20/'BS Input'!G$39 -> 0.023579109 | H44: ='BS Input'!H20/'BS Input'!H$39 -> 0.017798637
C45: Deferred Tax Assets(net) | D45: ='BS Input'!D21/'BS Input'!D$39 -> 0.010281206 | E45: ='BS Input'!E21/'BS Input'!E$39 -> 0.0098954028 | F45: ='BS Input'!F21/'BS Input'!F$39 -> 0.0032942952 | G45: ='BS Input'!G21/'BS Input'!G$39 -> 0.0074410858 | H45: ='BS Input'!H21/'BS Input'!H$39 -> 0.014515891
C46: Income tax assets (net) | D46: ='BS Input'!D22/'BS Input'!D$39 -> 0.051728379 | E46: ='BS Input'!E22/'BS Input'!E$39 -> 0.051289184 | F46: ='BS Input'!F22/'BS Input'!F$39 -> 0.022094998 | G46: ='BS Input'!G22/'BS Input'!G$39 -> 0.010892997 | H46: ='BS Input'!H22/'BS Input'!H$39 -> 0.0042701341
C47: Other non-current assets | D47: ='BS Input'!D23/'BS Input'!D$39 -> 0.017211689 | E47: ='BS Input'!E23/'BS Input'!E$39 -> 0.01842373 | F47: ='BS Input'!F23/'BS Input'!F$39 -> 0.015390309 | G47: ='BS Input'!G23/'BS Input'!G$39 -> 0.018219915 | H47: ='BS Input'!H23/'BS Input'!H$39 -> 0.022697109
B49: Current Assets
C50: Financial Assets
C51: Investments | D51: ='BS Input'!D29/'BS Input'!D$39 -> 0.056606014 | E51: ='BS Input'!E29/'BS Input'!E$39 -> 0.054913525 | F51: ='BS Input'!F29/'BS Input'!F$39 -> 0.093713266 | G51: ='BS Input'!G29/'BS Input'!G$39 -> 0.083826384 | H51: ='BS Input'!H29/'BS Input'!H$39 -> 0.083030385
C52: Trade Receivables | D52: ='BS Input'!D30/'BS Input'!D$39 -> 0.19254358 | E52: ='BS Input'!E30/'BS Input'!E$39 -> 0.20207287 | F52: ='BS Input'!F30/'BS Input'!F$39 -> 0.21908514 | G52: ='BS Input'!G30/'BS Input'!G$39 -> 0.20925032 | H52: ='BS Input'!H30/'BS Input'!H$39 -> 0.22590676
C53: Cash & Cash Equivalents | D53: ='BS Input'!D31/'BS Input'!D$39 -> 0.14821224 | E53: ='BS Input'!E31/'BS Input'!E$39 -> 0.0967524 | F53: ='BS Input'!F31/'BS Input'!F$39 -> 0.10728954 | G53: ='BS Input'!G31/'BS Input'!G$39 -> 0.16423443 | H53: ='BS Input'!H31/'BS Input'!H$39 -> 0.14234421
C54: Other financial assets | D54: ='BS Input'!D33/'BS Input'!D$39 -> 0.074029775 | E54: ='BS Input'!E33/'BS Input'!E$39 -> 0.092229923 | F54: ='BS Input'!F33/'BS Input'!F$39 -> 0.087690656 | G54: ='BS Input'!G33/'BS Input'!G$39 -> 0.092946415 | H54: ='BS Input'!H33/'BS Input'!H$39 -> 0.10188053
C55: Other current assets | D55: ='BS Input'!D35/'BS Input'!D$39 -> 0.095966408 | E55: ='BS Input'!E35/'BS Input'!E$39 -> 0.11505691 | F55: ='BS Input'!F35/'BS Input'!F$39 -> 0.092936857 | G55: ='BS Input'!G35/'BS Input'!G$39 -> 0.08018643 | H55: ='BS Input'!H35/'BS Input'!H$39 -> 0.097103875
B57: TOTAL | D57: ='BS Input'!D39/'BS Input'!D$39 -> 1 | E57: ='BS Input'!E39/'BS Input'!E$39 -> 1 | F57: ='BS Input'!F39/'BS Input'!F$39 -> 1 | G57: ='BS Input'!G39/'BS Input'!G$39 -> 1 | H57: ='BS Input'!H39/'BS Input'!H$39 -> 1
B59: EQUITY AND LIABILITIES
B61: Shareholder Funds
C62: Equity Share Capital | D62: ='BS Input'!D44/'BS Input'!D$70 -> 0.017797006 | E62: ='BS Input'!E44/'BS Input'!E$70 -> 0.016444649 | F62: ='BS Input'!F44/'BS Input'!F$70 -> 0.015027501 | G62: ='BS Input'!G44/'BS Input'!G$70 -> 0.013921815 | H62: ='BS Input'!H44/'BS Input'!H$70 -> 0.012977104
C63: Other Equity | D63: ='BS Input'!D45/'BS Input'!D$70 -> 0.62138525 | E63: ='BS Input'!E45/'BS Input'!E$70 -> 0.58289884 | F63: ='BS Input'!F45/'BS Input'!F$70 -> 0.62435602 | G63: ='BS Input'!G45/'BS Input'!G$70 -> 0.62957093 | H63: ='BS Input'!H45/'BS Input'!H$70 -> 0.58235396
C64: Non-Controlling Interest | D64: ='BS Input'!D46/'BS Input'!D$70 -> 0.0032743776 | E64: ='BS Input'!E46/'BS Input'!E$70 -> 0.0030838685 | F64: ='BS Input'!F46/'BS Input'!F$70 -> 0.0025033741 | G64: ='BS Input'!G46/'BS Input'!G$70 -> 0.0025855758 | H64: ='BS Input'!H46/'BS Input'!H$70 -> 0.0028531677
B66: Non-current liabilities
C67: Financial Liabilities
C68: Lease Liabilities | D68: ='BS Input'!D52/'BS Input'!D$70 -> 0.039038046 | E68: ='BS Input'!E52/'BS Input'!E$70 -> 0.056089845 | F68: ='BS Input'!F52/'BS Input'!F$70 -> 0.046439404 | G68: ='BS Input'!G52/'BS Input'!G$70 -> 0.03876349 | H68: ='BS Input'!H52/'BS Input'!H$70 -> 0.038572262
C69: Other financial liabilities | D69: ='BS Input'!D53/'BS Input'!D$70 -> 0.019824405 | E69: ='BS Input'!E53/'BS Input'!E$70 -> 0.01635722 | F69: ='BS Input'!F53/'BS Input'!F$70 -> 0.015455614 | G69: ='BS Input'!G53/'BS Input'!G$70 -> 0.014378488 | H69: ='BS Input'!H53/'BS Input'!H$70 -> 0.013413094
C70: ='BS Input'!C54 -> Other non current liabilities | D70: ='BS Input'!D54/'BS Input'!D$70 -> 0.0038257624 | E70: ='BS Input'!E54/'BS Input'!E$70 -> 0.0039740574 | F70: ='BS Input'!F54/'BS Input'!F$70 -> 0.0017051969 | G70: ='BS Input'!G54/'BS Input'!G$70 -> 0.001443893 | H70: ='BS Input'!H54/'BS Input'!H$70 -> 0.0035969147
C71: Deferred Tax Liability | D71: ='BS Input'!D55/'BS Input'!D$70 -> 0.009806167 | E71: ='BS Input'!E55/'BS Input'!E$70 -> 0.0096966999 | F71: ='BS Input'!F55/'BS Input'!F$70 -> 0.013017545 | G71: ='BS Input'!G55/'BS Input'!G$70 -> 0.011564576 | H71: ='BS Input'!H55/'BS Input'!H$70 -> 0.010765098
B73: Current Liabilities
C74: Financial Liabilities
C75: Lease liabilities | D75: ='BS Input'!D61/'BS Input'!D$70 -> 0.0073970395 | E75: ='BS Input'!E61/'BS Input'!E$70 -> 0.0098715585 | F75: ='BS Input'!F61/'BS Input'!F$70 -> 0.014214811 | G75: ='BS Input'!G61/'BS Input'!G$70 -> 0.016487243 | H75: ='BS Input'!H61/'BS Input'!H$70 -> 0.020260696
C76: Trade Payables | D76: ='BS Input'!D62/'BS Input'!D$70 -> 0.035068075 | E76: ='BS Input'!E62/'BS Input'!E$70 -> 0.030719463 | F76: ='BS Input'!F62/'BS Input'!F$70 -> 0.028705356 | G76: ='BS Input'!G62/'BS Input'!G$70 -> 0.027964514 | H76: ='BS Input'!H62/'BS Input'!H$70 -> 0.030416691
C77: Other Financial liabilities | D77: ='BS Input'!D63/'BS Input'!D$70 -> 0.13434279 | E77: ='BS Input'!E63/'BS Input'!E$70 -> 0.14750111 | F77: ='BS Input'!F63/'BS Input'!F$70 -> 0.12305716 | G77: ='BS Input'!G63/'BS Input'!G$70 -> 0.12181084 | H77: ='BS Input'!H63/'BS Input'!H$70 -> 0.13774068
C78: Other current liabilities | D78: ='BS Input'!D64/'BS Input'!D$70 -> 0.077855537 | E78: ='BS Input'!E64/'BS Input'!E$70 -> 0.086078082 | F78: ='BS Input'!F64/'BS Input'!F$70 -> 0.076472637 | G78: ='BS Input'!G64/'BS Input'!G$70 -> 0.079011168 | H78: ='BS Input'!H64/'BS Input'!H$70 -> 0.10116884
C79: Provisions | D79: ='BS Input'!D65/'BS Input'!D$70 -> 0.0082707724 | E79: ='BS Input'!E65/'BS Input'!E$70 -> 0.010388186 | F79: ='BS Input'!F65/'BS Input'!F$70 -> 0.013032058 | G79: ='BS Input'!G65/'BS Input'!G$70 -> 0.0099057776 | H79: ='BS Input'!H65/'BS Input'!H$70 -> 0.0096943584
C80: Current Tax Liabilities(net) | D80: ='BS Input'!D66/'BS Input'!D$70 -> 0.022114773 | E80: ='BS Input'!E66/'BS Input'!E$70 -> 0.02689642 | F80: ='BS Input'!F66/'BS Input'!F$70 -> 0.026013322 | G80: ='BS Input'!G66/'BS Input'!G$70 -> 0.032591687 | H80: ='BS Input'!H66/'BS Input'!H$70 -> 0.036187142
B82: TOTAL | D82: ='BS Input'!D70/'BS Input'!D$70 -> 1 | E82: ='BS Input'!E70/'BS Input'!E$70 -> 1 | F82: ='BS Input'!F70/'BS Input'!F$70 -> 1 | G82: ='BS Input'!G70/'BS Input'!G$70 -> 1 | H82: ='BS Input'!H70/'BS Input'!H$70 -> 1

Sheet Revenue Buildup
B2: Infosys Limited
P6: (INR in Crores)
B7: Revenue Buildup
B8: Particulars | C8: 2022 | D8: =C8+1 -> 2023 | E8: =D8+1 -> 2024 | F8: =E8+1 -> 2025 | G8: =F8+1 -> 2026 | H8: =G8+1 -> 2027 | I8: =H8+1 -> 2028 | J8: =I8+1 -> 2029 | K8: =J8+1 -> 2030 | ... Q8: =P8+1 -> 2036
C9: Audited | D9: Audited | E9: Audited | F9: Audited | G9: Audited | H9: Estimated | I9: Projected | J9: Projected | K9: Projected | L9: Projected | M9: Projected | N9: Projected | O9: Projected | P9: Projected | Q9: Projected
B11: Sale of Service | C11: =C15-C12 -> 113536 | D11: =D15-D12 -> 137575 | E11: =E15-E12 -> 145285 | F11: =F15-F12 -> 155395 | G11: =G15-G12 -> 170122 | H11: =H15-H12 -> 184226.18 | I11: =I15-I12 -> 201780.73 | J11: =J15-J12 -> 219161.02 | ... Q11: =Q15-Q12 -> 309346.78
B12: Other Operating Revenues | C12: 8105 | D12: 9192 | E12: 8385 | F12: 7595 | G12: 8528 | H12: =H$13*H$28 -> 11547.509 | I12: =I$13*I$28 -> 12647.848 | J12: =J$13*J$28 -> 13737.265 | K12: =K$13*K$28 -> 14796.293 | L12: =L$13*L$28 -> 15804.64 | M12: =M$13*M$28 -> 16741.738 | N12: =N$13*N$28 -> 17587.332 | O12: =O$13*O$28 -> 18322.1 | ... Q12: =Q$13*Q$28 -> 19390.212
B13: (% on total Revenue) | C13: =C$12/C$11 -> 0.071387049 | D13: =D$12/D$11 -> 0.066814465 | E13: =E$12/E$11 -> 0.057714148 | F13: =F$12/F$11 -> 0.048875446 | G13: =G$12/G$11 -> 0.050128731 | H13: =AVERAGE(C13:G13) -> 0.058983968 | I13: =H13 -> 0.058983968 | J13: =I13 -> 0.058983968 | K13: =J13 -> 0.058983968 | L13: =K13 -> 0.058983968 | M13: =L13 -> 0.058983968 | N13: =M13 -> 0.058983968 | O13: =N13 -> 0.058983968 | P13: =O13 -> 0.058983968 | Q13: =P13 -> 0.058983968
B15: Revenue from Operations | C15: =C62 -> 121641 | D15: =D62 -> 146767 | E15: =E62 -> 153670 | F15: =F62 -> 162990 | G15: =G62 -> 178650 | H15: =H28 -> 195773.69 | I15: =I28 -> 214428.58 | J15: =J28 -> 232898.28 | K15: =K28 -> 250852.79 | L15: =L28 -> 267948.07 | M15: =M28 -> 283835.39 | N15: =N28 -> 298171.4 | O15: =O28 -> 310628.48 | ... Q15: =Q28 -> 328737
B16: Y-O-Y Growth | D16: =D15/C15-1 -> 0.20655864 | E16: =E15/D15-1 -> 0.047033734 | F16: =F15/E15-1 -> 0.060649444 | G16: =G15/F15-1 -> 0.096079514 | H16: =H15/G15-1 -> 0.095850477 | I16: =I15/H15-1 -> 0.095288044 | J16: =J15/I15-1 -> 0.086134516 | K16: =K15/J15-1 -> 0.077091624 | ... Q16: =Q15/P15-1 -> 0.024405003
B18: Other Income | C18: 2295 | D18: 2701 | E18: 4711 | F18: 3600 | G18: 4322 | H18: =H11*H19 -> 4452.554 | I18: =I11*I19 -> 4876.8291 | J18: =J11*J19 -> 5296.8924 | K18: =K11*K19 -> 5705.2385 | L18: =L11*L19 -> 6094.0427 | M18: =M11*M19 -> 6455.3741 | N18: =N11*N19 -> 6781.4232 | O18: =O11*O19 -> 7064.7393 | ... Q18: =Q11*Q19 -> 7476.5881
C19: =C18/C11 -> 0.020213853 | D19: =D18/D11 -> 0.019632927 | E19: =E18/E11 -> 0.032425921 | F19: =F18/F11 -> 0.023166769 | G19: =G18/G11 -> 0.025405297 | H19: =AVERAGE(C19:G19) -> 0.024168954 | I19: =H19 -> 0.024168954 | J19: =I19 -> 0.024168954 | K19: =J19 -> 0.024168954 | L19: =K19 -> 0.024168954 | M19: =L19 -> 0.024168954 | N19: =M19 -> 0.024168954 | O19: =N19 -> 0.024168954 | P19: =O19 -> 0.024168954 | Q19: =P19 -> 0.024168954
B22: Exceptional Items | C22: 0 | D22: 0 | E22: 0 | F22: 0 | G22: 1289 | H22: =H23*H11 -> 465.28872 | I22: =I23*I11 -> 509.62518 | J22: =J23*J11 -> 553.52149 | K22: =K23*K11 -> 596.19336 | L22: =L23*L11 -> 636.82313 | M22: =M23*M11 -> 674.582 | N22: =N23*N11 -> 708.6539 | O22: =O23*O11 -> 738.26024 | ... Q22: =Q23*Q11 -> 781.29814
C23: =C22/C11 -> 0 | D23: =D22/D11 -> 0 | E23: =E22/E11 -> 0 | F23: =F22/F11 -> 0 | G23: =G22/G11 -> 0.0075769154 | H23: =AVERAGE(E23:G23) -> 0.0025256385 | I23: =H23 -> 0.0025256385 | J23: =I23 -> 0.0025256385 | K23: =J23 -> 0.0025256385 | L23: =K23 -> 0.0025256385 | M23: =L23 -> 0.0025256385 | N23: =M23 -> 0.0025256385 | O23: =N23 -> 0.0025256385 | P23: =O23 -> 0.0025256385 | Q23: =P23 -> 0.0025256385
B24: Revenue by Geographies
B25: North America | C25: 0.617045 | D25: 0.61815 | E25: 0.60136 | F25: 0.579158 | G25: 0.560688 | H25: =$J$32*H$28 -> 109767.96 | I25: =$J$32*I$28 -> 120227.53 | J25: =$J$32*J$28 -> 130583.27 | K25: =$J$32*K$28 -> 140650.15 | L25: =$J$32*L$28 -> 150235.26 | M25: =$J$32*M$28 -> 159143.1 | N25: =$J$32*N$28 -> 167181.12 | O25: =$J$32*O$28 -> 174165.66 | ... Q25: =$J$32*Q$28 -> 184318.89
B26: Europe | C26: 0.247688 | D26: 0.256699 | E26: 0.27505 | F26: 0.298147 | G26: 0.321601 | H26: =$J$33*H$28 -> 62961.014 | I26: =$J$33*I$28 -> 68960.446 | J26: =$J$33*J$28 -> 74900.32 | K26: =$J$33*K$28 -> 80674.508 | L26: =$J$33*L$28 -> 86172.366 | M26: =$J$33*M$28 -> 91281.746 | N26: =$J$33*N$28 -> 95892.219 | O26: =$J$33*O$28 -> 99898.43 | ... Q26: =$J$33*Q$28 -> 105722.15
B27: Rest of the World* | C27: 0.135267 | D27: 0.125151 | E27: 0.12359 | F27: 0.122695 | G27: 0.117711 | H27: =$J$34*H$28 -> 26481.719 | I27: =$J$34*I$28 -> 29005.111 | J27: =$J$34*J$28 -> 31503.452 | K27: =$J$34*K$28 -> 33932.104 | L27: =$J$34*L$28 -> 36244.531 | M27: =$J$34*M$28 -> 38393.562 | N27: =$J$34*N$28 -> 40332.75 | O27: =$J$34*O$28 -> 42017.783 | ... Q27: =$J$34*Q$28 -> 44467.267
C28: =C15 -> 121641 | D28: =D15 -> 146767 | E28: =E15 -> 153670 | F28: =F15 -> 162990 | G28: =G15 -> 178650 | H28: =H62 -> 195773.69 | I28: =I62 -> 214428.58 | J28: =J62 -> 232898.28 | K28: =K62 -> 250852.79 | L28: =L62 -> 267948.07 | M28: =M62 -> 283835.39 | N28: =N62 -> 298171.4 | O28: =O62 -> 310628.48 | ... Q28: =Q62 -> 328737
B31: IT Sector Growth Projection | C31: United Kingdom | E31: North America | G31: AMEA | H31: Min Growth | J31: Revenue Segment By geography
B32: Digital & Application Engineering | C32: 0.0471 | E32: 0.0377 | G32: 0.0483 | H32: =MIN(C32:G32) -> 0.0377 | J32: =MIN(C25:G25) -> 0.560688
B33: Oracle Cloud & Enterprise Apps | C33: 0.1243 | E33: 0.153 | G33: 0.2094 | H33: =MIN(C33:G33) -> 0.1243 | J33: =MAX(C26:G26) -> 0.321601
B34: Digital Commerce & Experience | C34: 0.0483 | E34: 0.0338 | G34: 0.0584 | H34: =MIN(C34:G34) -> 0.0338 | J34: =MAX(C27:G27) -> 0.135267
B35: Data, Automation and AI | C35: 0.2633 | E35: 0.2688 | G35: 0.2661 | H35: =MIN(C35:G35) -> 0.2633
B37: Revenue by Geography | C37: 2022 | D37: 2023 | E37: 2024 | F37: 2025 | G37: 2026 | H37: 2027 | I37: 2028 | J37: 2029 | K37: 2030 | L37: 2031 | M37: 2032 | N37: 2033 | O37: 2034 | P37: 2035 | Q37: 2036
B38: North America | C38: 75058 | D38: 90724 | E38: 92411 | F38: 94397 | G38: 100167 | H38: =G38*(1+H$39) -> 106726.17 | I38: =H38*(1+I$39) -> 112697.6 | J38: =I38*(1+J$39) -> 117650.77 | K38: =J38*(1+K$39) -> 121409.83 | L38: =K38*(1+L$39) -> 123832.08 | M38: =L38*(1+M$39) -> 124816.66 | N38: =M38*(1+N$39) -> 124311.28 | O38: =N38*(1+O$39) -> 122316.21 | ... Q38: =P38*(1+Q$39) -> 114124.12
D39: =D38/C38-1 -> 0.20871859 | E39: =E38/D38-1 -> 0.018594859 | F39: =F38/E38-1 -> 0.021490948 | G39: =G38/F38-1 -> 0.061124824 | H39: {=CHOOSE(Assumptions!D17,'Revenue Buildup'!H40:Q40,'Revenue Buildup'!H41:Q41,'Revenue Buildup'!H42:Q42)} -> 0.065482306 | I39: 0.055950988 | J39: 0.043950988 | K39: 0.031950988 | L39: 0.019950988 | M39: 0.0079509884 | N39: -0.0040490116 | O39: -0.016049012 | P39: -0.028049012 | Q39: -0.040049012
H40: =H41+0.05 -> 0.11548231 | I40: =I41+MAX(0,(H40-H41)-Assumptions!$D$32) -> 0.095950988 | J40: =J41+MAX(0,(I40-I41)-Assumptions!$D$32) -> 0.073950988 | K40: =K41+MAX(0,(J40-J41)-Assumptions!$D$32) -> 0.051950988 | L40: =L41+MAX(0,(K40-K41)-Assumptions!$D$32) -> 0.029950988 | M40: =M41+MAX(0,(L40-L41)-Assumptions!$D$32) -> 0.0079509884 | N40: =N41+MAX(0,(M40-M41)-Assumptions!$D$32) -> -0.0040490116 | O40: =O41+MAX(0,(N40-N41)-Assumptions!$D$32) -> -0.016049012 | P40: =P41+MAX(0,(O40-O41)-Assumptions!$D$32) -> -0.028049012 | Q40: =Q41+MAX(0,(P40-P41)-Assumptions!$D$32) -> -0.040049012
H41: =AVERAGE(D39:G39)-0.012 -> 0.065482306 | I41: =(H41*(1+$H$32))-0.012 -> 0.055950988 | J41: =I41-0.012 -> 0.043950988 | K41: =J41-0.012 -> 0.031950988 | L41: =K41-0.012 -> 0.019950988 | M41: =L41-0.012 -> 0.0079509884 | N41: =M41-0.012 -> -0.0040490116 | O41: =N41-0.012 -> -0.016049012 | P41: =O41-0.012 -> -0.028049012 | Q41: =P41-0.012 -> -0.040049012
H42: =H41-0.05 -> 0.015482306 | I42: =I41-0.05 -> 0.0059509884 | J42: =J41-0.05 -> -0.0060490116 | K42: =K41-0.05 -> -0.018049012 | L42: =L41-0.05 -> -0.030049012 | M42: =M41-0.05 -> -0.042049012 | N42: =N41-0.05 -> -0.054049012 | O42: =O41-0.05 -> -0.066049012 | ... Q42: =Q41-0.05 -> -0.090049012
B44: Europe | C44: 30129 | D44: 37675 | E44: 42267 | F44: 48595 | G44: 57454 | H44: =G44*(1+H$45) -> 66881.606 | I44: =H44*(1+I$45) -> 78417.744 | J44: =I44*(1+J$45) -> 91002.692 | K44: =J44*(1+K$45) -> 104515.32 | L44: =K44*(1+L$45) -> 118780.19 | M44: =L44*(1+M$45) -> 133566.66 | N44: =M44*(1+N$45) -> 148591.03 | O44: =N44*(1+O$45) -> 163522.35 | ... Q44: =P44*(1+Q$45) -> 191605.66
D45: =D44/C44-1 -> 0.25045637 | E45: =E44/D44-1 -> 0.12188454 | F45: =F44/E44-1 -> 0.14971491 | G45: =G44/F44-1 -> 0.18230271 | H45: {=CHOOSE(Assumptions!D17,'Revenue Buildup'!H46:Q46,'Revenue Buildup'!H47:Q47,'Revenue Buildup'!H48:Q48)} -> 0.16408963 | I45: 0.17248597 | J45: 0.16048597 | K45: 0.14848597 | L45: 0.13648597 | M45: 0.12448597 | N45: 0.11248597 | O45: 0.10048597 | P45: 0.088485972 | Q45: 0.076485972
H46: =H47+0.05 -> 0.21408963 | I46: =I47+MAX(0,(H46-H47)-Assumptions!$D$32) -> 0.21248597 | J46: =J47+MAX(0,(I46-I47)-Assumptions!$D$32) -> 0.19048597 | K46: =K47+MAX(0,(J46-J47)-Assumptions!$D$32) -> 0.16848597 | L46: =L47+MAX(0,(K46-K47)-Assumptions!$D$32) -> 0.14648597 | M46: =M47+MAX(0,(L46-L47)-Assumptions!$D$32) -> 0.12448597 | N46: =N47+MAX(0,(M46-M47)-Assumptions!$D$32) -> 0.11248597 | O46: =O47+MAX(0,(N46-N47)-Assumptions!$D$32) -> 0.10048597 | P46: =P47+MAX(0,(O46-O47)-Assumptions!$D$32) -> 0.088485972 | Q46: =Q47+MAX(0,(P46-P47)-Assumptions!$D$32) -> 0.076485972
H47: =AVERAGE(D45:G45)-0.012 -> 0.16408963 | I47: =(H47*(1+$H$33))-0.012 -> 0.17248597 | J47: =I47-0.012 -> 0.16048597 | K47: =J47-0.012 -> 0.14848597 | L47: =K47-0.012 -> 0.13648597 | M47: =L47-0.012 -> 0.12448597 | N47: =M47-0.012 -> 0.11248597 | O47: =N47-0.012 -> 0.10048597 | P47: =O47-0.012 -> 0.088485972 | Q47: =P47-0.012 -> 0.076485972
H48: =H47-0.05 -> 0.11408963 | I48: =I47-0.05 -> 0.12248597 | J48: =J47-0.05 -> 0.11048597 | K48: =K47-0.05 -> 0.098485972 | L48: =L47-0.05 -> 0.086485972 | M48: =M47-0.05 -> 0.074485972 | N48: =N47-0.05 -> 0.062485972 | O48: =O47-0.05 -> 0.050485972 | ... Q48: =Q47-0.05 -> 0.026485972
B50: India | C50: 3585 | D50: 3861 | E50: 3881 | F50: 5014 | G50: 5102 | H50: =G50*(1+H$51) -> 5540.3299 | I50: =H50*(1+I$51) -> 5965.9226 | J50: =I50*(1+J$51) -> 6352.6171 | K50: =J50*(1+K$51) -> 6688.1446 | L50: =K50*(1+L$51) -> 6961.1361 | M50: =L50*(1+M$51) -> 7161.7366 | N50: =M50*(1+N$51) -> 7282.1771 | O50: =N50*(1+O$51) -> 7317.2569 | ... Q50: =P50*(1+Q$51) -> 7125.3415
D51: =D50/C50-1 -> 0.076987448 | E51: =E50/D50-1 -> 0.0051800052 | F51: =F50/E50-1 -> 0.29193507 | G51: =G50/F50-1 -> 0.017550858 | H51: {=CHOOSE(Assumptions!D17,'Revenue Buildup'!H52:Q52,'Revenue Buildup'!H53:Q53,'Revenue Buildup'!H54:Q54)} -> 0.085913345 | I51: 0.076817216 | J51: 0.064817216 | K51: 0.052817216 | L51: 0.040817216 | M51: 0.028817216 | N51: 0.016817216 | O51: 0.0048172157 | P51: -0.0071827843 | Q51: -0.019182784
H52: =H53+0.05 -> 0.13591334 | I52: =I53+MAX(0,(H52-H53)-Assumptions!$D$32) -> 0.11681722 | J52: =J53+MAX(0,(I52-I53)-Assumptions!$D$32) -> 0.094817216 | K52: =K53+MAX(0,(J52-J53)-Assumptions!$D$32) -> 0.072817216 | L52: =L53+MAX(0,(K52-K53)-Assumptions!$D$32) -> 0.050817216 | M52: =M53+MAX(0,(L52-L53)-Assumptions!$D$32) -> 0.028817216 | N52: =N53+MAX(0,(M52-M53)-Assumptions!$D$32) -> 0.016817216 | O52: =O53+MAX(0,(N52-N53)-Assumptions!$D$32) -> 0.0048172157 | P52: =P53+MAX(0,(O52-O53)-Assumptions!$D$32) -> -0.0071827843 | Q52: =Q53+MAX(0,(P52-P53)-Assumptions!$D$32) -> -0.019182784
H53: =AVERAGE(D51:G51)-0.012 -> 0.085913345 | I53: =(H53*(1+$H$34))-0.012 -> 0.076817216 | J53: =I53-0.012 -> 0.064817216 | K53: =J53-0.012 -> 0.052817216 | L53: =K53-0.012 -> 0.040817216 | M53: =L53-0.012 -> 0.028817216 | N53: =M53-0.012 -> 0.016817216 | O53: =N53-0.012 -> 0.0048172157 | P53: =O53-0.012 -> -0.0071827843 | Q53: =P53-0.012 -> -0.019182784
H54: =H53-0.05 -> 0.035913345 | I54: =I53-0.05 -> 0.026817216 | J54: =J53-0.05 -> 0.014817216 | K54: =K53-0.05 -> 0.0028172157 | L54: =L53-0.05 -> -0.0091827843 | M54: =M53-0.05 -> -0.021182784 | N54: =N53-0.05 -> -0.033182784 | O54: =O53-0.05 -> -0.045182784 | ... Q54: =Q53-0.05 -> -0.069182784
B56: Rest of the World | C56: 12869 | D56: 14507 | E56: 15111 | F56: 14984 | G56: 15927 | H56: =G56*(1+H$57) -> 16625.586 | I56: =H56*(1+I$57) -> 17347.312 | J56: =I56*(1+J$57) -> 17892.201 | K56: =J56*(1+K$57) -> 18239.498 | L56: =K56*(1+L$57) -> 18374.663 | M56: =L56*(1+M$57) -> 18290.333 | N56: =M56*(1+N$57) -> 17986.907 | O56: =N56*(1+O$57) -> 17472.671 | ... Q56: =P56*(1+Q$57) -> 15881.884
D57: =D56/C56-1 -> 0.12728262 | E57: =E56/D56-1 -> 0.041635073 | F57: =F56/E56-1 -> -0.0084044736 | G57: =G56/F56-1 -> 0.062933796 | H57: {=CHOOSE(Assumptions!D17,'Revenue Buildup'!H58:Q58,'Revenue Buildup'!H59:Q59,'Revenue Buildup'!H60:Q60)} -> 0.043861753 | I57: 0.043410553 | J57: 0.031410553 | K57: 0.019410553 | L57: 0.0074105527 | M57: -0.0045894473 | N57: -0.016589447 | O57: -0.028589447 | P57: -0.040589447 | Q57: -0.052589447
H58: =H59+0.05 -> 0.093861753 | I58: =I59+MAX(0,(H58-H59)-Assumptions!$D$32) -> 0.083410553 | J58: =J59+MAX(0,(I58-I59)-Assumptions!$D$32) -> 0.061410553 | K58: =K59+MAX(0,(J58-J59)-Assumptions!$D$32) -> 0.039410553 | L58: =L59+MAX(0,(K58-K59)-Assumptions!$D$32) -> 0.017410553 | M58: =M59+MAX(0,(L58-L59)-Assumptions!$D$32) -> -0.0045894473 | N58: =N59+MAX(0,(M58-M59)-Assumptions!$D$32) -> -0.016589447 | O58: =O59+MAX(0,(N58-N59)-Assumptions!$D$32) -> -0.028589447 | P58: =P59+MAX(0,(O58-O59)-Assumptions!$D$32) -> -0.040589447 | Q58: =Q59+MAX(0,(P58-P59)-Assumptions!$D$32) -> -0.052589447
H59: =AVERAGE(D57:G57)-0.012 -> 0.043861753 | I59: =(H59*(1+$H$35))-0.012 -> 0.043410553 | J59: =I59-0.012 -> 0.031410553 | K59: =J59-0.012 -> 0.019410553 | L59: =K59-0.012 -> 0.0074105527 | M59: =L59-0.012 -> -0.0045894473 | N59: =M59-0.012 -> -0.016589447 | O59: =N59-0.012 -> -0.028589447 | P59: =O59-0.012 -> -0.040589447 | Q59: =P59-0.012 -> -0.052589447
H60: =H59-0.05 -> -0.0061382469 | I60: =I59-0.05 -> -0.0065894473 | J60: =J59-0.05 -> -0.018589447 | K60: =K59-0.05 -> -0.030589447 | L60: =L59-0.05 -> -0.042589447 | M60: =M59-0.05 -> -0.054589447 | N60: =N59-0.05 -> -0.066589447 | O60: =O59-0.05 -> -0.078589447 | ... Q60: =Q59-0.05 -> -0.10258945
C62: =SUM(C38,C44,C50,C56) -> 121641 | D62: =SUM(D38,D44,D50,D56) -> 146767 | E62: =SUM(E38,E44,E50,E56) -> 153670 | F62: =SUM(F38,F44,F50,F56) -> 162990 | G62: =SUM(G38,G44,G50,G56) -> 178650 | H62: =SUM(H38,H44,H50,H56) -> 195773.69 | I62: =SUM(I38,I44,I50,I56) -> 214428.58 | J62: =SUM(J38,J44,J50,J56) -> 232898.28 | ... Q62: =SUM(Q38,Q44,Q50,Q56) -> 328737

Sheet Cost Buildup
B2: Infosys Limited
P6: (INR in Crores)
B7: Cost Build-up
B8: Particulars | C8: ='Revenue Buildup'!C8 -> 2022 | D8: ='Revenue Buildup'!D8 -> 2023 | E8: ='Revenue Buildup'!E8 -> 2024 | F8: ='Revenue Buildup'!F8 -> 2025 | G8: ='Revenue Buildup'!G8 -> 2026 | H8: ='Revenue Buildup'!H8 -> 2027 | I8: ='Revenue Buildup'!I8 -> 2028 | J8: ='Revenue Buildup'!J8 -> 2029 | ... Q8: ='Revenue Buildup'!Q8 -> 2036
C9: Audited | D9: Audited | E9: Audited | F9: Audited | G9: Audited | H9: Estimated | I9: Projected | J9: Projected | K9: Projected | L9: Projected | M9: Projected | N9: Projected | O9: Projected | P9: Projected | Q9: Projected
B11: ='Revenue Buildup'!B15 -> Revenue from Operations | C11: ='Revenue Buildup'!C15 -> 121641 | D11: ='Revenue Buildup'!D15 -> 146767 | E11: ='Revenue Buildup'!E15 -> 153670 | F11: ='Revenue Buildup'!F15 -> 162990 | G11: ='Revenue Buildup'!G15 -> 178650 | H11: ='Revenue Buildup'!H15 -> 195773.69 | I11: ='Revenue Buildup'!I15 -> 214428.58 | ... Q11: ='Revenue Buildup'!Q15 -> 328737
B13: Employee Benefit Expenses | C13: ='P&L Input'!C17 -> 63986 | D13: ='P&L Input'!D17 -> 78359 | E13: ='P&L Input'!E17 -> 82620 | F13: ='P&L Input'!F17 -> 85950 | G13: ='P&L Input'!G17 -> 95094 | H13: =H11*H14 -> 104041.76 | I13: =I11*I14 -> 113955.7 | J13: =J11*J14 -> 123771.22 | K13: =K11*K14 -> 133312.94 | L13: =L11*L14 -> 142398.04 | M13: =M11*M14 -> 150841.18 | N13: =N11*N14 -> 158459.89 | O13: =O11*O14 -> 165080.07 | ... Q13: =Q11*Q14 -> 174703.64
C14: =C13/C$11 -> 0.5260233 | D14: =D13/D$11 -> 0.53390067 | E14: =E13/E$11 -> 0.5376456 | F14: =F13/F$11 -> 0.52733297 | G14: =G13/G$11 -> 0.53229219 | H14: =AVERAGE(C14:G14) -> 0.53143895 | I14: =H14 -> 0.53143895 | J14: =I14 -> 0.53143895 | K14: =J14 -> 0.53143895 | L14: =K14 -> 0.53143895 | M14: =L14 -> 0.53143895 | N14: =M14 -> 0.53143895 | O14: =N14 -> 0.53143895 | P14: =O14 -> 0.53143895 | Q14: =P14 -> 0.53143895
B16: ='P&L Input'!B18 -> Cost of technical sub-contractors | C16: ='P&L Input'!C18 -> 12606 | D16: ='P&L Input'!D18 -> 14062 | E16: ='P&L Input'!E18 -> 12232 | F16: ='P&L Input'!F18 -> 12937 | G16: ='P&L Input'!G18 -> 15421 | H16: =H11*H17 -> 17413.532 | I16: =I11*I17 -> 19072.834 | J16: =J11*J17 -> 20715.663 | K16: =K11*K17 -> 22312.667 | L16: =L11*L17 -> 23833.245 | M16: =M11*M17 -> 25246.379 | N16: =N11*N17 -> 26521.527 | O16: =O11*O17 -> 27629.551 | ... Q16: =Q11*Q17 -> 29240.254
C17: =C16/C$11 -> 0.10363282 | D17: =D16/D$11 -> 0.095811729 | E17: =E16/E$11 -> 0.079599141 | F17: =F16/F$11 -> 0.079372968 | G17: =G16/G$11 -> 0.086319619 | H17: =AVERAGE(C17:G17) -> 0.088947256 | I17: =H17 -> 0.088947256 | J17: =I17 -> 0.088947256 | K17: =J17 -> 0.088947256 | L17: =K17 -> 0.088947256 | M17: =L17 -> 0.088947256 | N17: =M17 -> 0.088947256 | O17: =N17 -> 0.088947256 | P17: =O17 -> 0.088947256 | Q17: =P17 -> 0.088947256
B19: ='P&L Input'!B19 -> Travel expenses | C19: ='P&L Input'!C19 -> 827 | D19: ='P&L Input'!D19 -> 1525 | E19: ='P&L Input'!E19 -> 1759 | F19: ='P&L Input'!F19 -> 1894 | G19: ='P&L Input'!G19 -> 2097 | H19: =H11*H20 -> 2035.8232 | I19: =I11*I20 -> 2229.8128 | J19: =J11*J20 -> 2421.8766 | K19: =K11*K20 -> 2608.583 | L19: =L11*L20 -> 2786.3544 | M19: =M11*M20 -> 2951.5645 | N19: =N11*N20 -> 3100.6426 | O19: =O11*O20 -> 3230.1821 | ... Q19: =Q11*Q20 -> 3418.49
C20: =C19/C$11 -> 0.0067986945 | D20: =D19/D$11 -> 0.010390619 | E20: =E19/E$11 -> 0.011446606 | F20: =F19/F$11 -> 0.011620345 | G20: =G19/G$11 -> 0.011738035 | H20: =AVERAGE(C20:G20) -> 0.01039886 | I20: =H20 -> 0.01039886 | J20: =I20 -> 0.01039886 | K20: =J20 -> 0.01039886 | L20: =K20 -> 0.01039886 | M20: =L20 -> 0.01039886 | N20: =M20 -> 0.01039886 | O20: =N20 -> 0.01039886 | P20: =O20 -> 0.01039886 | Q20: =P20 -> 0.01039886
B22: ='P&L Input'!B20 -> Cost of software packages and others | C22: ='P&L Input'!C20 -> 6811 | D22: ='P&L Input'!D20 -> 10902 | E22: ='P&L Input'!E20 -> 13515 | F22: ='P&L Input'!F20 -> 15911 | G22: ='P&L Input'!G20 -> 15722 | H22: =H11*H23 -> 15812.476 | I22: =I11*I23 -> 17319.216 | J22: =J11*J23 -> 18810.999 | K22: =K11*K23 -> 20261.169 | L22: =L11*L23 -> 21641.94 | M22: =M11*M23 -> 22925.146 | N22: =N11*N23 -> 24083.053 | O22: =O11*O23 -> 25089.202 | ... Q22: =Q11*Q23 -> 26551.811
C23: =C22/C$11 -> 0.055992634 | D23: =D22/D$11 -> 0.074281003 | E23: =E22/E$11 -> 0.087948201 | F23: =F22/F$11 -> 0.097619486 | G23: =G22/G$11 -> 0.088004478 | H23: =AVERAGE(C23:G23) -> 0.08076916 | I23: =H23 -> 0.08076916 | J23: =I23 -> 0.08076916 | K23: =J23 -> 0.08076916 | L23: =K23 -> 0.08076916 | M23: =L23 -> 0.08076916 | N23: =M23 -> 0.08076916 | O23: =N23 -> 0.08076916 | P23: =O23 -> 0.08076916 | Q23: =P23 -> 0.08076916
B25: ='P&L Input'!B21 -> Communication expenses | C25: ='P&L Input'!C21 -> 611 | D25: ='P&L Input'!D21 -> 713 | E25: ='P&L Input'!E21 -> 677 | F25: ='P&L Input'!F21 -> 620 | G25: ='P&L Input'!G21 -> 603 | H25: =H26*H11 -> 840.48742 | I25: =I26*I11 -> 920.57583 | J25: =J26*J11 -> 999.86918 | K25: =K26*K11 -> 1076.9507 | L25: =L26*L11 -> 1150.3434 | M25: =M26*M11 -> 1218.5503 | N25: =N26*N11 -> 1280.097 | O25: =O26*O11 -> 1333.5772 | ... Q25: =Q26*Q11 -> 1411.32
C26: =C25/C$11 -> 0.0050229775 | D26: =D25/D$11 -> 0.0048580403 | E26: =E25/E$11 -> 0.0044055443 | F26: =F25/F$11 -> 0.0038039144 | G26: =G25/G$11 -> 0.0033753149 | H26: =AVERAGE(C26:G26) -> 0.0042931583 | I26: =H26 -> 0.0042931583 | J26: =I26 -> 0.0042931583 | K26: =J26 -> 0.0042931583 | L26: =K26 -> 0.0042931583 | M26: =L26 -> 0.0042931583 | N26: =M26 -> 0.0042931583 | O26: =N26 -> 0.0042931583 | P26: =O26 -> 0.0042931583 | Q26: =P26 -> 0.0042931583
B28: ='P&L Input'!B22 -> Consultancy and professional charges | C28: ='P&L Input'!C22 -> 1885 | D28: ='P&L Input'!D22 -> 1684 | E28: ='P&L Input'!E22 -> 1726 | F28: ='P&L Input'!F22 -> 1655 | G28: ='P&L Input'!G22 -> 2090 | H28: =H11*H29 -> 2351.4416 | I28: =I11*I29 -> 2575.5059 | J28: =J11*J29 -> 2797.3459 | K28: =K11*K29 -> 3012.9978 | L28: =L11*L29 -> 3218.3295 | M28: =M11*M29 -> 3409.1525 | N28: =N11*N29 -> 3581.3425 | O28: =O11*O29 -> 3730.9648 | ... Q28: =Q11*Q29 -> 3948.4666
C29: =C28/C$11 -> 0.01549642 | D29: =D28/D$11 -> 0.011473969 | E29: =E28/E$11 -> 0.01123186 | F29: =F28/F$11 -> 0.010153997 | G29: =G28/G$11 -> 0.011698853 | H29: =AVERAGE(C29:G29) -> 0.01201102 | I29: =H29 -> 0.01201102 | J29: =I29 -> 0.01201102 | K29: =J29 -> 0.01201102 | L29: =K29 -> 0.01201102 | M29: =L29 -> 0.01201102 | N29: =M29 -> 0.01201102 | O29: =N29 -> 0.01201102 | P29: =O29 -> 0.01201102 | Q29: =P29 -> 0.01201102
B31: Other Expenses | C31: ='P&L Input'!C23 -> 3424 | D31: ='P&L Input'!D23 -> 4392 | E31: ='P&L Input'!E23 -> 4716 | F31: ='P&L Input'!F23 -> 4787 | G31: ='P&L Input'!G23 -> 5343 | H31: =H11*H32 -> 5796.47 | I31: =I11*I32 -> 6348.8042 | J31: =J11*J32 -> 6895.6554 | K31: =K11*K32 -> 7427.2527 | L31: =L11*L32 -> 7933.4099 | M31: =M11*M32 -> 8403.802 | N31: =N11*N32 -> 8828.2627 | O31: =O11*O32 -> 9197.0922 | ... Q31: =Q11*Q32 -> 9733.2494
C32: =C31/C$11 -> 0.028148404 | D32: =D31/D$11 -> 0.029924983 | E32: =E31/E$11 -> 0.030689139 | F32: =F31/F$11 -> 0.0293699 | G32: =G31/G$11 -> 0.029907641 | H32: =AVERAGE(C32:G32) -> 0.029608013 | I32: =H32 -> 0.029608013 | J32: =I32 -> 0.029608013 | K32: =J32 -> 0.029608013 | L32: =K32 -> 0.029608013 | M32: =L32 -> 0.029608013 | N32: =M32 -> 0.029608013 | O32: =N32 -> 0.029608013 | P32: =O32 -> 0.029608013 | Q32: =P32 -> 0.029608013
B34: Finance Costs | C34: ='P&L Input'!C32 -> 200 | D34: ='P&L Input'!D32 -> 284 | E34: ='P&L Input'!E32 -> 470 | F34: ='P&L Input'!F32 -> 416 | G34: ='P&L Input'!G32 -> 416 | H34: =H11*H35 -> 8727.0051 | I34: =I11*I35 -> 9558.5843 | J34: =J11*J35 -> 10381.908 | K34: =K11*K35 -> 11182.267 | L34: =L11*L35 -> 11944.323 | M34: =M11*M35 -> 12652.532 | N34: =N11*N35 -> 13291.588 | O34: =O11*O35 -> 13846.888 | ... Q34: =Q11*Q35 -> 14654.111
B35: (as % of period-end Lease Liabilities) | C35: =C34/('BS Input'!D52+'BS Input'!D61) -> 0.036536354 | D35: =D34/('BS Input'!E52+'BS Input'!E61) -> 0.03422099 | E35: =E34/('BS Input'!F52+'BS Input'!F61) -> 0.056226821 | F35: =F34/('BS Input'!G52+'BS Input'!G61) -> 0.050565212 | G35: =G34/('BS Input'!H52+'BS Input'!H61) -> 0.045335658 | H35: =AVERAGE(C35:G35) -> 0.044577007 | I35: =H35 -> 0.044577007 | J35: =I35 -> 0.044577007 | K35: =J35 -> 0.044577007 | L35: =K35 -> 0.044577007 | M35: =L35 -> 0.044577007 | N35: =M35 -> 0.044577007 | O35: =N35 -> 0.044577007 | P35: =O35 -> 0.044577007 | Q35: =P35 -> 0.044577007
B37: Effective Tax rate | C37: ='P&L Input'!C40/'P&L Input'!C38 -> 0.26449684 | D37: ='P&L Input'!D40/'P&L Input'!D38 -> 0.27651401 | E37: ='P&L Input'!E40/'P&L Input'!E38 -> 0.27064577 | F37: ='P&L Input'!F40/'P&L Input'!F38 -> 0.28871517 | G37: ='P&L Input'!G40/'P&L Input'!G38 -> 0.26305788 | H37: =G37+0.3% -> 0.26605788 | I37: =H37+0.3% -> 0.26905788 | J37: =I37+0.3% -> 0.27205788 | K37: =J37+0.3% -> 0.27505788 | L37: =K37+0.3% -> 0.27805788 | M37: =L37+0.3% -> 0.28105788 | N37: =M37+0.3% -> 0.28405788 | O37: =N37+0.3% -> 0.28705788 | ... Q37: =P37+0.3% -> 0.29305788

Sheet FAS
B2: Infosys Limited
P6: (INR in Crores)
B7: Fixed Assets Schedule
B8: Particulars | C8: ='Cost Buildup'!C8 -> 2022 | D8: ='Cost Buildup'!D8 -> 2023 | E8: ='Cost Buildup'!E8 -> 2024 | F8: ='Cost Buildup'!F8 -> 2025 | G8: ='Cost Buildup'!G8 -> 2026 | H8: ='Cost Buildup'!H8 -> 2027 | I8: ='Cost Buildup'!I8 -> 2028 | J8: ='Cost Buildup'!J8 -> 2029 | ... Q8: ='Cost Buildup'!Q8 -> 2036
C9: Audited | D9: Audited | E9: Audited | F9: Audited | G9: Audited | H9: Estimated | I9: Projected | J9: Projected | K9: Projected | L9: Projected | M9: Projected | N9: Projected | O9: Projected | P9: Projected | Q9: Projected
B10: PPE Assets
B11: Buildings
B12: Opening Gross Block | C12: 10565 | D12: =C15 -> 11224 | E12: =D15 -> 11562 | F12: =E15 -> 11770 | G12: =F15 -> 11721 | H12: =G15 -> 12574 | I12: =H15 -> 13302 | J12: =I15 -> 14030 | K12: =J15 -> 14758 | ... Q12: =P15 -> 19391.574
B13: Additions | C13: 598 | D13: 337 | E13: 245 | F13: -69 | G13: 700 | H13: =G13*1.04 -> 728 | I13: =H13 -> 728 | J13: =I13 -> 728 | K13: =J13*1.04 -> 757.12 | L13: =K13 -> 757.12 | M13: =L13 -> 757.12 | N13: =M13*1.04 -> 787.4048 | O13: =N13 -> 787.4048 | P13: =O13 -> 787.4048 | Q13: =P13*1.04 -> 818.90099
B14: Forex fluctuations | C14: 61 | D14: 1 | E14: -37 | F14: 20 | G14: 153
B15: Closing Gross Block | C15: =SUM(C12:C14) -> 11224 | D15: =SUM(D12:D14) -> 11562 | E15: =SUM(E12:E14) -> 11770 | F15: =SUM(F12:F14) -> 11721 | G15: =SUM(G12:G14) -> 12574 | H15: =SUM(H12:H14) -> 13302 | I15: =SUM(I12:I14) -> 14030 | J15: =SUM(J12:J14) -> 14758 | ... Q15: =SUM(Q12:Q14) -> 20210.475
B16: Accumulated Depreciation | C16: 3675 | D16: =SUM(C16:C18) -> 4100 | E16: =SUM(D16:D18) -> 4535 | F16: =SUM(E16:E18) -> 4921 | G16: =SUM(F16:F18) -> 5358 | H16: =SUM(G16:G18) -> 5856 | I16: =SUM(H16:H18) -> 6320.88 | J16: =SUM(I16:I18) -> 6785.76 | K16: =SUM(J16:J18) -> 7250.64 | ... Q16: =SUM(P16:P18) -> 10209.508
B17: Depreciation for year | C17: 417 | D17: 434 | E17: 395 | F17: 431 | G17: 447 | H17: =G17*1.04 -> 464.88 | I17: =H17 -> 464.88 | J17: =I17 -> 464.88 | K17: =J17*1.04 -> 483.4752 | L17: =K17 -> 483.4752 | M17: =L17 -> 483.4752 | N17: =M17*1.04 -> 502.81421 | O17: =N17 -> 502.81421 | P17: =O17 -> 502.81421 | Q17: =P17*1.04 -> 522.92678
B18: Forex fluctuations | C18: 8 | D18: 1 | E18: -9 | F18: 6 | G18: 51
B19: Net Block | C19: =C15-SUM(C16:C18) -> 7124 | D19: =D15-SUM(D16:D18) -> 7027 | E19: =E15-SUM(E16:E18) -> 6849 | F19: =F15-SUM(F16:F18) -> 6363 | G19: =G15-SUM(G16:G18) -> 6718 | H19: =H15-SUM(H16:H18) -> 6981.12 | I19: =I15-SUM(I16:I18) -> 7244.24 | J19: =J15-SUM(J16:J18) -> 7507.36 | ... Q19: =Q15-SUM(Q16:Q18) -> 9478.0404
B21: Computers
B22: Opening Gross Block | C22: 7639 | D22: =C27 -> 8527 | E22: =D27 -> 8519 | F22: =E27 -> 8611 | G22: =F27 -> 9306 | H22: =G27 -> 9607 | I22: =H27 -> 9916.92 | J22: =I27 -> 10226.84 | K22: =J27 -> 10536.76 | ... Q22: =P27 -> 12509.339
B23: Acquired through BC | C23: 0 | D23: 6 | E23: 0 | F23: 6 | G23: 3
B24: Additions | C24: 1542 | D24: 1510 | E24: 931 | F24: 1317 | G24: 1524 | H24: =G24*1.04 -> 1584.96 | I24: =H24 -> 1584.96 | J24: =I24 -> 1584.96 | K24: =J24*1.04 -> 1648.3584 | L24: =K24 -> 1648.3584 | M24: =L24 -> 1648.3584 | N24: =M24*1.04 -> 1714.2927 | O24: =N24 -> 1714.2927 | P24: =O24 -> 1714.2927 | Q24: =P24*1.04 -> 1782.8644
B25: Forex fluctuations | C25: 18 | D25: 39 | E25: 7 | F25: 5 | G25: 99 | H25: =G25*1.04 -> 102.96 | I25: =H25 -> 102.96 | J25: =I25 -> 102.96 | K25: =J25*1.04 -> 107.0784 | L25: =K25 -> 107.0784 | M25: =L25 -> 107.0784 | N25: =M25*1.04 -> 111.36154 | O25: =N25 -> 111.36154 | P25: =O25 -> 111.36154 | Q25: =P25*1.04 -> 115.816
B26: Disposal | C26: -672 | D26: -1563 | E26: -846 | F26: -633 | G26: -1325 | H26: =G26*1.04 -> -1378 | I26: =H26 -> -1378 | J26: =I26 -> -1378 | K26: =J26*1.04 -> -1433.12 | L26: =K26 -> -1433.12 | M26: =L26 -> -1433.12 | N26: =M26*1.04 -> -1490.4448 | O26: =N26 -> -1490.4448 | P26: =O26 -> -1490.4448 | Q26: =P26*1.04 -> -1550.0626
B27: Closing Gross Block | C27: =SUM(C22:C26) -> 8527 | D27: =SUM(D22:D26) -> 8519 | E27: =SUM(E22:E26) -> 8611 | F27: =SUM(F22:F26) -> 9306 | G27: =SUM(G22:G26) -> 9607 | H27: =SUM(H22:H26) -> 9916.92 | I27: =SUM(I22:I26) -> 10226.84 | J27: =SUM(J22:J26) -> 10536.76 | ... Q27: =SUM(Q22:Q26) -> 12857.957
B28: Accumulated Depreciation | C28: 5636 | D28: =SUM(C28:C31) -> 6034 | E28: =SUM(D28:D31) -> 5826 | F28: =SUM(E28:E31) -> 6380 | G28: =SUM(F28:F31) -> 7013 | H28: =SUM(G28:G31) -> 6850 | I28: =SUM(H28:H31) -> 6680.48 | J28: =SUM(I28:I31) -> 6510.96 | K28: =SUM(J28:J31) -> 6341.44 | ... Q28: =SUM(P28:P31) -> 5262.4791
B29: Depreciation for year | C29: 1055 | D29: 1322 | E29: 1387 | F29: 1249 | G29: 1079 | H29: =G29*1.04 -> 1122.16 | I29: =H29 -> 1122.16 | J29: =I29 -> 1122.16 | K29: =J29*1.04 -> 1167.0464 | L29: =K29 -> 1167.0464 | M29: =L29 -> 1167.0464 | N29: =M29*1.04 -> 1213.7283 | O29: =N29 -> 1213.7283 | P29: =O29 -> 1213.7283 | Q29: =P29*1.04 -> 1262.2774
B30: Forex fluctuations | C30: 14 | D30: 26 | E30: 3 | F30: 0 | G30: 60 | H30: =G30*1.04 -> 62.4 | I30: =H30 -> 62.4 | J30: =I30 -> 62.4 | K30: =J30*1.04 -> 64.896 | L30: =K30 -> 64.896 | M30: =L30 -> 64.896 | N30: =M30*1.04 -> 67.49184 | O30: =N30 -> 67.49184 | P30: =O30 -> 67.49184 | Q30: =P30*1.04 -> 70.191514
B31: Disposal | C31: -671 | D31: -1556 | E31: -836 | F31: -616 | G31: -1302 | H31: =G31*1.04 -> -1354.08 | I31: =H31 -> -1354.08 | J31: =I31 -> -1354.08 | K31: =J31*1.04 -> -1408.2432 | L31: =K31 -> -1408.2432 | M31: =L31 -> -1408.2432 | N31: =M31*1.04 -> -1464.5729 | O31: =N31 -> -1464.5729 | P31: =O31 -> -1464.5729 | Q31: =P31*1.04 -> -1523.1558
B32: Net Block | C32: =C27-SUM(C28:C31) -> 2493 | D32: =D27-SUM(D28:D31) -> 2693 | E32: =E27-SUM(E28:E31) -> 2231 | F32: =F27-SUM(F28:F31) -> 2293 | G32: =G27-SUM(G28:G31) -> 2757 | H32: =H27-SUM(H28:H31) -> 3236.44 | I32: =I27-SUM(I28:I31) -> 3715.88 | J32: =J27-SUM(J28:J31) -> 4195.32 | ... Q32: =Q27-SUM(Q28:Q31) -> 7786.1645
B34: Plants & Equipment
B35: Opening Gross Block | C35: 3296 | D35: =C39 -> 3210 | E35: =D39 -> 3302 | F35: =E39 -> 3428 | G35: =F39 -> 3461 | H35: =G39 -> 3714 | I35: =H39 -> 3977.12 | J35: =I39 -> 4240.24 | K35: =J39 -> 4503.36 | ... Q35: =P39 -> 6178.0662
B36: Additions | C36: 256 | D36: 273 | E36: 193 | F36: 63 | G36: 270 | H36: =G36*1.04 -> 280.8 | I36: =H36 -> 280.8 | J36: =I36 -> 280.8 | K36: =J36*1.04 -> 292.032 | L36: =K36 -> 292.032 | M36: =L36 -> 292.032 | N36: =M36*1.04 -> 303.71328 | O36: =N36 -> 303.71328 | P36: =O36 -> 303.71328 | Q36: =P36*1.04 -> 315.86181
B37: Forex fluctuations | C37: 7 | D37: 1 | E37: -3 | F37: 1 | G37: 14 | H37: =G37*1.04 -> 14.56 | I37: =H37 -> 14.56 | J37: =I37 -> 14.56 | K37: =J37*1.04 -> 15.1424 | L37: =K37 -> 15.1424 | M37: =L37 -> 15.1424 | N37: =M37*1.04 -> 15.748096 | O37: =N37 -> 15.748096 | P37: =O37 -> 15.748096 | Q37: =P37*1.04 -> 16.37802
B38: Disposal | C38: -349 | D38: -182 | E38: -64 | F38: -31 | G38: -31 | H38: =G38*1.04 -> -32.24 | I38: =H38 -> -32.24 | J38: =I38 -> -32.24 | K38: =J38*1.04 -> -33.5296 | L38: =K38 -> -33.5296 | M38: =L38 -> -33.5296 | N38: =M38*1.04 -> -34.870784 | O38: =N38 -> -34.870784 | P38: =O38 -> -34.870784 | Q38: =P38*1.04 -> -36.265615
B39: Closing Gross Block | C39: =SUM(C35:C38) -> 3210 | D39: =SUM(D35:D38) -> 3302 | E39: =SUM(E35:E38) -> 3428 | F39: =SUM(F35:F38) -> 3461 | G39: =SUM(G35:G38) -> 3714 | H39: =SUM(H35:H38) -> 3977.12 | I39: =SUM(I35:I38) -> 4240.24 | J39: =SUM(J35:J38) -> 4503.36 | ... Q39: =SUM(Q35:Q38) -> 6474.0404
B40: Accumulated Depreciation | C40: 2425 | D40: =SUM(C40:C43) -> 2344 | E40: =SUM(D40:D43) -> 2437 | F40: =SUM(E40:E43) -> 2630 | G40: =SUM(F40:F43) -> 2813 | H40: =SUM(G40:G43) -> 2985 | I40: =SUM(H40:H43) -> 3163.88 | J40: =SUM(I40:I43) -> 3342.76 | K40: =SUM(J40:J43) -> 3521.64 | ... Q40: =SUM(P40:P43) -> 4660.1754
B41: Depreciation for year | C41: 245 | D41: 273 | E41: 259 | F41: 203 | G41: 188 | H41: =G41*1.04 -> 195.52 | I41: =H41 -> 195.52 | J41: =I41 -> 195.52 | K41: =J41*1.04 -> 203.3408 | L41: =K41 -> 203.3408 | M41: =L41 -> 203.3408 | N41: =M41*1.04 -> 211.47443 | O41: =N41 -> 211.47443 | P41: =O41 -> 211.47443 | Q41: =P41*1.04 -> 219.93341
B42: Forex fluctuations | C42: 4 | D42: 1 | E42: -2 | F42: 1 | G42: 14 | H42: =G42*1.04 -> 14.56 | I42: =H42 -> 14.56 | J42: =I42 -> 14.56 | K42: =J42*1.04 -> 15.1424 | L42: =K42 -> 15.1424 | M42: =L42 -> 15.1424 | N42: =M42*1.04 -> 15.748096 | O42: =N42 -> 15.748096 | P42: =O42 -> 15.748096 | Q42: =P42*1.04 -> 16.37802
B43: Disposal | C43: -330 | D43: -181 | E43: -64 | F43: -21 | G43: -30 | H43: =G43*1.04 -> -31.2 | I43: =H43 -> -31.2 | J43: =I43 -> -31.2 | K43: =J43*1.04 -> -32.448 | L43: =K43 -> -32.448 | M43: =L43 -> -32.448 | N43: =M43*1.04 -> -33.74592 | O43: =N43 -> -33.74592 | P43: =O43 -> -33.74592 | Q43: =P43*1.04 -> -35.095757
B44: Net Block | C44: =C39-SUM(C40:C43) -> 866 | D44: =D39-SUM(D40:D43) -> 865 | E44: =E39-SUM(E40:E43) -> 798 | F44: =F39-SUM(F40:F43) -> 648 | G44: =G39-SUM(G40:G43) -> 729 | H44: =H39-SUM(H40:H43) -> 813.24 | I44: =I39-SUM(I40:I43) -> 897.48 | J44: =J39-SUM(J40:J43) -> 981.72 | ... Q44: =Q39-SUM(Q40:Q43) -> 1612.6493
B46: Furniture & Fixtures
B47: Opening Gross Block | C47: 2149 | D47: =C52 -> 2278 | E47: =D52 -> 2303 | F47: =E52 -> 2326 | G47: =F52 -> 2340 | H47: =G52 -> 2438 | I47: =H52 -> 2539.92 | J47: =I52 -> 2641.84 | K47: =J52 -> 2743.76 | ... Q47: =P52 -> 3392.4604
B48: Acquired through BC | C48: 0 | D48: 1 | E48: 0 | F48: 23 | G48: 0
B49: Additions | C49: 140 | D49: 364 | E49: 121 | F49: 93 | G49: 195 | H49: =G49*1.04 -> 202.8 | I49: =H49 -> 202.8 | J49: =I49 -> 202.8 | K49: =J49*1.04 -> 210.912 | L49: =K49 -> 210.912 | M49: =L49 -> 210.912 | N49: =M49*1.04 -> 219.34848 | O49: =N49 -> 219.34848 | P49: =O49 -> 219.34848 | Q49: =P49*1.04 -> 228.12242
B50: Forex fluctuations | C50: 6 | D50: 8 | E50: 1 | F50: -1 | G50: 24 | H50: =G50*1.04 -> 24.96 | I50: =H50 -> 24.96 | J50: =I50 -> 24.96 | K50: =J50*1.04 -> 25.9584 | L50: =K50 -> 25.9584 | M50: =L50 -> 25.9584 | N50: =M50*1.04 -> 26.996736 | O50: =N50 -> 26.996736 | P50: =O50 -> 26.996736 | Q50: =P50*1.04 -> 28.076605
B51: Disposal | C51: -17 | D51: -348 | E51: -99 | F51: -101 | G51: -121 | H51: =G51*1.04 -> -125.84 | I51: =H51 -> -125.84 | J51: =I51 -> -125.84 | K51: =J51*1.04 -> -130.8736 | L51: =K51 -> -130.8736 | M51: =L51 -> -130.8736 | N51: =M51*1.04 -> -136.10854 | O51: =N51 -> -136.10854 | P51: =O51 -> -136.10854 | Q51: =P51*1.04 -> -141.55289
B52: Closing Gross Block | C52: =SUM(C47:C51) -> 2278 | D52: =SUM(D47:D51) -> 2303 | E52: =SUM(E47:E51) -> 2326 | F52: =SUM(F47:F51) -> 2340 | G52: =SUM(G47:G51) -> 2438 | H52: =SUM(H47:H51) -> 2539.92 | I52: =SUM(I47:I51) -> 2641.84 | J52: =SUM(J47:J51) -> 2743.76 | ... Q52: =SUM(Q47:Q51) -> 3507.1066
B53: Accumulated Depreciation | C53: 1580 | D53: =SUM(C53:C56) -> 1779 | E53: =SUM(D53:D56) -> 1675 | F53: =SUM(E53:E56) -> 1837 | G53: =SUM(F53:F56) -> 1929 | H53: =SUM(G53:G56) -> 1995 | I53: =SUM(H53:H56) -> 2063.64 | J53: =SUM(I53:I56) -> 2132.28 | K53: =SUM(J53:J56) -> 2200.92 | ... Q53: =SUM(P53:P56) -> 2637.7999
B54: Depreciation for year | C54: 210 | D54: 236 | E54: 250 | F54: 187 | G54: 167 | H54: =G54*1.04 -> 173.68 | I54: =H54 -> 173.68 | J54: =I54 -> 173.68 | K54: =J54*1.04 -> 180.6272 | L54: =K54 -> 180.6272 | M54: =L54 -> 180.6272 | N54: =M54*1.04 -> 187.85229 | O54: =N54 -> 187.85229 | P54: =O54 -> 187.85229 | Q54: =P54*1.04 -> 195.36638
B55: Forex fluctuations | C55: 5 | D55: 7 | E55: 1 | F55: -1 | G55: 18 | H55: =G55*1.04 -> 18.72 | I55: =H55 -> 18.72 | J55: =I55 -> 18.72 | K55: =J55*1.04 -> 19.4688 | L55: =K55 -> 19.4688 | M55: =L55 -> 19.4688 | N55: =M55*1.04 -> 20.247552 | O55: =N55 -> 20.247552 | P55: =O55 -> 20.247552 | Q55: =P55*1.04 -> 21.057454
B56: Disposal | C56: -16 | D56: -347 | E56: -89 | F56: -94 | G56: -119 | H56: =G56*1.04 -> -123.76 | I56: =H56 -> -123.76 | J56: =I56 -> -123.76 | K56: =J56*1.04 -> -128.7104 | L56: =K56 -> -128.7104 | M56: =L56 -> -128.7104 | N56: =M56*1.04 -> -133.85882 | O56: =N56 -> -133.85882 | P56: =O56 -> -133.85882 | Q56: =P56*1.04 -> -139.21317
B57: Net Block | C57: =C52-SUM(C53:C56) -> 499 | D57: =D52-SUM(D53:D56) -> 628 | E57: =E52-SUM(E53:E56) -> 489 | F57: =F52-SUM(F53:F56) -> 411 | G57: =G52-SUM(G53:G56) -> 443 | H57: =H52-SUM(H53:H56) -> 476.28 | I57: =I52-SUM(I53:I56) -> 509.56 | J57: =J52-SUM(J53:J56) -> 542.84 | ... Q57: =Q52-SUM(Q53:Q56) -> 792.09602
B59: Vehicles
B60: Opening Gross Block | C60: 44 | D60: =C65 -> 44 | E60: =D65 -> 45 | F60: =E65 -> 45 | G60: =F65 -> 48 | H60: =G65 -> 44 | I60: =H65 -> 39.84 | J60: =I65 -> 35.68 | K60: =J65 -> 31.52 | ... Q60: =P65 -> 5.042432
B61: Acquired through BC | C61: 0 | D61: 0 | E61: 0 | F61: 2 | G61: 0
B62: Additions | C62: 0 | D62: 2 | E62: 1 | F62: 2 | G62: 1 | H62: =G62*1.04 -> 1.04 | I62: =H62 -> 1.04 | J62: =I62 -> 1.04 | K62: =J62*1.04 -> 1.0816 | L62: =K62 -> 1.0816 | M62: =L62 -> 1.0816 | N62: =M62*1.04 -> 1.124864 | O62: =N62 -> 1.124864 | P62: =O62 -> 1.124864 | Q62: =P62*1.04 -> 1.1698586
B63: Forex fluctuations | C63: 0 | D63: 0 | E63: 0 | F63: 0 | G63: 0 | H63: =G63*1.04 -> 0 | I63: =H63 -> 0 | J63: =I63 -> 0 | K63: =J63*1.04 -> 0 | L63: =K63 -> 0 | M63: =L63 -> 0 | N63: =M63*1.04 -> 0 | O63: =N63 -> 0 | P63: =O63 -> 0 | Q63: =P63*1.04 -> 0
B64: Disposal | C64: 0 | D64: -1 | E64: -1 | F64: -1 | G64: -5 | H64: =G64*1.04 -> -5.2 | I64: =H64 -> -5.2 | J64: =I64 -> -5.2 | K64: =J64*1.04 -> -5.408 | L64: =K64 -> -5.408 | M64: =L64 -> -5.408 | N64: =M64*1.04 -> -5.62432 | O64: =N64 -> -5.62432 | P64: =O64 -> -5.62432 | Q64: =P64*1.04 -> -5.8492928
B65: Closing Gross Block | C65: =SUM(C60:C64) -> 44 | D65: =SUM(D60:D64) -> 45 | E65: =SUM(E60:E64) -> 45 | F65: =SUM(F60:F64) -> 48 | G65: =SUM(G60:G64) -> 44 | H65: =SUM(H60:H64) -> 39.84 | I65: =SUM(I60:I64) -> 35.68 | J65: =SUM(J60:J64) -> 31.52 | ... Q65: =SUM(Q60:Q64) -> 0.36299776
B66: Accumulated Depreciation | C66: 32 | D66: =SUM(C66:C69) -> 37 | E66: =SUM(D66:D69) -> 40 | F66: =SUM(E66:E69) -> 42 | G66: =SUM(F66:F69) -> 43 | H66: =SUM(G66:G69) -> 39 | I66: =SUM(H66:H69) -> 34.84 | J66: =SUM(I66:I69) -> 30.68 | K66: =SUM(J66:J69) -> 26.52 | ... Q66: =SUM(P66:P69) -> 0.042432
B67: Depreciation for year | C67: 5 | D67: 4 | E67: 3 | F67: 2 | G67: 1 | H67: =G67*1.04 -> 1.04 | I67: =H67 -> 1.04 | J67: =I67 -> 1.04 | K67: =J67*1.04 -> 1.0816 | L67: =K67 -> 1.0816 | M67: =L67 -> 1.0816 | N67: =M67*1.04 -> 1.124864 | O67: =N67 -> 1.124864 | P67: =O67 -> 1.124864 | Q67: =P67*1.04 -> 1.1698586
B68: Forex fluctuations | C68: 0 | D68: 0 | E68: 0 | F68: 0 | G68: 0 | H68: =G68*1.04 -> 0 | I68: =H68 -> 0 | J68: =I68 -> 0 | K68: =J68*1.04 -> 0 | L68: =K68 -> 0 | M68: =L68 -> 0 | N68: =M68*1.04 -> 0 | O68: =N68 -> 0 | P68: =O68 -> 0 | Q68: =P68*1.04 -> 0
B69: Disposal | C69: 0 | D69: -1 | E69: -1 | F69: -1 | G69: -5 | H69: =G69*1.04 -> -5.2 | I69: =H69 -> -5.2 | J69: =I69 -> -5.2 | K69: =J69*1.04 -> -5.408 | L69: =K69 -> -5.408 | M69: =L69 -> -5.408 | N69: =M69*1.04 -> -5.62432 | O69: =N69 -> -5.62432 | P69: =O69 -> -5.62432 | Q69: =P69*1.04 -> -5.8492928
B70: Net Block | C70: =C65-SUM(C66:C69) -> 7 | D70: =D65-SUM(D66:D69) -> 5 | E70: =E65-SUM(E66:E69) -> 3 | F70: =F65-SUM(F66:F69) -> 5 | G70: =G65-SUM(G66:G69) -> 5 | H70: =H65-SUM(H66:H69) -> 5 | I70: =I65-SUM(I66:I69) -> 5 | J70: =J65-SUM(J66:J69) -> 5 | ... Q70: =Q65-SUM(Q66:Q69) -> 5
B72: Office Equipment
B73: Opening Gross Block | C73: 1371 | D73: =SUM(C77) -> 1427 | E73: =SUM(D77) -> 1482 | F73: =SUM(E77) -> 1528 | G73: =SUM(F77) -> 1628 | H73: =G77 -> 1732 | I73: =H77 -> 1840.16 | J73: =I77 -> 1948.32 | K73: =J77 -> 2056.48 | L73: =K77 -> 2168.9664 | M73: =L77 -> 2281.4528 | N73: =M77 -> 2393.9392 | O73: =N77 -> 2510.9251 | ... Q73: =P77 -> 2744.8968
B74: Additions | C74: 68 | D74: 127 | E74: 106 | F74: 150 | G74: 137 | H74: =G74*1.04 -> 142.48 | I74: =H74 -> 142.48 | J74: =I74 -> 142.48 | K74: =J74*1.04 -> 148.1792 | L74: =K74 -> 148.1792 | M74: =L74 -> 148.1792 | N74: =M74*1.04 -> 154.10637 | O74: =N74 -> 154.10637 | P74: =O74 -> 154.10637 | Q74: =P74*1.04 -> 160.27062
B75: Forex fluctuations | C75: 3 | D75: 4 | E75: 0 | F75: 2 | G75: 17 | H75: =G75*1.04 -> 17.68 | I75: =H75 -> 17.68 | J75: =I75 -> 17.68 | K75: =J75*1.04 -> 18.3872 | L75: =K75 -> 18.3872 | M75: =L75 -> 18.3872 | N75: =M75*1.04 -> 19.122688 | O75: =N75 -> 19.122688 | P75: =O75 -> 19.122688 | Q75: =P75*1.04 -> 19.887596
B76: Disposal | C76: -15 | D76: -76 | E76: -60 | F76: -52 | G76: -50 | H76: =G76*1.04 -> -52 | I76: =H76 -> -52 | J76: =I76 -> -52 | K76: =J76*1.04 -> -54.08 | L76: =K76 -> -54.08 | M76: =L76 -> -54.08 | N76: =M76*1.04 -> -56.2432 | O76: =N76 -> -56.2432 | P76: =O76 -> -56.2432 | Q76: =P76*1.04 -> -58.492928
B77: Closing Gross Block | C77: =SUM(C73:C76) -> 1427 | D77: =SUM(D73:D76) -> 1482 | E77: =SUM(E73:E76) -> 1528 | F77: =SUM(F73:F76) -> 1628 | G77: =SUM(G73:G76) -> 1732 | H77: =SUM(H73:H76) -> 1840.16 | I77: =SUM(I73:I76) -> 1948.32 | J77: =SUM(J73:J76) -> 2056.48 | ... Q77: =SUM(Q73:Q76) -> 2866.5621
B78: Accumulated Depreciation | C78: 1043 | D78: =SUM(C78:C81) -> 1150 | E78: =SUM(D78:D81) -> 1198 | F78: =SUM(E78:E81) -> 1269 | G78: =SUM(F78:F81) -> 1337 | H78: =SUM(G78:G81) -> 1417 | I78: =SUM(H78:H81) -> 1500.2 | J78: =SUM(I78:I81) -> 1583.4 | K78: =SUM(J78:J81) -> 1666.6 | ... Q78: =SUM(P78:P81) -> 2196.1514
B79: Depreciation for year | C79: 120 | D79: 121 | E79: 130 | F79: 118 | G79: 118 | H79: =G79*1.04 -> 122.72 | I79: =H79 -> 122.72 | J79: =I79 -> 122.72 | K79: =J79*1.04 -> 127.6288 | L79: =K79 -> 127.6288 | M79: =L79 -> 127.6288 | N79: =M79*1.04 -> 132.73395 | O79: =N79 -> 132.73395 | P79: =O79 -> 132.73395 | Q79: =P79*1.04 -> 138.04331
B80: Forex fluctuations | C80: 1 | D80: 3 | E80: 0 | F80: 1 | G80: 12 | H80: =G80*1.04 -> 12.48 | I80: =H80 -> 12.48 | J80: =I80 -> 12.48 | K80: =J80*1.04 -> 12.9792 | L80: =K80 -> 12.9792 | M80: =L80 -> 12.9792 | N80: =M80*1.04 -> 13.498368 | O80: =N80 -> 13.498368 | P80: =O80 -> 13.498368 | Q80: =P80*1.04 -> 14.038303
B81: Disposal | C81: -14 | D81: -76 | E81: -59 | F81: -51 | G81: -50 | H81: =G81*1.04 -> -52 | I81: =H81 -> -52 | J81: =I81 -> -52 | K81: =J81*1.04 -> -54.08 | L81: =K81 -> -54.08 | M81: =L81 -> -54.08 | N81: =M81*1.04 -> -56.2432 | O81: =N81 -> -56.2432 | P81: =O81 -> -56.2432 | Q81: =P81*1.04 -> -58.492928
B82: Net Block | C82: =C77-SUM(C78:C81) -> 277 | D82: =D77-SUM(D78:D81) -> 284 | E82: =E77-SUM(E78:E81) -> 259 | F82: =F77-SUM(F78:F81) -> 291 | G82: =G77-SUM(G78:G81) -> 315 | H82: =H77-SUM(H78:H81) -> 339.96 | I82: =I77-SUM(I78:I81) -> 364.92 | J82: =J77-SUM(J78:J81) -> 389.88 | ... Q82: =Q77-SUM(Q78:Q81) -> 576.82201
B84: Land - Freehold
B85: Opening Gross Block | C85: 1399 | D85: =C86 -> 1431 | E85: =D86 -> 1431 | F85: =E86 -> 1432 | G85: =F86 -> 1479 | H85: =G86 -> 1440 | I85: =H86 -> 1440 | J85: =I86 -> 1440 | K85: =J86 -> 1440 | ... Q85: =P86 -> 1440
B86: Closing Gross Block | C86: 1431 | D86: 1431 | E86: 1432 | F86: 1479 | G86: 1440 | H86: =SUM(H85) -> 1440 | I86: =SUM(I85) -> 1440 | J86: =SUM(J85) -> 1440 | K86: =SUM(K85) -> 1440 | L86: =SUM(L85) -> 1440 | M86: =SUM(M85) -> 1440 | N86: =SUM(N85) -> 1440 | O86: =SUM(O85) -> 1440 | ... Q86: =SUM(Q85) -> 1440
B87: Accumulated Depreciation | C87: 0 | D87: =SUM(C87:C88) -> 0 | E87: =SUM(D87:D88) -> 0 | F87: =SUM(E87:E88) -> 0 | G87: =SUM(F87:F88) -> 0 | H87: =SUM(G87:G88) -> 0 | I87: =SUM(H87:H88) -> 0 | J87: =SUM(I87:I88) -> 0 | K87: =SUM(J87:J88) -> 0 | ... Q87: =SUM(P87:P88) -> 0
B88: Depreciation for year | C88: 0 | D88: 0 | E88: 0 | F88: 0 | G88: 0 | H88: =G88 -> 0 | I88: =H88 -> 0 | J88: =I88 -> 0 | K88: =J88 -> 0 | L88: =K88 -> 0 | M88: =L88 -> 0 | N88: =M88 -> 0 | O88: =N88 -> 0 | ... Q88: =P88 -> 0
B89: Net Block | C89: =C86-SUM(C87:C88) -> 1431 | D89: =D86-SUM(D87:D88) -> 1431 | E89: =E86-SUM(E87:E88) -> 1432 | F89: =F86-SUM(F87:F88) -> 1479 | G89: =G86-SUM(G87:G88) -> 1440 | H89: =H86-SUM(H87:H88) -> 1440 | I89: =I86-SUM(I87:I88) -> 1440 | J89: =J86-SUM(J87:J88) -> 1440 | ... Q89: =Q86-SUM(Q87:Q88) -> 1440
B91: Leasehold improvements
B92: Opening Gross Block | C92: 1188 | D92: =C97 -> 1234 | E92: =D97 -> 1445 | F92: =E97 -> 1447 | G92: =F97 -> 1307 | H92: =G97 -> 1369 | I92: =H97 -> 1490.68 | J92: =I97 -> 1612.36 | K92: =J97 -> 1734.04 | ... Q92: =P97 -> 2508.5089
B93: Acquired through BC | C93: 0 | D93: 2 | E93: 0 | F93: 0 | G93: 0
B94: Additions | C94: 79 | D94: 220 | E94: 108 | F94: 139 | G94: 64 | H94: =G94*1.04 -> 66.56 | I94: =H94 -> 66.56 | J94: =I94 -> 66.56 | K94: =J94*1.04 -> 69.2224 | L94: =K94 -> 69.2224 | M94: =L94 -> 69.2224 | N94: =M94*1.04 -> 71.991296 | O94: =N94 -> 71.991296 | P94: =O94 -> 71.991296 | Q94: =P94*1.04 -> 74.870948
B95: Forex fluctuations | C95: 13 | D95: 14 | E95: -4 | F95: 11 | G95: 53 | H95: =G95*1.04 -> 55.12 | I95: =H95 -> 55.12 | J95: =I95 -> 55.12 | K95: =J95*1.04 -> 57.3248 | L95: =K95 -> 57.3248 | M95: =L95 -> 57.3248 | N95: =M95*1.04 -> 59.617792 | O95: =N95 -> 59.617792 | P95: =O95 -> 59.617792 | Q95: =P95*1.04 -> 62.002504
B96: Disposal | C96: -46 | D96: -25 | E96: -102 | F96: -290 | G96: -55 | H96: =G96*1.04 -> -57.2 | I96: =H96 -> -57.2 | J96: =I96 -> -57.2 | K96: =J96*1.04 -> -59.488 | L96: =K96 -> -59.488 | M96: =L96 -> -59.488 | N96: =M96*1.04 -> -61.86752 | O96: =N96 -> -61.86752 | P96: =O96 -> -61.86752 | Q96: =P96*1.04 -> -64.342221
B97: Closing Gross Block | C97: =SUM(C92:C96) -> 1234 | D97: =SUM(D92:D96) -> 1445 | E97: =SUM(E92:E96) -> 1447 | F97: =SUM(F92:F96) -> 1307 | G97: =SUM(G92:G96) -> 1369 | H97: =SUM(H92:H95) -> 1490.68 | I97: =SUM(I92:I95) -> 1612.36 | J97: =SUM(J92:J95) -> 1734.04 | K97: =SUM(K92:K95) -> 1860.5872 | L97: =SUM(L92:L95) -> 1987.1344 | M97: =SUM(M92:M95) -> 2113.6816 | N97: =SUM(N92:N95) -> 2245.2907 | O97: =SUM(O92:O95) -> 2376.8998 | ... Q97: =SUM(Q92:Q95) -> 2645.3823
B98: Accumulated Depreciation | C98: 700 | D98: =SUM(C98:C100) -> 856 | E98: =SUM(D98:D100) -> 1032 | F98: =SUM(E98:E100) -> 1138 | G98: =SUM(F98:F100) -> 1019 | H98: =SUM(G98:G100) -> 1125 | I98: =SUM(H98:H100) -> 1235.24 | J98: =SUM(I98:I100) -> 1345.48 | K98: =SUM(J98:J100) -> 1455.72 | ... Q98: =SUM(P98:P100) -> 2157.3756
B99: Depreciation for year | C99: 144 | D99: 166 | E99: 109 | F99: -129 | G99: 56 | H99: =G99*1.04 -> 58.24 | I99: =H99 -> 58.24 | J99: =I99 -> 58.24 | K99: =J99*1.04 -> 60.5696 | L99: =K99 -> 60.5696 | M99: =L99 -> 60.5696 | N99: =M99*1.04 -> 62.992384 | O99: =N99 -> 62.992384 | P99: =O99 -> 62.992384 | Q99: =P99*1.04 -> 65.512079
B100: Forex fluctuations | C100: 12 | D100: 10 | E100: -3 | F100: 10 | G100: 50 | H100: =G100*1.04 -> 52 | I100: =H100 -> 52 | J100: =I100 -> 52 | K100: =J100*1.04 -> 54.08 | L100: =K100 -> 54.08 | M100: =L100 -> 54.08 | N100: =M100*1.04 -> 56.2432 | O100: =N100 -> 56.2432 | P100: =O100 -> 56.2432 | Q100: =P100*1.04 -> 58.492928
B101: Net Block | C101: =C97-SUM(C98:C100) -> 378 | D101: =D97-SUM(D98:D100) -> 413 | E101: =E97-SUM(E98:E100) -> 309 | F101: =F97-SUM(F98:F100) -> 288 | G101: =G97-SUM(G98:G100) -> 244 | H101: =H97-SUM(H98:H100) -> 255.44 | I101: =I97-SUM(I98:I100) -> 266.88 | J101: =J97-SUM(J98:J100) -> 278.32 | ... Q101: =Q97-SUM(Q98:Q100) -> 364.00176
B104: Total PPE - Net block | C104: =SUM(C19,C32,C44,C57,C70,C82,C89,C101,) -> 13075 | D104: =SUM(D19,D32,D44,D57,D70,D82,D89,D101,D103) -> 13346 | E104: =SUM(E19,E32,E44,E57,E70,E82,E89,E101,E103) -> 12370 | F104: =SUM(F19,F32,F44,F57,F70,F82,F89,F101,F103) -> 11778 | G104: =SUM(G19,G32,G44,G57,G70,G82,G89,G101,G103) -> 12651 | H104: =SUM(H19,H32,H44,H57,H70,H82,H89,H101,H103) -> 13547.48 | I104: =SUM(I19,I32,I44,I57,I70,I82,I89,I101,I103) -> 14443.96 | J104: =SUM(J19,J32,J44,J57,J70,J82,J89,J101,J103) -> 15340.44 | K104: =SUM(K19,K32,K44,K57,K70,K82,K89,K101,K103) -> 16272.779 | ... Q104: =SUM(Q19,Q32,Q44,Q57,Q70,Q82,Q89,Q101,Q103) -> 22054.774
B106: ROU Assets
B107: Right-of-use Assets (Total)
B108: Opening Gross Block | C108: 4794 | D108: =C113 -> 4823 | E108: =D113 -> 6882 | F108: =E113 -> 6552 | G108: =F113 -> 6311 | H108: =G113 -> 6177 | I108: =H113 -> 6037.64 | J108: =I113 -> 5898.28 | K108: =J113 -> 5758.92 | ... Q108: =P113 -> 4871.9215
B109: Acquired through BC | C109: 0 | D109: 0 | E109: 0 | F109: 160 | G109: 0
B110: Additions | C110: 914 | D110: 3501 | E110: 2278 | F110: 2135 | G110: 2537 | H110: =G110*1.04 -> 2638.48 | I110: =H110 -> 2638.48 | J110: =I110 -> 2638.48 | K110: =J110*1.04 -> 2744.0192 | L110: =K110 -> 2744.0192 | M110: =L110 -> 2744.0192 | N110: =M110*1.04 -> 2853.78 | O110: =N110 -> 2853.78 | P110: =O110 -> 2853.78 | Q110: =P110*1.04 -> 2967.9312
B111: Forex fluctuations | C111: 28 | D111: 153 | E111: 22 | F111: 54 | G111: 398 | H111: =G111*1.04 -> 413.92 | I111: =H111 -> 413.92 | J111: =I111 -> 413.92 | K111: =J111*1.04 -> 430.4768 | L111: =K111 -> 430.4768 | M111: =L111 -> 430.4768 | N111: =M111*1.04 -> 447.69587 | O111: =N111 -> 447.69587 | P111: =O111 -> 447.69587 | Q111: =P111*1.04 -> 465.60371
B112: Disposal | C112: -913 | D112: -1595 | E112: -2630 | F112: -2590 | G112: -3069 | H112: =G112*1.04 -> -3191.76 | I112: =H112 -> -3191.76 | J112: =I112 -> -3191.76 | K112: =J112*1.04 -> -3319.4304 | L112: =K112 -> -3319.4304 | M112: =L112 -> -3319.4304 | N112: =M112*1.04 -> -3452.2076 | O112: =N112 -> -3452.2076 | P112: =O112 -> -3452.2076 | Q112: =P112*1.04 -> -3590.2959
B113: Closing Gross Block | C113: =SUM(C108:C112) -> 4823 | D113: =SUM(D108:D112) -> 6882 | E113: =SUM(E108:E112) -> 6552 | F113: =SUM(F108:F112) -> 6311 | G113: =SUM(G108:G112) -> 6177 | H113: =SUM(H108:H112) -> 6037.64 | I113: =SUM(I108:I112) -> 5898.28 | J113: =SUM(J108:J112) -> 5758.92 | ... Q113: =SUM(Q108:Q112) -> 4715.1604
B114: Accumulated Depreciation | C114: 0 | D114: =SUM(C114:C117) -> 0 | E114: =SUM(D114:D117) -> 0 | F114: =SUM(E114:E117) -> 0 | G114: =SUM(F114:F117) -> 0 | H114: =SUM(G114:G117) -> 0 | I114: =SUM(H114:H117) -> 0 | J114: =SUM(I114:I117) -> 0 | K114: =SUM(J114:J117) -> 0 | ... Q114: =SUM(P114:P117) -> 0
...

Sheet BS items 
B2: Infosys Limited
M6: (unless otherwise mentioned - % on Revenue) | Q6: (INR in Crores)
B7: Balance Sheet Items
B8: Particulars | D8: =FAS!C8 -> 2022 | E8: =FAS!D8 -> 2023 | F8: =FAS!E8 -> 2024 | G8: =FAS!F8 -> 2025 | H8: =FAS!G8 -> 2026 | I8: =FAS!H8 -> 2027 | J8: =FAS!I8 -> 2028 | K8: =FAS!J8 -> 2029 | ... R8: =FAS!Q8 -> 2036
D9: Audited | E9: Audited | F9: Audited | G9: Audited | H9: Audited | I9: Estimated | J9: Projected | K9: Projected | L9: Projected | M9: Projected | N9: Projected | O9: Projected | P9: Projected | Q9: Projected | R9: Projected
B10: ASSETS
B12: ='Balance Sheet'!B12:C12 -> Non-Current Assets
C13: Investments | D13: ='BS Input'!D18 -> 13651 | E13: ='BS Input'!E18 -> 12569 | F13: ='BS Input'!F18 -> 11708 | G13: ='BS Input'!G18 -> 11059 | H13: ='BS Input'!H18 -> 8930 | I13: ='Revenue Buildup'!H$15*'BS items '!I14 -> 15344.305 | J13: ='Revenue Buildup'!I$15*'BS items '!J14 -> 16806.434 | K13: ='Revenue Buildup'!J$15*'BS items '!K14 -> 18254.048 | L13: ='Revenue Buildup'!K$15*'BS items '!L14 -> 19661.282 | M13: ='Revenue Buildup'!L$15*'BS items '!M14 -> 21001.172 | N13: ='Revenue Buildup'!M$15*'BS items '!N14 -> 22246.385 | O13: ='Revenue Buildup'!N$15*'BS items '!O14 -> 23370.009 | P13: ='Revenue Buildup'!O$15*'BS items '!P14 -> 24346.368 | ... R13: ='Revenue Buildup'!Q$15*'BS items '!R14 -> 25765.673
D14: =D13/'P&L Input'!C$11 -> 0.11222367 | E14: =E13/'P&L Input'!D$11 -> 0.085639142 | F14: =F13/'P&L Input'!E$11 -> 0.076189237 | G14: =G13/'P&L Input'!F$11 -> 0.067850788 | H14: =H13/'P&L Input'!G$11 -> 0.049986006 | I14: =AVERAGE(D14:H14) -> 0.07837777 | J14: =I14 -> 0.07837777 | K14: =J14 -> 0.07837777 | L14: =K14 -> 0.07837777 | M14: =L14 -> 0.07837777 | N14: =M14 -> 0.07837777 | O14: =N14 -> 0.07837777 | P14: =O14 -> 0.07837777 | Q14: =P14 -> 0.07837777 | R14: =Q14 -> 0.07837777
C15: Other financial assets | D15: ='BS Input'!D20 -> 1460 | E15: ='BS Input'!E20 -> 2798 | F15: ='BS Input'!F20 -> 3105 | G15: ='BS Input'!G20 -> 3511 | H15: ='BS Input'!H20 -> 2776 | I15: ='Revenue Buildup'!H$15*'BS items '!I16 -> 3459.4135 | J15: ='Revenue Buildup'!I$15*'BS items '!J16 -> 3789.0542 | K15: ='Revenue Buildup'!J$15*'BS items '!K16 -> 4115.4226 | L15: ='Revenue Buildup'!K$15*'BS items '!L16 -> 4432.6872 | M15: ='Revenue Buildup'!L$15*'BS items '!M16 -> 4734.7688 | N15: ='Revenue Buildup'!M$15*'BS items '!N16 -> 5015.5053 | O15: ='Revenue Buildup'!N$15*'BS items '!O16 -> 5268.8293 | P15: ='Revenue Buildup'!O$15*'BS items '!P16 -> 5488.9519 | ... R15: ='Revenue Buildup'!Q$15*'BS items '!R16 -> 5808.9379
D16: =D15/'P&L Input'!C$11 -> 0.012002532 | E16: =E15/'P&L Input'!D$11 -> 0.019064231 | F16: =F15/'P&L Input'!E$11 -> 0.020205635 | G16: =G15/'P&L Input'!F$11 -> 0.021541199 | H16: =H15/'P&L Input'!G$11 -> 0.015538763 | I16: =AVERAGE(D16:H16) -> 0.017670472 | J16: =I16 -> 0.017670472 | K16: =J16 -> 0.017670472 | L16: =K16 -> 0.017670472 | M16: =L16 -> 0.017670472 | N16: =M16 -> 0.017670472 | O16: =N16 -> 0.017670472 | P16: =O16 -> 0.017670472 | Q16: =P16 -> 0.017670472 | R16: =Q16 -> 0.017670472
C17: Deferred Tax Assets(net) | D17: ='BS Input'!D21 -> 1212 | E17: ='BS Input'!E21 -> 1245 | F17: ='BS Input'!F21 -> 454 | G17: ='BS Input'!G21 -> 1108 | H17: ='BS Input'!H21 -> 2264 | I17: ='Revenue Buildup'!H$15*'BS items '!I18 -> 1600.3226 | J17: ='Revenue Buildup'!I$15*'BS items '!J18 -> 1752.8142 | K17: ='Revenue Buildup'!J$15*'BS items '!K18 -> 1903.792 | L17: ='Revenue Buildup'!K$15*'BS items '!L18 -> 2050.5584 | M17: ='Revenue Buildup'!L$15*'BS items '!M18 -> 2190.3012 | N17: ='Revenue Buildup'!M$15*'BS items '!N18 -> 2320.1698 | O17: ='Revenue Buildup'!N$15*'BS items '!O18 -> 2437.3573 | P17: ='Revenue Buildup'!O$15*'BS items '!P18 -> 2539.1859 | ... R17: ='Revenue Buildup'!Q$15*'BS items '!R18 -> 2687.2112
D18: =D17/'P&L Input'!C$11 -> 0.0099637458 | E18: =E17/'P&L Input'!D$11 -> 0.0084828333 | F18: =F17/'P&L Input'!E$11 -> 0.0029543828 | G18: =G17/'P&L Input'!F$11 -> 0.0067979631 | H18: =H17/'P&L Input'!G$11 -> 0.012672824 | I18: =AVERAGE(D18:H18) -> 0.0081743498 | J18: =I18 -> 0.0081743498 | K18: =J18 -> 0.0081743498 | L18: =K18 -> 0.0081743498 | M18: =L18 -> 0.0081743498 | N18: =M18 -> 0.0081743498 | O18: =N18 -> 0.0081743498 | P18: =O18 -> 0.0081743498 | Q18: =P18 -> 0.0081743498 | R18: =Q18 -> 0.0081743498
C19: Income tax assets (net) | D19: ='BS Input'!D22 -> 6098 | E19: ='BS Input'!E22 -> 6453 | F19: ='BS Input'!F22 -> 3045 | G19: ='BS Input'!G22 -> 1622 | H19: ='BS Input'!H22 -> 666 | I19: ='Revenue Buildup'!H$15*'BS items '!I20 -> 4995.8881 | J19: ='Revenue Buildup'!I$15*'BS items '!J20 -> 5471.9365 | K19: ='Revenue Buildup'!J$15*'BS items '!K20 -> 5943.2591 | L19: ='Revenue Buildup'!K$15*'BS items '!L20 -> 6401.4346 | M19: ='Revenue Buildup'!L$15*'BS items '!M20 -> 6837.6837 | N19: ='Revenue Buildup'!M$15*'BS items '!N20 -> 7243.1075 | O19: ='Revenue Buildup'!N$15*'BS items '!O20 -> 7608.9435 | P19: ='Revenue Buildup'!O$15*'BS items '!P20 -> 7926.832 | ... R19: ='Revenue Buildup'!Q$15*'BS items '!R20 -> 8388.9376
D20: =D19/'P&L Input'!C$11 -> 0.050131124 | E20: =E19/'P&L Input'!D$11 -> 0.043967649 | F20: =F19/'P&L Input'!E$11 -> 0.019815188 | G20: =G19/'P&L Input'!F$11 -> 0.0099515308 | H20: =H19/'P&L Input'!G$11 -> 0.0037279597 | I20: =AVERAGE(D20:H20) -> 0.02551869 | J20: =I20 -> 0.02551869 | K20: =J20 -> 0.02551869 | L20: =K20 -> 0.02551869 | M20: =L20 -> 0.02551869 | N20: =M20 -> 0.02551869 | O20: =N20 -> 0.02551869 | P20: =O20 -> 0.02551869 | Q20: =P20 -> 0.02551869 | R20: =Q20 -> 0.02551869
C21: Other non-current assets | D21: ='BS Input'!D23 -> 2029 | E21: ='BS Input'!E23 -> 2318 | F21: ='BS Input'!F23 -> 2121 | G21: ='BS Input'!G23 -> 2713 | H21: ='BS Input'!H23 -> 3540 | I21: ='Revenue Buildup'!H$15*'BS items '!I22 -> 3239.5357 | J21: ='Revenue Buildup'!I$15*'BS items '!J22 -> 3548.2248 | K21: ='Revenue Buildup'!J$15*'BS items '!K22 -> 3853.8494 | L21: ='Revenue Buildup'!K$15*'BS items '!L22 -> 4150.9489 | M21: ='Revenue Buildup'!L$15*'BS items '!M22 -> 4433.8304 | N21: ='Revenue Buildup'!M$15*'BS items '!N22 -> 4696.7236 | O21: ='Revenue Buildup'!N$15*'BS items '!O22 -> 4933.9465 | P21: ='Revenue Buildup'!O$15*'BS items '!P22 -> 5140.0782 | ... R21: ='Revenue Buildup'!Q$15*'BS items '!R22 -> 5439.7262
D22: =D21/'P&L Input'!C$11 -> 0.016680231 | E22: =E21/'P&L Input'!D$11 -> 0.015793741 | F22: =F21/'P&L Input'!E$11 -> 0.013802304 | G22: =G21/'P&L Input'!F$11 -> 0.016645193 | H22: =H21/'P&L Input'!G$11 -> 0.019815281 | I22: =AVERAGE(D22:H22) -> 0.01654735 | J22: =I22 -> 0.01654735 | K22: =J22 -> 0.01654735 | L22: =K22 -> 0.01654735 | M22: =L22 -> 0.01654735 | N22: =M22 -> 0.01654735 | O22: =N22 -> 0.01654735 | P22: =O22 -> 0.01654735 | Q22: =P22 -> 0.01654735 | R22: =Q22 -> 0.01654735
B23: ='Balance Sheet'!B28:C28 -> Current Assets
C24: Investments | D24: ='BS Input'!D29 -> 6673 | E24: ='BS Input'!E29 -> 6909 | F24: ='BS Input'!F29 -> 12915 | G24: ='BS Input'!G29 -> 12482 | H24: ='BS Input'!H29 -> 12950 | I24: ='Revenue Buildup'!H$15*'BS items '!I25 -> 13118.638 | J24: ='Revenue Buildup'!I$15*'BS items '!J25 -> 14368.687 | K24: ='Revenue Buildup'!J$15*'BS items '!K25 -> 15606.327 | L24: ='Revenue Buildup'!K$15*'BS items '!L25 -> 16809.444 | M24: ='Revenue Buildup'!L$15*'BS items '!M25 -> 17954.985 | N24: ='Revenue Buildup'!M$15*'BS items '!N25 -> 19019.582 | O24: ='Revenue Buildup'!N$15*'BS items '!O25 -> 19980.226 | P24: ='Revenue Buildup'!O$15*'BS items '!P25 -> 20814.965 | ... R24: ='Revenue Buildup'!Q$15*'BS items '!R25 -> 22028.402
D25: =D24/'P&L Input'!C$11 -> 0.054858148 | E25: =E24/'P&L Input'!D$11 -> 0.047074615 | F25: =F24/'P&L Input'!E$11 -> 0.08404373 | G25: =G24/'P&L Input'!F$11 -> 0.076581385 | H25: =H24/'P&L Input'!G$11 -> 0.072488105 | I25: =AVERAGE(D25:H25) -> 0.067009197 | J25: =I25 -> 0.067009197 | K25: =J25 -> 0.067009197 | L25: =K25 -> 0.067009197 | M25: =L25 -> 0.067009197 | N25: =M25 -> 0.067009197 | O25: =N25 -> 0.067009197 | P25: =O25 -> 0.067009197 | Q25: =P25 -> 0.067009197 | R25: =Q25 -> 0.067009197
C26: Other financial assets | D26: ='BS Input'!D33 -> 8727 | E26: ='BS Input'!E33 -> 11604 | F26: ='BS Input'!F33 -> 12085 | G26: ='BS Input'!G33 -> 13840 | H26: ='BS Input'!H33 -> 15890 | I26: ='Revenue Buildup'!H$15*'BS items '!I27 -> 15791.442 | J26: ='Revenue Buildup'!I$15*'BS items '!J27 -> 17296.178 | K26: ='Revenue Buildup'!J$15*'BS items '!K27 -> 18785.976 | L26: ='Revenue Buildup'!K$15*'BS items '!L27 -> 20234.217 | M26: ='Revenue Buildup'!L$15*'BS items '!M27 -> 21613.151 | N26: ='Revenue Buildup'!M$15*'BS items '!N27 -> 22894.65 | O26: ='Revenue Buildup'!N$15*'BS items '!O27 -> 24051.017 | P26: ='Revenue Buildup'!O$15*'BS items '!P27 -> 25055.827 | ... R26: ='Revenue Buildup'!Q$15*'BS items '!R27 -> 26516.491
D27: =D26/'P&L Input'!C$11 -> 0.071743902 | E27: =E26/'P&L Input'!D$11 -> 0.079064095 | F27: =F26/'P&L Input'!E$11 -> 0.078642546 | G27: =G26/'P&L Input'!F$11 -> 0.084913185 | H27: =H26/'P&L Input'!G$11 -> 0.088944864 | I27: =AVERAGE(D27:H27) -> 0.080661718 | J27: =I27 -> 0.080661718 | K27: =J27 -> 0.080661718 | L27: =K27 -> 0.080661718 | M27: =L27 -> 0.080661718 | N27: =M27 -> 0.080661718 | O27: =N27 -> 0.080661718 | P27: =O27 -> 0.080661718 | Q27: =P27 -> 0.080661718 | R27: =Q27 -> 0.080661718
C28: ='BS Input'!C34 -> Income tax assets (net) | D28: ='BS Input'!D34 -> 54 | E28: ='BS Input'!E34 -> 6 | F28: ='BS Input'!F34 -> 6397 | G28: ='BS Input'!G34 -> 2975 | H28: ='BS Input'!H34 -> 1835 | I28: ='Revenue Buildup'!H15*I29 -> 2765.7775 | J28: ='Revenue Buildup'!I15*J29 -> 3029.323 | K28: ='Revenue Buildup'!J15*K29 -> 3290.2522 | L28: ='Revenue Buildup'!K15*L29 -> 3543.9031 | M28: ='Revenue Buildup'!L15*M29 -> 3785.4153 | N28: ='Revenue Buildup'!M15*N29 -> 4009.8623 | O28: ='Revenue Buildup'!N15*O29 -> 4212.3931 | P28: ='Revenue Buildup'!O15*P29 -> 4388.3796 | ... R28: ='Revenue Buildup'!Q15*R29 -> 4644.2062
D29: =D28/'P&L Input'!C$11 -> 0.00044392927 | E29: =E28/'P&L Input'!D$11 -> 4.0881125e-05 | F29: =F28/'P&L Input'!E$11 -> 0.041628164 | G29: =G28/'P&L Input'!F$11 -> 0.018252654 | H29: =H28/'P&L Input'!G$11 -> 0.010271481 | I29: =AVERAGE(D29:H29) -> 0.014127422 | J29: =I29 -> 0.014127422 | K29: =J29 -> 0.014127422 | L29: =K29 -> 0.014127422 | M29: =L29 -> 0.014127422 | N29: =M29 -> 0.014127422 | O29: =N29 -> 0.014127422 | P29: =O29 -> 0.014127422 | Q29: =P29 -> 0.014127422 | R29: =Q29 -> 0.014127422
C30: Other current assets | D30: ='BS Input'!D35 -> 11313 | E30: ='BS Input'!E35 -> 14476 | F30: ='BS Input'!F35 -> 12808 | G30: ='BS Input'!G35 -> 11940 | H30: ='BS Input'!H35 -> 15145 | I30: ='Revenue Buildup'!H$15*'BS items '!I31 -> 16954.544 | J30: ='Revenue Buildup'!I$15*'BS items '!J31 -> 18570.11 | K30: ='Revenue Buildup'!J$15*'BS items '!K31 -> 20169.637 | L30: ='Revenue Buildup'!K$15*'BS items '!L31 -> 21724.547 | M30: ='Revenue Buildup'!L$15*'BS items '!M31 -> 23205.046 | N30: ='Revenue Buildup'!M$15*'BS items '!N31 -> 24580.932 | O30: ='Revenue Buildup'!N$15*'BS items '!O31 -> 25822.47 | P30: ='Revenue Buildup'!O$15*'BS items '!P31 -> 26901.288 | ... R30: ='Revenue Buildup'!Q$15*'BS items '!R31 -> 28469.536
D31: =D30/'P&L Input'!C$11 -> 0.093003181 | E31: =E30/'P&L Input'!D$11 -> 0.098632526 | F31: =F30/'P&L Input'!E$11 -> 0.083347433 | G31: =G30/'P&L Input'!F$11 -> 0.073256028 | H31: =H30/'P&L Input'!G$11 -> 0.084774699 | I31: =AVERAGE(D31:H31) -> 0.086602774 | J31: =I31 -> 0.086602774 | K31: =J31 -> 0.086602774 | L31: =K31 -> 0.086602774 | M31: =L31 -> 0.086602774 | N31: =M31 -> 0.086602774 | O31: =N31 -> 0.086602774 | P31: =O31 -> 0.086602774 | Q31: =P31 -> 0.086602774 | R31: =Q31 -> 0.086602774
B33: LIABILITIES
B35: Non-current liabilities
C36: Lease liabilities | D36: ='BS Input'!D52 -> 4602 | E36: ='BS Input'!E52 -> 7057 | F36: ='BS Input'!F52 -> 6400 | G36: ='BS Input'!G52 -> 5772 | H36: ='BS Input'!H52 -> 6016 | I36: ='Revenue Buildup'!H$15*'BS items '!I37 -> 7699.8316 | J36: ='Revenue Buildup'!I$15*'BS items '!J37 -> 8433.5335 | K36: ='Revenue Buildup'!J$15*'BS items '!K37 -> 9159.9518 | L36: ='Revenue Buildup'!K$15*'BS items '!L37 -> 9866.1074 | M36: ='Revenue Buildup'!L$15*'BS items '!M37 -> 10538.469 | N36: ='Revenue Buildup'!M$15*'BS items '!N37 -> 11163.322 | O36: ='Revenue Buildup'!N$15*'BS items '!O37 -> 11727.161 | P36: ='Revenue Buildup'!O$15*'BS items '!P37 -> 12217.101 | ... R36: ='Revenue Buildup'!Q$15*'BS items '!R37 -> 12929.314
D37: =D36/'P&L Input'!C$11 -> 0.037832639 | E37: =E36/'P&L Input'!D$11 -> 0.048083016 | F37: =F36/'P&L Input'!E$11 -> 0.041647687 | G37: =G36/'P&L Input'!F$11 -> 0.035413216 | H37: =H36/'P&L Input'!G$11 -> 0.033674783 | I37: =AVERAGE(D37:H37) -> 0.039330268 | J37: =I37 -> 0.039330268 | K37: =J37 -> 0.039330268 | L37: =K37 -> 0.039330268 | M37: =L37 -> 0.039330268 | N37: =M37 -> 0.039330268 | O37: =N37 -> 0.039330268 | P37: =O37 -> 0.039330268 | Q37: =P37 -> 0.039330268 | R37: =Q37 -> 0.039330268
C38: Other Financial liabilities | D38: ='BS Input'!D53 -> 2337 | E38: ='BS Input'!E53 -> 2058 | F38: ='BS Input'!F53 -> 2130 | G38: ='BS Input'!G53 -> 2141 | H38: ='BS Input'!H53 -> 2092 | I38: ='Revenue Buildup'!H$15*'BS items '!I39 -> 2816.8385 | J38: ='Revenue Buildup'!I$15*'BS items '!J39 -> 3085.2495 | K38: ='Revenue Buildup'!J$15*'BS items '!K39 -> 3350.996 | L38: ='Revenue Buildup'!K$15*'BS items '!L39 -> 3609.3297 | M38: ='Revenue Buildup'!L$15*'BS items '!M39 -> 3855.3006 | N38: ='Revenue Buildup'!M$15*'BS items '!N39 -> 4083.8912 | O38: ='Revenue Buildup'!N$15*'BS items '!O39 -> 4290.1611 | P38: ='Revenue Buildup'!O$15*'BS items '!P39 -> 4469.3966 | ... R38: ='Revenue Buildup'!Q$15*'BS items '!R39 -> 4729.9462
D39: =D38/'P&L Input'!C$11 -> 0.019212272 | E39: =E38/'P&L Input'!D$11 -> 0.014022226 | F39: =F38/'P&L Input'!E$11 -> 0.013860871 | G39: =G38/'P&L Input'!F$11 -> 0.013135775 | H39: =H38/'P&L Input'!G$11 -> 0.011710048 | I39: =AVERAGE(D39:H39) -> 0.014388238 | J39: =I39 -> 0.014388238 | K39: =J39 -> 0.014388238 | L39: =K39 -> 0.014388238 | M39: =L39 -> 0.014388238 | N39: =M39 -> 0.014388238 | O39: =N39 -> 0.014388238 | P39: =O39 -> 0.014388238 | Q39: =P39 -> 0.014388238 | R39: =Q39 -> 0.014388238
C40: ='BS Input'!C54 -> Other non current liabilities | D40: ='BS Input'!D54 -> 451 | E40: ='BS Input'!E54 -> 500 | F40: ='BS Input'!F54 -> 235 | G40: ='BS Input'!G54 -> 215 | H40: ='BS Input'!H54 -> 561 | I40: ='Revenue Buildup'!H$15*'BS items '!I41 -> 513.04298 | J40: ='Revenue Buildup'!I$15*'BS items '!J41 -> 561.92984 | K40: ='Revenue Buildup'!J$15*'BS items '!K41 -> 610.3314 | L40: ='Revenue Buildup'!K$15*'BS items '!L41 -> 657.38283 | M40: ='Revenue Buildup'!L$15*'BS items '!M41 -> 702.18258 | N40: ='Revenue Buildup'!M$15*'BS items '!N41 -> 743.81678 | O40: ='Revenue Buildup'!N$15*'BS items '!O41 -> 781.3856 | P40: ='Revenue Buildup'!O$15*'BS items '!P41 -> 814.03054 | ... R40: ='Revenue Buildup'!Q$15*'BS items '!R41 -> 861.48558
D41: =D40/'P&L Input'!C$11 -> 0.0037076315 | E41: =E40/'P&L Input'!D$11 -> 0.0034067604 | F41: =F40/'P&L Input'!E$11 -> 0.001529251 | G41: =G40/'P&L Input'!F$11 -> 0.0013190993 | H41: =H40/'P&L Input'!G$11 -> 0.0031402183 | I41: =AVERAGE(D41:H41) -> 0.0026205921 | J41: =I41 -> 0.0026205921 | K41: =J41 -> 0.0026205921 | L41: =K41 -> 0.0026205921 | M41: =L41 -> 0.0026205921 | N41: =M41 -> 0.0026205921 | O41: =N41 -> 0.0026205921 | P41: =O41 -> 0.0026205921 | Q41: =P41 -> 0.0026205921 | R41: =Q41 -> 0.0026205921
C42: Deferred Tax Liability(net) | D42: ='BS Input'!D55 -> 1156 | E42: ='BS Input'!E55 -> 1220 | F42: ='BS Input'!F55 -> 1794 | G42: ='BS Input'!G55 -> 1722 | H42: ='BS Input'!H55 -> 1679 | I42: ='Revenue Buildup'!H$15*'BS items '!I43 -> 1936.3414 | J42: ='Revenue Buildup'!I$15*'BS items '!J43 -> 2120.8516 | K42: ='Revenue Buildup'!J$15*'BS items '!K43 -> 2303.5302 | L42: ='Revenue Buildup'!K$15*'BS items '!L43 -> 2481.113 | M42: ='Revenue Buildup'!L$15*'BS items '!M43 -> 2650.1975 | N42: ='Revenue Buildup'!M$15*'BS items '!N43 -> 2807.3345 | O42: ='Revenue Buildup'!N$15*'BS items '!O43 -> 2949.1278 | P42: ='Revenue Buildup'!O$15*'BS items '!P43 -> 3072.3373 | ... R42: ='Revenue Buildup'!Q$15*'BS items '!R43 -> 3251.4434
D43: =D42/'P&L Input'!C$11 -> 0.0095033747 | E43: =E42/'P&L Input'!D$11 -> 0.0083124953 | F43: =F42/'P&L Input'!E$11 -> 0.011674367 | G43: =G42/'P&L Input'!F$11 -> 0.010565065 | H43: =H42/'P&L Input'!G$11 -> 0.0093982648 | I43: =AVERAGE(D43:H43) -> 0.0098907135 | J43: =I43 -> 0.0098907135 | K43: =J43 -> 0.0098907135 | L43: =K43 -> 0.0098907135 | M43: =L43 -> 0.0098907135 | N43: =M43 -> 0.0098907135 | O43: =N43 -> 0.0098907135 | P43: =O43 -> 0.0098907135 | Q43: =P43 -> 0.0098907135 | R43: =Q43 -> 0.0098907135
B45: Current Liabilities
C46: Lease liabilities | D46: ='BS Input'!D61 -> 872 | E46: ='BS Input'!E61 -> 1242 | F46: ='BS Input'!F61 -> 1959 | G46: ='BS Input'!G61 -> 2455 | H46: ='BS Input'!H61 -> 3160 | I46: ='Revenue Buildup'!H$15*'BS items '!I47 -> 2393.5141 | J46: ='Revenue Buildup'!I$15*'BS items '!J47 -> 2621.5873 | K46: ='Revenue Buildup'!J$15*'BS items '!K47 -> 2847.3965 | L46: ='Revenue Buildup'!K$15*'BS items '!L47 -> 3066.9069 | M46: ='Revenue Buildup'!L$15*'BS items '!M47 -> 3275.9125 | N46: ='Revenue Buildup'!M$15*'BS items '!N47 -> 3470.1497 | O46: ='Revenue Buildup'!N$15*'BS items '!O47 -> 3645.4206 | P46: ='Revenue Buildup'!O$15*'BS items '!P47 -> 3797.7199 | ... R46: ='Revenue Buildup'!Q$15*'BS items '!R47 -> 4019.1133
D47: =D46/'P&L Input'!C$11 -> 0.0071686356 | E47: =E46/'P&L Input'!D$11 -> 0.0084623928 | F47: =F46/'P&L Input'!E$11 -> 0.012748097 | G47: =G46/'P&L Input'!F$11 -> 0.015062274 | H47: =H46/'P&L Input'!G$11 -> 0.017688217 | I47: =AVERAGE(D47:H47) -> 0.012225923 | J47: =I47 -> 0.012225923 | K47: =J47 -> 0.012225923 | L47: =K47 -> 0.012225923 | M47: =L47 -> 0.012225923 | N47: =M47 -> 0.012225923 | O47: =N47 -> 0.012225923 | P47: =O47 -> 0.012225923 | Q47: =P47 -> 0.012225923 | R47: =Q47 -> 0.012225923
C48: Other financial liabilities | D48: ='BS Input'!D63 -> 15837 | E48: ='BS Input'!E63 -> 18558 | F48: ='BS Input'!F63 -> 16959 | G48: ='BS Input'!G63 -> 18138 | H48: ='BS Input'!H63 -> 21483 | I48: ='Revenue Buildup'!H$15*'BS items '!I49 -> 23435.464 | J48: ='Revenue Buildup'!I$15*'BS items '!J49 -> 25668.583 | K48: ='Revenue Buildup'!J$15*'BS items '!K49 -> 27879.534 | L48: ='Revenue Buildup'!K$15*'BS items '!L49 -> 30028.813 | M48: ='Revenue Buildup'!L$15*'BS items '!M49 -> 32075.235 | N48: ='Revenue Buildup'!M$15*'BS items '!N49 -> 33977.058 | O48: ='Revenue Buildup'!N$15*'BS items '!O49 -> 35693.177 | P48: ='Revenue Buildup'!O$15*'BS items '!P49 -> 37184.376 | ... R48: ='Revenue Buildup'!Q$15*'BS items '!R49 -> 39352.091
D49: =D48/'P&L Input'!C$11 -> 0.13019459 | E49: =E48/'P&L Input'!D$11 -> 0.12644532 | F49: =F48/'P&L Input'!E$11 -> 0.11035986 | G49: =G48/'P&L Input'!F$11 -> 0.1112829 | H49: =H48/'P&L Input'!G$11 -> 0.12025189 | I49: =AVERAGE(D49:H49) -> 0.11970691 | J49: =I49 -> 0.11970691 | K49: =J49 -> 0.11970691 | L49: =K49 -> 0.11970691 | M49: =L49 -> 0.11970691 | N49: =M49 -> 0.11970691 | O49: =N49 -> 0.11970691 | P49: =O49 -> 0.11970691 | Q49: =P49 -> 0.11970691 | R49: =Q49 -> 0.11970691
C50: Other current liabilities | D50: ='BS Input'!D64 -> 9178 | E50: ='BS Input'!E64 -> 10830 | F50: ='BS Input'!F64 -> 10539 | G50: ='BS Input'!G64 -> 11765 | H50: ='BS Input'!H64 -> 15779 | I50: ='Revenue Buildup'!H$15*'BS items '!I51 -> 14813.407 | J50: ='Revenue Buildup'!I$15*'BS items '!J51 -> 16224.947 | K50: ='Revenue Buildup'!J$15*'BS items '!K51 -> 17622.475 | L50: ='Revenue Buildup'!K$15*'BS items '!L51 -> 18981.021 | M50: ='Revenue Buildup'!L$15*'BS items '!M51 -> 20274.551 | N50: ='Revenue Buildup'!M$15*'BS items '!N51 -> 21476.681 | O50: ='Revenue Buildup'!N$15*'BS items '!O51 -> 22561.429 | P50: ='Revenue Buildup'!O$15*'BS items '!P51 -> 23504.007 | ... R50: ='Revenue Buildup'!Q$15*'BS items '!R51 -> 24874.205
D51: =D50/'P&L Input'!C$11 -> 0.075451534 | E51: =E50/'P&L Input'!D$11 -> 0.07379043 | F51: =F50/'P&L Input'!E$11 -> 0.068582026 | G51: =G50/'P&L Input'!F$11 -> 0.072182342 | H51: =H50/'P&L Input'!G$11 -> 0.088323538 | I51: =AVERAGE(D51:H51) -> 0.075665974 | J51: =I51 -> 0.075665974 | K51: =J51 -> 0.075665974 | L51: =K51 -> 0.075665974 | M51: =L51 -> 0.075665974 | N51: =M51 -> 0.075665974 | O51: =N51 -> 0.075665974 | P51: =O51 -> 0.075665974 | Q51: =P51 -> 0.075665974 | R51: =Q51 -> 0.075665974
C52: Provisions | D52: ='BS Input'!D65 -> 975 | E52: ='BS Input'!E65 -> 1307 | F52: ='BS Input'!F65 -> 1796 | G52: ='BS Input'!G65 -> 1475 | H52: ='BS Input'!H65 -> 1512 | I52: ='Revenue Buildup'!H$15*'BS items '!I53 -> 1805.8617 | J52: ='Revenue Buildup'!I$15*'BS items '!J53 -> 1977.9387 | K52: ='Revenue Buildup'!J$15*'BS items '!K53 -> 2148.3075 | L52: ='Revenue Buildup'!K$15*'BS items '!L53 -> 2313.924 | M52: ='Revenue Buildup'!L$15*'BS items '!M53 -> 2471.6148 | N52: ='Revenue Buildup'!M$15*'BS items '!N53 -> 2618.1632 | O52: ='Revenue Buildup'!N$15*'BS items '!O53 -> 2750.4018 | P52: ='Revenue Buildup'!O$15*'BS items '!P53 -> 2865.3088 | ... R52: ='Revenue Buildup'!Q$15*'BS items '!R53 -> 3032.3459
D53: =D52/'P&L Input'!C$11 -> 0.0080153895 | E53: =E52/'P&L Input'!D$11 -> 0.0089052716 | F53: =F52/'P&L Input'!E$11 -> 0.011687382 | G53: =G52/'P&L Input'!F$11 -> 0.0090496349 | H53: =H52/'P&L Input'!G$11 -> 0.0084634761 | I53: =AVERAGE(D53:H53) -> 0.0092242308 | J53: =I53 -> 0.0092242308 | K53: =J53 -> 0.0092242308 | L53: =K53 -> 0.0092242308 | M53: =L53 -> 0.0092242308 | N53: =M53 -> 0.0092242308 | O53: =N53 -> 0.0092242308 | P53: =O53 -> 0.0092242308 | Q53: =P53 -> 0.0092242308 | R53: =Q53 -> 0.0092242308
C54: Current Tax Liabilities(net) | D54: ='BS Input'!D66 -> 2607 | E54: ='BS Input'!E66 -> 3384 | F54: ='BS Input'!F66 -> 3585 | G54: ='BS Input'!G66 -> 4853 | H54: ='BS Input'!H66 -> 5644 | I54: ='Revenue Buildup'!H$15*'BS items '!I55 -> 5058.2211 | J54: ='Revenue Buildup'!I$15*'BS items '!J55 -> 5540.2091 | K54: ='Revenue Buildup'!J$15*'BS items '!K55 -> 6017.4123 | L54: ='Revenue Buildup'!K$15*'BS items '!L55 -> 6481.3044 | M54: ='Revenue Buildup'!L$15*'BS items '!M55 -> 6922.9965 | N54: ='Revenue Buildup'!M$15*'BS items '!N55 -> 7333.4787 | O54: ='Revenue Buildup'!N$15*'BS items '!O55 -> 7703.8792 | P54: ='Revenue Buildup'!O$15*'BS items '!P55 -> 8025.734 | ... R54: ='Revenue Buildup'!Q$15*'BS items '!R55 -> 8493.6052
D55: =D54/'P&L Input'!C$11 -> 0.021431919 | E55: =E54/'P&L Input'!D$11 -> 0.023056954 | F55: =F54/'P&L Input'!E$11 -> 0.023329212 | G55: =G54/'P&L Input'!F$11 -> 0.029774833 | H55: =H54/'P&L Input'!G$11 -> 0.031592499 | I55: =AVERAGE(D55:H55) -> 0.025837083 | J55: =I55 -> 0.025837083 | K55: =J55 -> 0.025837083 | L55: =K55 -> 0.025837083 | M55: =L55 -> 0.025837083 | N55: =M55 -> 0.025837083 | O55: =N55 -> 0.025837083 | P55: =O55 -> 0.025837083 | Q55: =P55 -> 0.025837083 | R55: =Q55 -> 0.025837083

Sheet Working Capital
B2: Infosys Limited
P6: (INR in Crores)
B7: Working Capital
B8: Particulars | C8: ='BS items '!D8 -> 2022 | D8: ='BS items '!E8 -> 2023 | E8: ='BS items '!F8 -> 2024 | F8: ='BS items '!G8 -> 2025 | G8: ='BS items '!H8 -> 2026 | H8: ='BS items '!I8 -> 2027 | I8: ='BS items '!J8 -> 2028 | J8: ='BS items '!K8 -> 2029 | ... Q8: ='BS items '!R8 -> 2036
C9: Audited | D9: Audited | E9: Audited | F9: Audited | G9: Audited | H9: Estimated | I9: Projected | J9: Projected | K9: Projected | L9: Projected | M9: Projected | N9: Projected | O9: Projected | P9: Projected | Q9: Projected
B11: Trade Receivables | C11: ='BS Input'!D30 -> 22698 | D11: ='BS Input'!E30 -> 25424 | E11: ='BS Input'!F30 -> 30193 | F11: ='BS Input'!G30 -> 31158 | G11: ='BS Input'!H30 -> 35234 | H11: =H12*'Revenue Buildup'!H15 -> 36158.374 | I11: =I12*'Revenue Buildup'!I15 -> 39603.834 | J11: =J12*'Revenue Buildup'!J15 -> 43015.091 | K11: =K12*'Revenue Buildup'!K15 -> 46331.195 | L11: =L12*'Revenue Buildup'!L15 -> 49488.603 | M11: =M12*'Revenue Buildup'!M15 -> 52422.908 | N11: =N12*'Revenue Buildup'!N15 -> 55070.693 | O11: =O12*'Revenue Buildup'!O15 -> 57371.452 | ... Q11: =Q12*'Revenue Buildup'!Q15 -> 60715.999
C12: =C11/'P&L Input'!C14 -> 0.18314291 | D12: =D11/'P&L Input'!D14 -> 0.17009661 | E12: =E11/'P&L Input'!E14 -> 0.19063524 | F12: =F11/'P&L Input'!F14 -> 0.18703404 | G12: =G11/'P&L Input'!G14 -> 0.19256498 | H12: =AVERAGE(C12:G12) -> 0.18469476 | I12: =H12 -> 0.18469476 | J12: =I12 -> 0.18469476 | K12: =J12 -> 0.18469476 | L12: =K12 -> 0.18469476 | M12: =L12 -> 0.18469476 | N12: =M12 -> 0.18469476 | O12: =N12 -> 0.18469476 | P12: =O12 -> 0.18469476 | Q12: =P12 -> 0.18469476
B13: Trade Payables | C13: ='BS Input'!D62 -> 4134 | D13: ='BS Input'!E62 -> 3865 | E13: ='BS Input'!F62 -> 3956 | F13: ='BS Input'!G62 -> 4164 | G13: ='BS Input'!H62 -> 4744 | H13: =H14*'Revenue Buildup'!H15 -> 5290.3927 | I13: =I14*'Revenue Buildup'!I15 -> 5794.5039 | J13: =J14*'Revenue Buildup'!J15 -> 6293.6107 | K13: =K14*'Revenue Buildup'!K15 -> 6778.7954 | L13: =L14*'Revenue Buildup'!L15 -> 7240.7611 | M13: =M14*'Revenue Buildup'!M15 -> 7670.0843 | N13: =N14*'Revenue Buildup'!N15 -> 8057.4862 | O13: =O14*'Revenue Buildup'!O15 -> 8394.114 | ... Q13: =Q14*'Revenue Buildup'!Q15 -> 8883.4605
C14: =C13/'P&L Input'!C14 -> 0.033355926 | D14: =D13/'P&L Input'!D14 -> 0.025858378 | E14: =E13/'P&L Input'!E14 -> 0.024977744 | F14: =F13/'P&L Input'!F14 -> 0.024995498 | G14: =G13/'P&L Input'!G14 -> 0.025927464 | H14: =AVERAGE(C14:G14) -> 0.027023002 | I14: =H14 -> 0.027023002 | J14: =I14 -> 0.027023002 | K14: =J14 -> 0.027023002 | L14: =K14 -> 0.027023002 | M14: =L14 -> 0.027023002 | N14: =M14 -> 0.027023002 | O14: =N14 -> 0.027023002 | P14: =O14 -> 0.027023002 | Q14: =P14 -> 0.027023002
B15: Provision | C15: ='Balance Sheet'!D66 -> 975 | D15: ='Balance Sheet'!E66 -> 1307 | E15: ='Balance Sheet'!F66 -> 1796 | F15: ='Balance Sheet'!G66 -> 1475 | G15: ='Balance Sheet'!H66 -> 1512 | H15: ='Balance Sheet'!I66 -> 1805.8617 | I15: ='Balance Sheet'!J66 -> 1977.9387 | J15: ='Balance Sheet'!K66 -> 2148.3075 | ... Q15: ='Balance Sheet'!R66 -> 3032.3459
B17: Other financial and non-financial liabilities | C17: ='Balance Sheet'!D55+'Balance Sheet'!D65+'Balance Sheet'!D54+'Balance Sheet'!D64 -> 27803 | D17: ='Balance Sheet'!E55+'Balance Sheet'!E65+'Balance Sheet'!E54+'Balance Sheet'!E64 -> 31946 | E17: ='Balance Sheet'!F55+'Balance Sheet'!F65+'Balance Sheet'!F54+'Balance Sheet'!F64 -> 29863 | F17: ='Balance Sheet'!G55+'Balance Sheet'!G65+'Balance Sheet'!G54+'Balance Sheet'!G64 -> 32259 | G17: ='Balance Sheet'!H55+'Balance Sheet'!H65+'Balance Sheet'!H54+'Balance Sheet'!H64 -> 39915 | H17: ='Balance Sheet'!I55+'Balance Sheet'!I65+'Balance Sheet'!I54+'Balance Sheet'!I64 -> 41578.752 | I17: ='Balance Sheet'!J55+'Balance Sheet'!J65+'Balance Sheet'!J54+'Balance Sheet'!J64 -> 45540.71 | J17: ='Balance Sheet'!K55+'Balance Sheet'!K65+'Balance Sheet'!K54+'Balance Sheet'!K64 -> 49463.337 | ... Q17: ='Balance Sheet'!R55+'Balance Sheet'!R65+'Balance Sheet'!R54+'Balance Sheet'!R64 -> 69817.728
B19: Other financial and non-financial assets | C19: ='Balance Sheet'!D21+'Balance Sheet'!D24+'Balance Sheet'!D34+'Balance Sheet'!D36 -> 23529 | D19: ='Balance Sheet'!E21+'Balance Sheet'!E24+'Balance Sheet'!E34+'Balance Sheet'!E36 -> 31196 | E19: ='Balance Sheet'!F21+'Balance Sheet'!F24+'Balance Sheet'!F34+'Balance Sheet'!F36 -> 30119 | F19: ='Balance Sheet'!G21+'Balance Sheet'!G24+'Balance Sheet'!G34+'Balance Sheet'!G36 -> 32004 | G19: ='Balance Sheet'!H21+'Balance Sheet'!H24+'Balance Sheet'!H34+'Balance Sheet'!H36 -> 37351 | H19: ='Balance Sheet'!I21+'Balance Sheet'!I24+'Balance Sheet'!I34+'Balance Sheet'!I36 -> 39444.936 | I19: ='Balance Sheet'!J21+'Balance Sheet'!J24+'Balance Sheet'!J34+'Balance Sheet'!J36 -> 43203.566 | J19: ='Balance Sheet'!K21+'Balance Sheet'!K24+'Balance Sheet'!K34+'Balance Sheet'!K36 -> 46924.885 | ... Q19: ='Balance Sheet'!R21+'Balance Sheet'!R24+'Balance Sheet'!R34+'Balance Sheet'!R36 -> 66234.691
B22: Net Working Capital | C22: =C11-C13-C15-C17+C19 -> 13315 | D22: =D11-D13-D15-D17+D19 -> 19502 | E22: =E11-E13-E15-E17+E19 -> 24697 | F22: =F11-F13-F15-F17+F19 -> 25264 | G22: =G11-G13-G15-G17+G19 -> 26414 | H22: =H11-H13-H15-H17+H19 -> 26928.303 | I22: =I11-I13-I15-I17+I19 -> 29494.248 | J22: =J11-J13-J15-J17+J19 -> 32034.721 | ... Q22: =Q11-Q13-Q15-Q17+Q19 -> 45217.156
B24: net change in working capital | C24: =SUM('CF Input'!D26:D29) -> -1424 | D24: =SUM('CF Input'!E26:E29) -> -6344 | E24: =SUM('CF Input'!F26:F29) -> -5082 | F24: =SUM('CF Input'!G26:G29) -> -295 | G24: =SUM('CF Input'!H26:H29) -> -2639 | H24: =H22-G22 -> 514.30294 | I24: =I22-H22 -> 2565.9453 | J24: =J22-I22 -> 2540.4728 | K24: =K22-J22 -> 2469.6087 | L24: =L22-K22 -> 2351.4232 | M24: =M22-L22 -> 2185.2718 | N24: =N22-M22 -> 1971.8906 | O24: =O22-N22 -> 1713.4487 | ... Q24: =Q22-P22 -> 1077.2349

Sheet Income Statement
B2: Infosys Limited
P6: (INR in Crores)
B7: Income Statement
B8: Particulars | C8: =FAS!C8 -> 2022 | D8: =FAS!D8 -> 2023 | E8: =FAS!E8 -> 2024 | F8: =FAS!F8 -> 2025 | G8: =FAS!G8 -> 2026 | H8: =FAS!H8 -> 2027 | I8: =FAS!I8 -> 2028 | J8: =FAS!J8 -> 2029 | ... Q8: =FAS!Q8 -> 2036
C9: Audited | D9: Audited | E9: Audited | F9: Audited | G9: Audited | H9: Estimated | I9: Projected | J9: Projected | K9: Projected | L9: Projected | M9: Projected | N9: Projected | O9: Projected | P9: Projected | Q9: Projected
B11: Revenue from Operations | C11: ='P&L Input'!C11 -> 121641 | D11: ='P&L Input'!D11 -> 146767 | E11: ='P&L Input'!E11 -> 153670 | F11: ='P&L Input'!F11 -> 162990 | G11: ='P&L Input'!G11 -> 178650 | H11: ='Revenue Buildup'!H11 -> 184226.18 | I11: ='Revenue Buildup'!I11 -> 201780.73 | J11: ='Revenue Buildup'!J11 -> 219161.02 | K11: ='Revenue Buildup'!K11 -> 236056.5 | L11: ='Revenue Buildup'!L11 -> 252143.43 | M11: ='Revenue Buildup'!M11 -> 267093.65 | N11: ='Revenue Buildup'!N11 -> 280584.06 | O11: ='Revenue Buildup'!O11 -> 292306.38 | ... Q11: ='Revenue Buildup'!Q11 -> 309346.78
B14: Total Income | C14: =SUM(C11:C13) -> 121641 | D14: =SUM(D11:D13) -> 146767 | E14: =SUM(E11:E13) -> 153670 | F14: =SUM(F11:F13) -> 162990 | G14: =SUM(G11:G13) -> 178650 | H14: =SUM(H11:H13) -> 184226.18 | I14: =SUM(I11:I13) -> 201780.73 | J14: =SUM(J11:J13) -> 219161.02 | ... Q14: =SUM(Q11:Q13) -> 309346.78
B16: Expenses
B18: ='P&L Input'!B17 -> Employee benefit expenses | C18: ='P&L Input'!C17 -> 63986 | D18: ='P&L Input'!D17 -> 78359 | E18: ='P&L Input'!E17 -> 82620 | F18: ='P&L Input'!F17 -> 85950 | G18: ='P&L Input'!G17 -> 95094 | H18: ='Cost Buildup'!H13 -> 104041.76 | I18: ='Cost Buildup'!I13 -> 113955.7 | J18: ='Cost Buildup'!J13 -> 123771.22 | K18: ='Cost Buildup'!K13 -> 133312.94 | L18: ='Cost Buildup'!L13 -> 142398.04 | M18: ='Cost Buildup'!M13 -> 150841.18 | N18: ='Cost Buildup'!N13 -> 158459.89 | O18: ='Cost Buildup'!O13 -> 165080.07 | ... Q18: ='Cost Buildup'!Q13 -> 174703.64
B19: ='P&L Input'!B18 -> Cost of technical sub-contractors | C19: ='P&L Input'!C18 -> 12606 | D19: ='P&L Input'!D18 -> 14062 | E19: ='P&L Input'!E18 -> 12232 | F19: ='P&L Input'!F18 -> 12937 | G19: ='P&L Input'!G18 -> 15421 | H19: ='Cost Buildup'!H16 -> 17413.532 | I19: ='Cost Buildup'!I16 -> 19072.834 | J19: ='Cost Buildup'!J16 -> 20715.663 | K19: ='Cost Buildup'!K16 -> 22312.667 | L19: ='Cost Buildup'!L16 -> 23833.245 | M19: ='Cost Buildup'!M16 -> 25246.379 | N19: ='Cost Buildup'!N16 -> 26521.527 | O19: ='Cost Buildup'!O16 -> 27629.551 | ... Q19: ='Cost Buildup'!Q16 -> 29240.254
B20: ='P&L Input'!B19 -> Travel expenses | C20: ='P&L Input'!C19 -> 827 | D20: ='P&L Input'!D19 -> 1525 | E20: ='P&L Input'!E19 -> 1759 | F20: ='P&L Input'!F19 -> 1894 | G20: ='P&L Input'!G19 -> 2097 | H20: ='Cost Buildup'!H19 -> 2035.8232 | I20: ='Cost Buildup'!I19 -> 2229.8128 | J20: ='Cost Buildup'!J19 -> 2421.8766 | K20: ='Cost Buildup'!K19 -> 2608.583 | L20: ='Cost Buildup'!L19 -> 2786.3544 | M20: ='Cost Buildup'!M19 -> 2951.5645 | N20: ='Cost Buildup'!N19 -> 3100.6426 | O20: ='Cost Buildup'!O19 -> 3230.1821 | ... Q20: ='Cost Buildup'!Q19 -> 3418.49
B21: ='P&L Input'!B20 -> Cost of software packages and others | C21: ='P&L Input'!C20 -> 6811 | D21: ='P&L Input'!D20 -> 10902 | E21: ='P&L Input'!E20 -> 13515 | F21: ='P&L Input'!F20 -> 15911 | G21: ='P&L Input'!G20 -> 15722 | H21: ='Cost Buildup'!H22 -> 15812.476 | I21: ='Cost Buildup'!I22 -> 17319.216 | J21: ='Cost Buildup'!J22 -> 18810.999 | K21: ='Cost Buildup'!K22 -> 20261.169 | L21: ='Cost Buildup'!L22 -> 21641.94 | M21: ='Cost Buildup'!M22 -> 22925.146 | N21: ='Cost Buildup'!N22 -> 24083.053 | O21: ='Cost Buildup'!O22 -> 25089.202 | ... Q21: ='Cost Buildup'!Q22 -> 26551.811
B22: ='P&L Input'!B21 -> Communication expenses | C22: ='P&L Input'!C21 -> 611 | D22: ='P&L Input'!D21 -> 713 | E22: ='P&L Input'!E21 -> 677 | F22: ='P&L Input'!F21 -> 620 | G22: ='P&L Input'!G21 -> 603 | H22: ='Cost Buildup'!H25 -> 840.48742 | I22: ='Cost Buildup'!I25 -> 920.57583 | J22: ='Cost Buildup'!J25 -> 999.86918 | K22: ='Cost Buildup'!K25 -> 1076.9507 | L22: ='Cost Buildup'!L25 -> 1150.3434 | M22: ='Cost Buildup'!M25 -> 1218.5503 | N22: ='Cost Buildup'!N25 -> 1280.097 | O22: ='Cost Buildup'!O25 -> 1333.5772 | ... Q22: ='Cost Buildup'!Q25 -> 1411.32
B23: ='P&L Input'!B22 -> Consultancy and professional charges | C23: ='P&L Input'!C22 -> 1885 | D23: ='P&L Input'!D22 -> 1684 | E23: ='P&L Input'!E22 -> 1726 | F23: ='P&L Input'!F22 -> 1655 | G23: ='P&L Input'!G22 -> 2090 | H23: ='Cost Buildup'!H28 -> 2351.4416 | I23: ='Cost Buildup'!I28 -> 2575.5059 | J23: ='Cost Buildup'!J28 -> 2797.3459 | K23: ='Cost Buildup'!K28 -> 3012.9978 | L23: ='Cost Buildup'!L28 -> 3218.3295 | M23: ='Cost Buildup'!M28 -> 3409.1525 | N23: ='Cost Buildup'!N28 -> 3581.3425 | O23: ='Cost Buildup'!O28 -> 3730.9648 | ... Q23: ='Cost Buildup'!Q28 -> 3948.4666
B24: ='P&L Input'!B23 -> Other expenses | C24: ='P&L Input'!C23 -> 3424 | D24: ='P&L Input'!D23 -> 4392 | E24: ='P&L Input'!E23 -> 4716 | F24: ='P&L Input'!F23 -> 4787 | G24: ='P&L Input'!G23 -> 5343 | H24: ='Cost Buildup'!H31 -> 5796.47 | I24: ='Cost Buildup'!I31 -> 6348.8042 | J24: ='Cost Buildup'!J31 -> 6895.6554 | K24: ='Cost Buildup'!K31 -> 7427.2527 | L24: ='Cost Buildup'!L31 -> 7933.4099 | M24: ='Cost Buildup'!M31 -> 8403.802 | N24: ='Cost Buildup'!N31 -> 8828.2627 | O24: ='Cost Buildup'!O31 -> 9197.0922 | ... Q24: ='Cost Buildup'!Q31 -> 9733.2494
B25: ='P&L Input'!B24 -> Total Expenses | C25: =SUM(C18:C24) -> 90150 | D25: =SUM(D18:D24) -> 111637 | E25: =SUM(E18:E24) -> 117245 | F25: =SUM(F18:F24) -> 123754 | G25: =SUM(G18:G24) -> 136370 | H25: =SUM(H18:H24) -> 148291.99 | I25: =SUM(I18:I24) -> 162422.45 | J25: =SUM(J18:J24) -> 176412.63 | ... Q25: =SUM(Q18:Q24) -> 249007.23
B27: EBITDA | C27: =C14-C25 -> 31491 | D27: =D14-D25 -> 35130 | E27: =E14-E25 -> 36425 | F27: =F14-F25 -> 39236 | G27: =G14-G25 -> 42280 | H27: =H14-H18-H24 -> 74387.947 | I27: =I14-I18-I24 -> 81476.229 | J27: =J14-J18-J24 -> 88494.144 | K27: =K14-K18-K24 -> 95316.301 | L27: =L14-L18-L24 -> 101811.98 | M27: =M14-M18-M24 -> 107848.67 | N27: =N14-N18-N24 -> 113295.91 | O27: =O14-O18-O24 -> 118029.22 | ... Q27: =Q14-Q18-Q24 -> 124909.89
B29: Depreciation & Amortisation | C29: ='P&L Input'!C28 -> 3476 | D29: ='P&L Input'!D28 -> 4225 | E29: ='P&L Input'!E28 -> 4678 | F29: ='P&L Input'!F28 -> 4812 | G29: ='P&L Input'!G28 -> 4902 | H29: =FAS!H161 -> 3083.6 | I29: =FAS!I161 -> 3083.6 | J29: =FAS!J161 -> 3083.6 | K29: =FAS!K161 -> 3206.944 | L29: =FAS!L161 -> 3206.944 | M29: =FAS!M161 -> 3206.944 | N29: =FAS!N161 -> 3335.2218 | O29: =FAS!O161 -> 3335.2218 | ... Q29: =FAS!Q161 -> 3468.6306
B31: EBIT | C31: =C27-C29 -> 28015 | D31: =D27-D29 -> 30905 | E31: =E27-E29 -> 31747 | F31: =F27-F29 -> 34424 | G31: =G27-G29 -> 37378 | H31: =H27-H29 -> 71304.347 | I31: =I27-I29 -> 78392.629 | J31: =J27-J29 -> 85410.544 | ... Q31: =Q27-Q29 -> 121441.26
B33: Other Income, net | C33: ='P&L Input'!C12 -> 2295 | D33: ='P&L Input'!D12 -> 2701 | E33: ='P&L Input'!E12 -> 4711 | F33: ='P&L Input'!F12 -> 3600 | G33: ='P&L Input'!G12 -> 4322 | H33: ='Revenue Buildup'!H18 -> 4452.554 | I33: ='Revenue Buildup'!I18 -> 4876.8291 | J33: ='Revenue Buildup'!J18 -> 5296.8924 | K33: ='Revenue Buildup'!K18 -> 5705.2385 | L33: ='Revenue Buildup'!L18 -> 6094.0427 | M33: ='Revenue Buildup'!M18 -> 6455.3741 | N33: ='Revenue Buildup'!N18 -> 6781.4232 | O33: ='Revenue Buildup'!O18 -> 7064.7393 | ... Q33: ='Revenue Buildup'!Q18 -> 7476.5881
B34: Finance Costs | C34: ='P&L Input'!C32 -> 200 | D34: ='P&L Input'!D32 -> 284 | E34: ='P&L Input'!E32 -> 470 | F34: ='P&L Input'!F32 -> 416 | G34: ='P&L Input'!G32 -> 416 | H34: ='Cost Buildup'!H34 -> 8727.0051 | I34: ='Cost Buildup'!I34 -> 9558.5843 | J34: ='Cost Buildup'!J34 -> 10381.908 | K34: ='Cost Buildup'!K34 -> 11182.267 | L34: ='Cost Buildup'!L34 -> 11944.323 | M34: ='Cost Buildup'!M34 -> 12652.532 | N34: ='Cost Buildup'!N34 -> 13291.588 | O34: ='Cost Buildup'!O34 -> 13846.888 | ... Q34: ='Cost Buildup'!Q34 -> 14654.111
B36: Profit before exceptional items | C36: =C31+C33-C34 -> 30110 | D36: =D31+D33-D34 -> 33322 | E36: =E31+E33-E34 -> 35988 | F36: =F31+F33-F34 -> 37608 | G36: =G31+G33-G34 -> 41284 | H36: =H31+H33-H34 -> 67029.895 | I36: =I31+I33-I34 -> 73710.873 | J36: =J31+J33-J34 -> 80325.528 | ... Q36: =Q31+Q33-Q34 -> 114263.74
B38: Exceptional items | C38: ='P&L Input'!C36 -> 0 | D38: ='P&L Input'!D36 -> 0 | E38: ='P&L Input'!E36 -> 0 | F38: ='P&L Input'!F36 -> 0 | G38: ='P&L Input'!G36 -> 1289 | H38: 0 | I38: =H38 -> 0 | J38: =I38 -> 0 | K38: =J38 -> 0 | L38: =K38 -> 0 | M38: =L38 -> 0 | N38: =M38 -> 0 | O38: =N38 -> 0 | P38: =O38 -> 0 | Q38: =P38 -> 0
B40: Profit before Tax | C40: =C36-C38 -> 30110 | D40: =D36-D38 -> 33322 | E40: =E36-E38 -> 35988 | F40: =F36-F38 -> 37608 | G40: =G36-G38 -> 39995 | H40: =H36-H38 -> 67029.895 | I40: =I36-I38 -> 73710.873 | J40: =J36-J38 -> 80325.528 | ... Q40: =Q36-Q38 -> 114263.74
B42: Taxes | C42: ='P&L Input'!C40 -> 7964 | D42: ='P&L Input'!D40 -> 9214 | E42: ='P&L Input'!E40 -> 9740 | F42: ='P&L Input'!F40 -> 10858 | G42: ='P&L Input'!G40 -> 10521 | H42: =H40*'Cost Buildup'!H37 -> 17833.832 | I42: =I40*'Cost Buildup'!I37 -> 19832.491 | J42: =J40*'Cost Buildup'!J37 -> 21853.193 | K42: =K40*'Cost Buildup'!K37 -> 23828.905 | L42: =L40*'Cost Buildup'!L37 -> 25791.19 | M42: =M40*'Cost Buildup'!M37 -> 27668.622 | N42: =N40*'Cost Buildup'!N37 -> 29385.936 | O42: =O40*'Cost Buildup'!O37 -> 30976.946 | ... Q42: =Q40*'Cost Buildup'!Q37 -> 33485.889
B44: Net Profit | C44: =C40-C42 -> 22146 | D44: =D40-D42 -> 24108 | E44: =E40-E42 -> 26248 | F44: =F40-F42 -> 26750 | G44: =G40-G42 -> 29474 | H44: =H40-H42 -> 49196.063 | I44: =I40-I42 -> 53878.382 | J44: =J40-J42 -> 58472.335 | ... Q44: =Q40-Q42 -> 80777.849
B46: Basic EPS | C46: =C44/420.95 -> 52.609574 | D46: =D44/420.95 -> 57.27046 | E46: =E44/420.95 -> 62.354199 | F46: =F44/420.95 -> 63.54674 | G46: =G44/420.95 -> 70.017817 | H46: =(H44)/30868597*10^7 -> 15937.253 | I46: =(I44)/30868597*10^7 -> 17454.108 | J46: =(J44)/30868597*10^7 -> 18942.336 | K46: =(K44)/30868597*10^7 -> 20345.409 | L46: =(L44)/30868597*10^7 -> 21693.102 | M46: =(M44)/30868597*10^7 -> 22928.138 | N46: =(N44)/30868597*10^7 -> 23993.506 | O46: =(O44)/30868597*10^7 -> 24923.355 | ... Q46: =(Q44)/30868597*10^7 -> 26168.293
B48: Total Dividend Payout | C48: 13039 | D48: 14203 | E48: 19093 | F48: 17814 | G48: 19651 | H48: =H44*H49 -> 31859.272 | I48: =I44*I49 -> 34891.532 | J48: =J44*J49 -> 37866.567 | K48: =K44*K49 -> 40671.372 | L48: =L44*L49 -> 43365.469 | M48: =M44*M49 -> 45834.361 | N48: =N44*N49 -> 47964.077 | O48: =O44*O49 -> 49822.887 | ... Q48: =Q44*Q49 -> 52311.573
B49: (as % on Net Profit) | C49: =C48/C44 -> 0.5887745 | D49: =D48/D44 -> 0.58914053 | E49: =E48/E44 -> 0.7274078 | F49: =F48/F44 -> 0.66594393 | G49: =G48/G44 -> 0.66672321 | H49: =AVERAGE(C49:G49) -> 0.64759799 | I49: =H49 -> 0.64759799 | J49: =I49 -> 0.64759799 | K49: =J49 -> 0.64759799 | L49: =K49 -> 0.64759799 | M49: =L49 -> 0.64759799 | N49: =M49 -> 0.64759799 | O49: =N49 -> 0.64759799 | P49: =O49 -> 0.64759799 | Q49: =P49 -> 0.64759799

Sheet Balance Sheet
B2: Infosys Limited
Q6: (INR in Crores)
B7: Balance Sheet
B8: Particulars | D8: ='Income Statement'!C8 -> 2022 | E8: ='Income Statement'!D8 -> 2023 | F8: ='Income Statement'!E8 -> 2024 | G8: ='Income Statement'!F8 -> 2025 | H8: ='Income Statement'!G8 -> 2026 | I8: ='Income Statement'!H8 -> 2027 | J8: ='Income Statement'!I8 -> 2028 | K8: ='Income Statement'!J8 -> 2029 | ... R8: ='Income Statement'!Q8 -> 2036
D9: Audited | E9: Audited | F9: Audited | G9: Audited | H9: Audited | I9: Estimated | J9: Projected | K9: Projected | L9: Projected | M9: Projected | N9: Projected | O9: Projected | P9: Projected | Q9: Projected | R9: Projected
B10: ASSETS
B12: Non-Current Assets
C13: ='BS Input'!C12 -> PPE | D13: ='BS Input'!D12 -> 13075 | E13: ='BS Input'!E12 -> 13346 | F13: ='BS Input'!F12 -> 12370 | G13: ='BS Input'!G12 -> 11778 | H13: ='BS Input'!H12 -> 12651 | I13: =FAS!H104 -> 13547.48 | J13: =FAS!I104 -> 14443.96 | K13: =FAS!J104 -> 15340.44 | L13: =FAS!K104 -> 16272.779 | M13: =FAS!L104 -> 17205.118 | N13: =FAS!M104 -> 18137.458 | O13: =FAS!N104 -> 19107.09 | P13: =FAS!O104 -> 20076.723 | ... R13: =FAS!Q104 -> 22054.774
C14: ='BS Input'!C13 -> ROU Assets | D14: ='BS Input'!D13 -> 4823 | E14: ='BS Input'!E13 -> 6882 | F14: ='BS Input'!F13 -> 6552 | G14: ='BS Input'!G13 -> 6311 | H14: ='BS Input'!H13 -> 6177 | I14: =FAS!H121 -> 6037.64 | J14: =FAS!I121 -> 5898.28 | K14: =FAS!J121 -> 5758.92 | L14: =FAS!K121 -> 5613.9856 | M14: =FAS!L121 -> 5469.0512 | N14: =FAS!M121 -> 5324.1168 | O14: =FAS!N121 -> 5173.385 | P14: =FAS!O121 -> 5022.6532 | ... R14: =FAS!Q121 -> 4715.1604
C15: ='BS Input'!C14 -> Capital WIP | D15: ='BS Input'!D14 -> 416 | E15: ='BS Input'!E14 -> 288 | F15: ='BS Input'!F14 -> 293 | G15: ='BS Input'!G14 -> 814 | H15: ='BS Input'!H14 -> 526 | I15: =FAS!H164 -> 548 | J15: =FAS!I164 -> 570.11 | K15: =FAS!J164 -> 592.33055 | L15: =FAS!K164 -> 614.6622 | M15: =FAS!L164 -> 637.10551 | N15: =FAS!M164 -> 659.66104 | O15: =FAS!N164 -> 682.32935 | P15: =FAS!O164 -> 705.11099 | ... R15: =FAS!Q164 -> 751.01658
C16: ='BS Input'!C15 -> Goodwill | D16: ='BS Input'!D15 -> 6195 | E16: ='BS Input'!E15 -> 7248 | F16: ='BS Input'!F15 -> 7303 | G16: ='BS Input'!G15 -> 10106 | H16: ='BS Input'!H15 -> 12117 | I16: =H16 -> 12117 | J16: =I16 -> 12117 | K16: =J16 -> 12117 | L16: =K16 -> 12117 | M16: =L16 -> 12117 | N16: =M16 -> 12117 | O16: =N16 -> 12117 | P16: =O16 -> 12117 | ... R16: =Q16 -> 12117
C17: ='BS Input'!C16 -> Other Intangible assets | D17: ='BS Input'!D16 -> 1707 | E17: ='BS Input'!E16 -> 1749 | F17: ='BS Input'!F16 -> 1397 | G17: ='BS Input'!G16 -> 2766 | H17: ='BS Input'!H16 -> 2825 | I17: =FAS!H158 -> 2886.36 | J17: =FAS!I158 -> 2947.72 | K17: =FAS!J158 -> 3009.08 | L17: =FAS!K158 -> 3072.8944 | M17: =FAS!L158 -> 3136.7088 | N17: =FAS!M158 -> 3200.5232 | O17: =FAS!N158 -> 3266.8902 | P17: =FAS!O158 -> 3333.2572 | ... R17: =FAS!Q158 -> 3468.6458
C18: ='BS Input'!C17 -> Financial Assets
C19: ='BS Input'!C18 -> Investments | D19: ='BS Input'!D18 -> 13651 | E19: ='BS Input'!E18 -> 12569 | F19: ='BS Input'!F18 -> 11708 | G19: ='BS Input'!G18 -> 11059 | H19: ='BS Input'!H18 -> 8930 | I19: ='BS items '!I13 -> 15344.305 | J19: ='BS items '!J13 -> 16806.434 | K19: ='BS items '!K13 -> 18254.048 | L19: ='BS items '!L13 -> 19661.282 | M19: ='BS items '!M13 -> 21001.172 | N19: ='BS items '!N13 -> 22246.385 | O19: ='BS items '!O13 -> 23370.009 | P19: ='BS items '!P13 -> 24346.368 | ... R19: ='BS items '!R13 -> 25765.673
C20: ='BS Input'!C19 -> Loans | D20: ='BS Input'!D19 -> 34 | E20: ='BS Input'!E19 -> 39 | F20: ='BS Input'!F19 -> 34 | G20: ='BS Input'!G19 -> 16 | H20: ='BS Input'!H19 -> 6 | I20: =H20 -> 6 | J20: =I20 -> 6 | K20: =J20 -> 6 | L20: =K20 -> 6 | M20: =L20 -> 6 | N20: =M20 -> 6 | O20: =N20 -> 6 | P20: =O20 -> 6 | ... R20: =Q20 -> 6
C21: ='BS Input'!C20 -> Other financial assets | D21: ='BS Input'!D20 -> 1460 | E21: ='BS Input'!E20 -> 2798 | F21: ='BS Input'!F20 -> 3105 | G21: ='BS Input'!G20 -> 3511 | H21: ='BS Input'!H20 -> 2776 | I21: ='BS items '!I15 -> 3459.4135 | J21: ='BS items '!J15 -> 3789.0542 | K21: ='BS items '!K15 -> 4115.4226 | L21: ='BS items '!L15 -> 4432.6872 | M21: ='BS items '!M15 -> 4734.7688 | N21: ='BS items '!N15 -> 5015.5053 | O21: ='BS items '!O15 -> 5268.8293 | P21: ='BS items '!P15 -> 5488.9519 | ... R21: ='BS items '!R15 -> 5808.9379
C22: ='BS Input'!C21 -> Deferred Tax Assets(net) | D22: ='BS Input'!D21 -> 1212 | E22: ='BS Input'!E21 -> 1245 | F22: ='BS Input'!F21 -> 454 | G22: ='BS Input'!G21 -> 1108 | H22: ='BS Input'!H21 -> 2264 | I22: ='BS items '!I17 -> 1600.3226 | J22: ='BS items '!J17 -> 1752.8142 | K22: ='BS items '!K17 -> 1903.792 | L22: ='BS items '!L17 -> 2050.5584 | M22: ='BS items '!M17 -> 2190.3012 | N22: ='BS items '!N17 -> 2320.1698 | O22: ='BS items '!O17 -> 2437.3573 | P22: ='BS items '!P17 -> 2539.1859 | ... R22: ='BS items '!R17 -> 2687.2112
C23: ='BS Input'!C22 -> Income tax assets (net) | D23: ='BS Input'!D22 -> 6098 | E23: ='BS Input'!E22 -> 6453 | F23: ='BS Input'!F22 -> 3045 | G23: ='BS Input'!G22 -> 1622 | H23: ='BS Input'!H22 -> 666 | I23: ='BS items '!I19 -> 4995.8881 | J23: ='BS items '!J19 -> 5471.9365 | K23: ='BS items '!K19 -> 5943.2591 | L23: ='BS items '!L19 -> 6401.4346 | M23: ='BS items '!M19 -> 6837.6837 | N23: ='BS items '!N19 -> 7243.1075 | O23: ='BS items '!O19 -> 7608.9435 | P23: ='BS items '!P19 -> 7926.832 | ... R23: ='BS items '!R19 -> 8388.9376
C24: ='BS Input'!C23 -> Other non-current assets | D24: ='BS Input'!D23 -> 2029 | E24: ='BS Input'!E23 -> 2318 | F24: ='BS Input'!F23 -> 2121 | G24: ='BS Input'!G23 -> 2713 | H24: ='BS Input'!H23 -> 3540 | I24: ='BS items '!I21 -> 3239.5357 | J24: ='BS items '!J21 -> 3548.2248 | K24: ='BS items '!K21 -> 3853.8494 | L24: ='BS items '!L21 -> 4150.9489 | M24: ='BS items '!M21 -> 4433.8304 | N24: ='BS items '!N21 -> 4696.7236 | O24: ='BS items '!O21 -> 4933.9465 | P24: ='BS items '!P21 -> 5140.0782 | ... R24: ='BS items '!R21 -> 5439.7262
B26: Total Non-current Assets | D26: =SUM(D13:D24) -> 50700 | E26: =SUM(E13:E24) -> 54935 | F26: =SUM(F13:F24) -> 48382 | G26: =SUM(G13:G24) -> 51804 | H26: =SUM(H13:H24) -> 52478 | I26: =SUM(I13:I24) -> 63781.945 | J26: =SUM(J13:J24) -> 67351.534 | K26: =SUM(K13:K24) -> 70894.142 | ... R26: =SUM(R13:R24) -> 91203.082
B28: Current Assets
C29: Financial Assets
C30: ='BS Input'!C29 -> Investments | D30: ='BS Input'!D29 -> 6673 | E30: ='BS Input'!E29 -> 6909 | F30: ='BS Input'!F29 -> 12915 | G30: ='BS Input'!G29 -> 12482 | H30: ='BS Input'!H29 -> 12950 | I30: ='BS items '!I24 -> 13118.638 | J30: ='BS items '!J24 -> 14368.687 | K30: ='BS items '!K24 -> 15606.327 | L30: ='BS items '!L24 -> 16809.444 | M30: ='BS items '!M24 -> 17954.985 | N30: ='BS items '!N24 -> 19019.582 | O30: ='BS items '!O24 -> 19980.226 | P30: ='BS items '!P24 -> 20814.965 | ... R30: ='BS items '!R24 -> 22028.402
C31: ='BS Input'!C30 -> Trade Receivables | D31: ='BS Input'!D30 -> 22698 | E31: ='BS Input'!E30 -> 25424 | F31: ='BS Input'!F30 -> 30193 | G31: ='BS Input'!G30 -> 31158 | H31: ='BS Input'!H30 -> 35234 | I31: ='Working Capital'!H11 -> 36158.374 | J31: ='Working Capital'!I11 -> 39603.834 | K31: ='Working Capital'!J11 -> 43015.091 | L31: ='Working Capital'!K11 -> 46331.195 | M31: ='Working Capital'!L11 -> 49488.603 | N31: ='Working Capital'!M11 -> 52422.908 | O31: ='Working Capital'!N11 -> 55070.693 | P31: ='Working Capital'!O11 -> 57371.452 | ... R31: ='Working Capital'!Q11 -> 60715.999
C32: ='BS Input'!C31 -> Cash & Cash Equivalents | D32: ='BS Input'!D31 -> 17472 | E32: ='BS Input'!E31 -> 12173 | F32: ='BS Input'!F31 -> 14786 | G32: ='BS Input'!G31 -> 24455 | H32: ='BS Input'!H31 -> 22201 | I32: ='Cash Flows'!H69 -> 27591.986 | J32: ='Cash Flows'!I69 -> 41196.31 | K32: ='Cash Flows'!J69 -> 56464.53 | L32: ='Cash Flows'!K69 -> 73351.621 | M32: ='Cash Flows'!L69 -> 91913.838 | N32: ='Cash Flows'!M69 -> 112113.54 | O32: ='Cash Flows'!N69 -> 133815.7 | P32: ='Cash Flows'!O69 -> 156986.72 | ... R32: ='Cash Flows'!Q69 -> 207110.96
C33: ='BS Input'!C32 -> Loans | D33: ='BS Input'!D32 -> 248 | E33: ='BS Input'!E32 -> 289 | F33: ='BS Input'!F32 -> 248 | G33: ='BS Input'!G32 -> 249 | H33: ='BS Input'!H32 -> 234 | I33: =H33 -> 234 | J33: =I33 -> 234 | K33: =J33 -> 234 | L33: =K33 -> 234 | M33: =L33 -> 234 | N33: =M33 -> 234 | O33: =N33 -> 234 | P33: =O33 -> 234 | ... R33: =Q33 -> 234
C34: ='BS Input'!C33 -> Other financial assets | D34: ='BS Input'!D33 -> 8727 | E34: ='BS Input'!E33 -> 11604 | F34: ='BS Input'!F33 -> 12085 | G34: ='BS Input'!G33 -> 13840 | H34: ='BS Input'!H33 -> 15890 | I34: ='BS items '!I26 -> 15791.442 | J34: ='BS items '!J26 -> 17296.178 | K34: ='BS items '!K26 -> 18785.976 | L34: ='BS items '!L26 -> 20234.217 | M34: ='BS items '!M26 -> 21613.151 | N34: ='BS items '!N26 -> 22894.65 | O34: ='BS items '!O26 -> 24051.017 | P34: ='BS items '!P26 -> 25055.827 | ... R34: ='BS items '!R26 -> 26516.491
C35: ='BS Input'!C34 -> Income tax assets (net) | D35: ='BS Input'!D34 -> 54 | E35: ='BS Input'!E34 -> 6 | F35: ='BS Input'!F34 -> 6397 | G35: ='BS Input'!G34 -> 2975 | H35: ='BS Input'!H34 -> 1835 | I35: ='BS items '!I28 -> 2765.7775 | J35: ='BS items '!J28 -> 3029.323 | K35: ='BS items '!K28 -> 3290.2522 | L35: ='BS items '!L28 -> 3543.9031 | M35: ='BS items '!M28 -> 3785.4153 | N35: ='BS items '!N28 -> 4009.8623 | O35: ='BS items '!O28 -> 4212.3931 | P35: ='BS items '!P28 -> 4388.3796 | ... R35: ='BS items '!R28 -> 4644.2062
C36: ='BS Input'!C35 -> Other current assets | D36: ='BS Input'!D35 -> 11313 | E36: ='BS Input'!E35 -> 14476 | F36: ='BS Input'!F35 -> 12808 | G36: ='BS Input'!G35 -> 11940 | H36: ='BS Input'!H35 -> 15145 | I36: ='BS items '!I30 -> 16954.544 | J36: ='BS items '!J30 -> 18570.11 | K36: ='BS items '!K30 -> 20169.637 | L36: ='BS items '!L30 -> 21724.547 | M36: ='BS items '!M30 -> 23205.046 | N36: ='BS items '!N30 -> 24580.932 | O36: ='BS items '!O30 -> 25822.47 | P36: ='BS items '!P30 -> 26901.288 | ... R36: ='BS items '!R30 -> 28469.536
B38: Total Current Assets | D38: =SUM(D29:D36) -> 67185 | E38: =SUM(E29:E36) -> 70881 | F38: =SUM(F29:F36) -> 89432 | G38: =SUM(G29:G36) -> 97099 | H38: =SUM(H29:H36) -> 103489 | I38: =SUM(I29:I36) -> 112614.76 | J38: =SUM(J29:J36) -> 134298.44 | K38: =SUM(K29:K36) -> 157565.81 | ... R38: =SUM(R29:R36) -> 349719.6
B40: TOTAL | D40: =D38+D26 -> 117885 | E40: =E38+E26 -> 125816 | F40: =F38+F26 -> 137814 | G40: =G38+G26 -> 148903 | H40: =H38+H26 -> 155967 | I40: =I38+I26 -> 176396.71 | J40: =J38+J26 -> 201649.98 | K40: =K38+K26 -> 228459.96 | ... R40: =R38+R26 -> 440922.68
B42: EQUITY AND LIABILITIES
B44: Shareholder Funds
C45: Equity Share Capital | D45: ='BS Input'!D44 -> 2098 | E45: ='BS Input'!E44 -> 2069 | F45: ='BS Input'!F44 -> 2071 | G45: ='BS Input'!G44 -> 2073 | H45: ='BS Input'!H44 -> 2024 | I45: =H45 -> 2024 | J45: =I45 -> 2024 | K45: =J45 -> 2024 | L45: =K45 -> 2024 | M45: =L45 -> 2024 | N45: =M45 -> 2024 | O45: =N45 -> 2024 | P45: =O45 -> 2024 | ... R45: =Q45 -> 2024
C46: Other Equity | D46: ='BS Input'!D45 -> 73252 | E46: ='BS Input'!E45 -> 73338 | F46: ='BS Input'!F45 -> 86045 | G46: ='BS Input'!G45 -> 93745 | H46: ='BS Input'!H45 -> 90828 | I46: =H46+'Income Statement'!H44-'Income Statement'!H48 -> 108164.79 | J46: =I46+'Income Statement'!I44-'Income Statement'!I48 -> 127151.64 | K46: =J46+'Income Statement'!J44-'Income Statement'!J48 -> 147757.41 | L46: =K46+'Income Statement'!K44-'Income Statement'!K48 -> 169889.46 | M46: =L46+'Income Statement'!L44-'Income Statement'!L48 -> 193487.56 | N46: =M46+'Income Statement'!M44-'Income Statement'!M48 -> 218429.14 | O46: =N46+'Income Statement'!N44-'Income Statement'!N48 -> 244529.65 | P46: =O46+'Income Statement'!O44-'Income Statement'!O48 -> 271641.66 | ... R46: =Q46+'Income Statement'!Q44-'Income Statement'!Q48 -> 328026.67
C47: Non-Controlling Interest | D47: ='BS Input'!D46 -> 386 | E47: ='BS Input'!E46 -> 388 | F47: ='BS Input'!F46 -> 345 | G47: ='BS Input'!G46 -> 385 | H47: ='BS Input'!H46 -> 445 | I47: =H47 -> 445 | J47: =I47 -> 445 | K47: =J47 -> 445 | L47: =K47 -> 445 | M47: =L47 -> 445 | N47: =M47 -> 445 | O47: =N47 -> 445 | P47: =O47 -> 445 | ... R47: =Q47 -> 445
B49: Total Shareholders' Equity | D49: =SUM(D45:D48) -> 75736 | E49: =SUM(E45:E48) -> 75795 | F49: =SUM(F45:F48) -> 88461 | G49: =SUM(G45:G48) -> 96203 | H49: =SUM(H45:H48) -> 93297 | I49: =SUM(I45:I48) -> 110633.79 | J49: =SUM(J45:J48) -> 129620.64 | K49: =SUM(K45:K48) -> 150226.41 | ... R49: =SUM(R45:R48) -> 330495.67
B51: Non-current liabilities
C52: Financial Liabilities
C53: ='BS Input'!C52 -> Lease Liabilities | D53: ='BS Input'!D52 -> 4602 | E53: ='BS Input'!E52 -> 7057 | F53: ='BS Input'!F52 -> 6400 | G53: ='BS Input'!G52 -> 5772 | H53: ='BS Input'!H52 -> 6016 | I53: ='BS items '!I36 -> 7699.8316 | J53: ='BS items '!J36 -> 8433.5335 | K53: ='BS items '!K36 -> 9159.9518 | L53: ='BS items '!L36 -> 9866.1074 | M53: ='BS items '!M36 -> 10538.469 | N53: ='BS items '!N36 -> 11163.322 | O53: ='BS items '!O36 -> 11727.161 | P53: ='BS items '!P36 -> 12217.101 | ... R53: ='BS items '!R36 -> 12929.314
C54: ='BS Input'!C53 -> Other financial liabilities | D54: ='BS Input'!D53 -> 2337 | E54: ='BS Input'!E53 -> 2058 | F54: ='BS Input'!F53 -> 2130 | G54: ='BS Input'!G53 -> 2141 | H54: ='BS Input'!H53 -> 2092 | I54: ='BS items '!I38 -> 2816.8385 | J54: ='BS items '!J38 -> 3085.2495 | K54: ='BS items '!K38 -> 3350.996 | L54: ='BS items '!L38 -> 3609.3297 | M54: ='BS items '!M38 -> 3855.3006 | N54: ='BS items '!N38 -> 4083.8912 | O54: ='BS items '!O38 -> 4290.1611 | P54: ='BS items '!P38 -> 4469.3966 | ... R54: ='BS items '!R38 -> 4729.9462
C55: ='BS Input'!C54 -> Other non current liabilities | D55: ='BS Input'!D54 -> 451 | E55: ='BS Input'!E54 -> 500 | F55: ='BS Input'!F54 -> 235 | G55: ='BS Input'!G54 -> 215 | H55: ='BS Input'!H54 -> 561 | I55: ='BS items '!I40 -> 513.04298 | J55: ='BS items '!J40 -> 561.92984 | K55: ='BS items '!K40 -> 610.3314 | L55: ='BS items '!L40 -> 657.38283 | M55: ='BS items '!M40 -> 702.18258 | N55: ='BS items '!N40 -> 743.81678 | O55: ='BS items '!O40 -> 781.3856 | P55: ='BS items '!P40 -> 814.03054 | ... R55: ='BS items '!R40 -> 861.48558
C56: ='BS Input'!C55 -> Deferred Tax Liability(net) | D56: ='BS Input'!D55 -> 1156 | E56: ='BS Input'!E55 -> 1220 | F56: ='BS Input'!F55 -> 1794 | G56: ='BS Input'!G55 -> 1722 | H56: ='BS Input'!H55 -> 1679 | I56: ='BS items '!I42 -> 1936.3414 | J56: ='BS items '!J42 -> 2120.8516 | K56: ='BS items '!K42 -> 2303.5302 | L56: ='BS items '!L42 -> 2481.113 | M56: ='BS items '!M42 -> 2650.1975 | N56: ='BS items '!N42 -> 2807.3345 | O56: ='BS items '!O42 -> 2949.1278 | P56: ='BS items '!P42 -> 3072.3373 | ... R56: ='BS items '!R42 -> 3251.4434
B58: Total Non-current Liabilities | D58: =SUM(D53:D57) -> 8546 | E58: =SUM(E53:E57) -> 10835 | F58: =SUM(F53:F57) -> 10559 | G58: =SUM(G53:G57) -> 9850 | H58: =SUM(H53:H57) -> 10348 | I58: =SUM(I53:I57) -> 12966.054 | J58: =SUM(J53:J57) -> 14201.564 | K58: =SUM(K53:K57) -> 15424.809 | ... R58: =SUM(R53:R57) -> 21772.189
B60: Current Liabilities
C61: Financial Liabilities
C62: ='BS Input'!C61 -> Lease liabilities | D62: ='BS Input'!D61 -> 872 | E62: ='BS Input'!E61 -> 1242 | F62: ='BS Input'!F61 -> 1959 | G62: ='BS Input'!G61 -> 2455 | H62: ='BS Input'!H61 -> 3160 | I62: ='BS items '!I46 -> 2393.5141 | J62: ='BS items '!J46 -> 2621.5873 | K62: ='BS items '!K46 -> 2847.3965 | L62: ='BS items '!L46 -> 3066.9069 | M62: ='BS items '!M46 -> 3275.9125 | N62: ='BS items '!N46 -> 3470.1497 | O62: ='BS items '!O46 -> 3645.4206 | P62: ='BS items '!P46 -> 3797.7199 | ... R62: ='BS items '!R46 -> 4019.1133
C63: ='BS Input'!C62 -> Trade Payables | D63: ='BS Input'!D62 -> 4134 | E63: ='BS Input'!E62 -> 3865 | F63: ='BS Input'!F62 -> 3956 | G63: ='BS Input'!G62 -> 4164 | H63: ='BS Input'!H62 -> 4744 | I63: ='Working Capital'!H13 -> 5290.3927 | J63: ='Working Capital'!I13 -> 5794.5039 | K63: ='Working Capital'!J13 -> 6293.6107 | L63: ='Working Capital'!K13 -> 6778.7954 | M63: ='Working Capital'!L13 -> 7240.7611 | N63: ='Working Capital'!M13 -> 7670.0843 | O63: ='Working Capital'!N13 -> 8057.4862 | P63: ='Working Capital'!O13 -> 8394.114 | ... R63: ='Working Capital'!Q13 -> 8883.4605
C64: ='BS Input'!C63 -> Other Financial liabilities | D64: ='BS Input'!D63 -> 15837 | E64: ='BS Input'!E63 -> 18558 | F64: ='BS Input'!F63 -> 16959 | G64: ='BS Input'!G63 -> 18138 | H64: ='BS Input'!H63 -> 21483 | I64: ='BS items '!I48 -> 23435.464 | J64: ='BS items '!J48 -> 25668.583 | K64: ='BS items '!K48 -> 27879.534 | L64: ='BS items '!L48 -> 30028.813 | M64: ='BS items '!M48 -> 32075.235 | N64: ='BS items '!N48 -> 33977.058 | O64: ='BS items '!O48 -> 35693.177 | P64: ='BS items '!P48 -> 37184.376 | ... R64: ='BS items '!R48 -> 39352.091
C65: ='BS Input'!C64 -> Other current liabilities | D65: ='BS Input'!D64 -> 9178 | E65: ='BS Input'!E64 -> 10830 | F65: ='BS Input'!F64 -> 10539 | G65: ='BS Input'!G64 -> 11765 | H65: ='BS Input'!H64 -> 15779 | I65: ='BS items '!I50 -> 14813.407 | J65: ='BS items '!J50 -> 16224.947 | K65: ='BS items '!K50 -> 17622.475 | L65: ='BS items '!L50 -> 18981.021 | M65: ='BS items '!M50 -> 20274.551 | N65: ='BS items '!N50 -> 21476.681 | O65: ='BS items '!O50 -> 22561.429 | P65: ='BS items '!P50 -> 23504.007 | ... R65: ='BS items '!R50 -> 24874.205
C66: ='BS Input'!C65 -> Provisions | D66: ='BS Input'!D65 -> 975 | E66: ='BS Input'!E65 -> 1307 | F66: ='BS Input'!F65 -> 1796 | G66: ='BS Input'!G65 -> 1475 | H66: ='BS Input'!H65 -> 1512 | I66: ='BS items '!I52 -> 1805.8617 | J66: ='BS items '!J52 -> 1977.9387 | K66: ='BS items '!K52 -> 2148.3075 | L66: ='BS items '!L52 -> 2313.924 | M66: ='BS items '!M52 -> 2471.6148 | N66: ='BS items '!N52 -> 2618.1632 | O66: ='BS items '!O52 -> 2750.4018 | P66: ='BS items '!P52 -> 2865.3088 | ... R66: ='BS items '!R52 -> 3032.3459
C67: ='BS Input'!C66 -> Income Tax Liabilities(net) | D67: ='BS Input'!D66 -> 2607 | E67: ='BS Input'!E66 -> 3384 | F67: ='BS Input'!F66 -> 3585 | G67: ='BS Input'!G66 -> 4853 | H67: ='BS Input'!H66 -> 5644 | I67: ='BS items '!I54 -> 5058.2211 | J67: ='BS items '!J54 -> 5540.2091 | K67: ='BS items '!K54 -> 6017.4123 | L67: ='BS items '!L54 -> 6481.3044 | M67: ='BS items '!M54 -> 6922.9965 | N67: ='BS items '!N54 -> 7333.4787 | O67: ='BS items '!O54 -> 7703.8792 | P67: ='BS items '!P54 -> 8025.734 | ... R67: ='BS items '!R54 -> 8493.6052
B69: Total Current Liabilities | D69: =SUM(D62:D67) -> 33603 | E69: =SUM(E62:E67) -> 39186 | F69: =SUM(F62:F67) -> 38794 | G69: =SUM(G62:G67) -> 42850 | H69: =SUM(H62:H67) -> 52322 | I69: =SUM(I62:I67) -> 52796.86 | J69: =SUM(J62:J67) -> 57827.769 | K69: =SUM(K62:K67) -> 62808.736 | ... R69: =SUM(R62:R67) -> 88654.821
B71: TOTAL | D71: =D69+D58+D49 -> 117885 | E71: =E69+E58+E49 -> 125816 | F71: =F69+F58+F49 -> 137814 | G71: =G69+G58+G49 -> 148903 | H71: =H69+H58+H49 -> 155967 | I71: =I69+I58+I49 -> 176396.71 | J71: =J69+J58+J49 -> 201649.98 | K71: =K69+K58+K49 -> 228459.96 | ... R71: =R69+R58+R49 -> 440922.68
D73: =D40-D71 -> 0 | E73: =E40-E71 -> 0 | F73: =F40-F71 -> 0 | G73: =G40-G71 -> 0 | H73: =H40-H71 -> 0 | I73: =I40-I71 -> 0 | J73: =J40-J71 -> 0 | K73: =K40-K71 -> 0 | ... R73: =R40-R71 -> 0

Sheet Ratio Analysis
B3: Infosys Limited
P6: ='Income Statement'!P6:Q6 -> (INR in Crores)
B7: Ratio Analysis | T7: Interpretation of ratios
B8: Particulars | C8: ='Balance Sheet'!D8 -> 2022 | D8: ='Balance Sheet'!E8 -> 2023 | E8: ='Balance Sheet'!F8 -> 2024 | F8: ='Balance Sheet'!G8 -> 2025 | G8: ='Balance Sheet'!H8 -> 2026 | H8: ='Balance Sheet'!I8 -> 2027 | I8: ='Balance Sheet'!J8 -> 2028 | J8: ='Balance Sheet'!K8 -> 2029 | ... Q8: ='Balance Sheet'!R8 -> 2036 | R8: Trend
C9: Audited | D9: Audited | E9: Audited | F9: Audited | G9: Audited | H9: Estimated | I9: Projected | J9: Projected | K9: Projected | L9: Projected | M9: Projected | N9: Projected | O9: Projected | P9: Projected | Q9: Projected
B11: Profitability Ratios
B12: EBITDA Margin | C12: ='Income Statement'!C27/'Income Statement'!C14 -> 0.25888475 | D12: ='Income Statement'!D27/'Income Statement'!D14 -> 0.23935898 | E12: ='Income Statement'!E27/'Income Statement'!E14 -> 0.2370339 | F12: ='Income Statement'!F27/'Income Statement'!F14 -> 0.24072642 | G12: ='Income Statement'!G27/'Income Statement'!G14 -> 0.23666387 | H12: ='Income Statement'!H27/'Income Statement'!H14 -> 0.40378597 | I12: ='Income Statement'!I27/'Income Statement'!I14 -> 0.40378597 | J12: ='Income Statement'!J27/'Income Statement'!J14 -> 0.40378597 | ... Q12: ='Income Statement'!Q27/'Income Statement'!Q14 -> 0.40378597 | T12: Infosys’ operating margin remained relatively stable at around 22–24% during FY22–FY26, indicating consistent operating efficiency despite changes in revenue and cost levels. Over the forecast period (FY27–FY36), the margin is projected to increase and stabilize at around 42–43%, reflecting an assumed improvement in operating efficiency and cost management. This expansion indicates stronger profitability from core operations, supported by better operating leverage and a more controlled cost structure.
B13: Operating Margin | C13: ='Income Statement'!C31/'Income Statement'!C14 -> 0.23030886 | D13: ='Income Statement'!D31/'Income Statement'!D14 -> 0.21057186 | E13: ='Income Statement'!E31/'Income Statement'!E14 -> 0.20659205 | F13: ='Income Statement'!F31/'Income Statement'!F14 -> 0.21120314 | G13: ='Income Statement'!G31/'Income Statement'!G14 -> 0.20922474 | H13: ='Income Statement'!H31/'Income Statement'!H14 -> 0.38704785 | I13: ='Income Statement'!I31/'Income Statement'!I14 -> 0.38850404 | J13: ='Income Statement'!J31/'Income Statement'!J14 -> 0.38971595 | ... Q13: ='Income Statement'!Q31/'Income Statement'!Q14 -> 0.39257321 | T13: Infosys’ operating margin remained relatively stable between 22.48% and 24.46% during FY22–FY26, indicating consistent operating profitability despite fluctuations in operating costs. Over the forecast period, the margin is projected to improve gradually from 42.32% to 42.84%, reflecting expectations of better cost control, operating efficiency, and operating leverage. This indicates an improvement in the company’s core operating profitability over the forecast period.
B14: Pretax Margin | C14: ='Income Statement'!C40/'Income Statement'!C14 -> 0.24753167 | D14: ='Income Statement'!D40/'Income Statement'!D14 -> 0.22704014 | E14: ='Income Statement'!E40/'Income Statement'!E14 -> 0.23419015 | F14: ='Income Statement'!F40/'Income Statement'!F14 -> 0.23073808 | G14: ='Income Statement'!G40/'Income Statement'!G14 -> 0.2238735 | H14: ='Income Statement'!H40/'Income Statement'!H14 -> 0.36384566 | I14: ='Income Statement'!I40/'Income Statement'!I14 -> 0.36530184 | J14: ='Income Statement'!J40/'Income Statement'!J14 -> 0.36651376 | ... Q14: ='Income Statement'!Q40/'Income Statement'!Q14 -> 0.36937102 | T14: Infosys’ Pretax Margin declined from 24.29% in 2022 to 21.86% in 2026, indicating a gradual moderation in pre-tax profitability during the initial period. The margin, however, remained above 21%, suggesting relatively stable profitability despite the decline. From 2027 onwards, the Pretax Margin is projected to increase sharply to 37.86% and remain broadly stable around 38% through 2036. This projected improvement indicates expectations of stronger earnings before tax relative to revenue, potentially supported by improved operating efficiency, cost control, and better resource utilization. Overall, the forecast reflects a significant improvement in Infosys’ projected pre-tax profitability compared with the earlier years.
B15: Effective Tax rate | C15: ='Cost Buildup'!C37 -> 0.26449684 | D15: ='Cost Buildup'!D37 -> 0.27651401 | E15: ='Cost Buildup'!E37 -> 0.27064577 | F15: ='Cost Buildup'!F37 -> 0.28871517 | G15: ='Cost Buildup'!G37 -> 0.26305788 | H15: ='Cost Buildup'!H37 -> 0.26605788 | I15: ='Cost Buildup'!I37 -> 0.26905788 | J15: ='Cost Buildup'!J37 -> 0.27205788 | ... Q15: ='Cost Buildup'!Q37 -> 0.29305788 | T15: nfosys’ Effective Tax Rate increased from 26.45% in 2022 to 28.87% in 2025, indicating a higher proportion of pre-tax income being paid as tax during this period. It then declined to 26.31% in 2026, suggesting some moderation in the tax burden. From 2027 onwards, the rate is projected to increase gradually from 26.61% to 29.31% by 2036. This indicates an expected gradual rise in the effective tax burden over the forecast period. A higher effective tax rate can reduce the proportion of pre-tax earnings retained as net profit, making tax management an important factor in future profitability.
B16: Net Margin | C16: ='Income Statement'!C44/'Income Statement'!C14 -> 0.18206033 | D16: ='Income Statement'!D44/'Income Statement'!D14 -> 0.16426036 | E16: ='Income Statement'!E44/'Income Statement'!E14 -> 0.17080757 | F16: ='Income Statement'!F44/'Income Statement'!F14 -> 0.1641205 | G16: ='Income Statement'!G44/'Income Statement'!G14 -> 0.16498181 | H16: ='Income Statement'!H44/'Income Statement'!H14 -> 0.26704165 | I16: ='Income Statement'!I44/'Income Statement'!I14 -> 0.2670145 | J16: ='Income Statement'!J44/'Income Statement'!J14 -> 0.2668008 | ... Q16: ='Income Statement'!Q44/'Income Statement'!Q14 -> 0.26112393 | T16: Infosys’ Net Margin declined from 17.87% in 2022 to 16.06% in 2025, indicating a gradual reduction in the proportion of revenue converted into net profit. It improved slightly to 16.11% in 2026, suggesting some stabilization in profitability. From 2027 onwards, the Net Margin is projected to rise significantly to 27.79%, remaining broadly stable before gradually declining to 27.13% by 2036. This projected improvement indicates expectations of stronger net profitability and better cost efficiency. However, the substantial increase between 2026 and 2027 should be assessed against the assumptions underlying the forecast.
B17: DuPont/Earning Power
B18: Asset Turnover | D18: ='Income Statement'!D14/AVERAGE('Balance Sheet'!D40:E40) -> 1.2044842 | E18: ='Income Statement'!E14/AVERAGE('Balance Sheet'!E40:F40) -> 1.1658006 | F18: ='Income Statement'!F14/AVERAGE('Balance Sheet'!F40:G40) -> 1.1369399 | G18: ='Income Statement'!G14/AVERAGE('Balance Sheet'!G40:H40) -> 1.1719749 | H18: ='Income Statement'!H14/AVERAGE('Balance Sheet'!H40:I40) -> 1.1085818 | I18: ='Income Statement'!I14/AVERAGE('Balance Sheet'!I40:J40) -> 1.0674911 | J18: ='Income Statement'!J14/AVERAGE('Balance Sheet'!J40:K40) -> 1.019093 | K18: ='Income Statement'!K14/AVERAGE('Balance Sheet'!K40:L40) -> 0.97326206 | ... Q18: ='Income Statement'!Q14/AVERAGE('Balance Sheet'!Q40:R40) -> 0.72723455 | T18: Infosys’ Asset Turnover ratio was 122.67% in 2022 and declined to 116.21% in 2024, before improving slightly to 120.03% in 2025. It then decreased to 117.16% in 2026, indicating some moderation in the efficiency of asset utilization. From 2027 onwards, the ratio is projected to decline consistently, reaching 73.26% by 2036. This downward trend suggests that revenue generated per unit of assets is expected to decrease over the forecast period, indicating relatively lower asset utilization efficiency. The trend may reflect growth in the asset base occurring faster than revenue growth, making efficient utilization of assets important for maintaining operational performance.
B19: Pre tax ROA | D19: ='Income Statement'!D40/AVERAGE('Balance Sheet'!D40:E40) -> 0.27346626 | E19: ='Income Statement'!E40/AVERAGE('Balance Sheet'!E40:F40) -> 0.273019 | F19: ='Income Statement'!F40/AVERAGE('Balance Sheet'!F40:G40) -> 0.26233533 | G19: ='Income Statement'!G40/AVERAGE('Balance Sheet'!G40:H40) -> 0.26237413 | H19: ='Income Statement'!H40/AVERAGE('Balance Sheet'!H40:I40) -> 0.40335268 | I19: ='Income Statement'!I40/AVERAGE('Balance Sheet'!I40:J40) -> 0.38995646 | J19: ='Income Statement'!J40/AVERAGE('Balance Sheet'!J40:K40) -> 0.37351162 | K19: ='Income Statement'!K40/AVERAGE('Balance Sheet'!K40:L40) -> 0.35718551 | ... Q19: ='Income Statement'!Q40/AVERAGE('Balance Sheet'!Q40:R40) -> 0.26861937 | T19: Infosys’ Pre-tax ROA remained relatively stable during the historical period, declining slightly from 27.35% in 2022 to 26.23% in 2024, before recovering marginally to 26.24% in 2025. This indicates that the company maintained a relatively consistent ability to generate pre-tax earnings from its asset base. In 2026, the ratio is projected to rise significantly to 44.36%, indicating a substantial improvement in asset profitability. However, from 2027 onwards, Pre-tax ROA is projected to decline gradually, reaching 28.12% by 2036. Despite this decline, the forecast remains above historical levels, suggesting stronger projected returns from asset utilization.
B20: Pre Tax ROE | D20: ='Income Statement'!D40/AVERAGE('Balance Sheet'!D49:E49) -> 0.4398044 | E20: ='Income Statement'!E40/AVERAGE('Balance Sheet'!E49:F49) -> 0.43819404 | F20: ='Income Statement'!F40/AVERAGE('Balance Sheet'!F49:G49) -> 0.40731274 | G20: ='Income Statement'!G40/AVERAGE('Balance Sheet'!G49:H49) -> 0.42211082 | H20: ='Income Statement'!H40/AVERAGE('Balance Sheet'!H49:I49) -> 0.65737886 | I20: ='Income Statement'!I40/AVERAGE('Balance Sheet'!I49:J49) -> 0.61360677 | J20: ='Income Statement'!J40/AVERAGE('Balance Sheet'!J49:K49) -> 0.57406736 | K20: ='Income Statement'!K40/AVERAGE('Balance Sheet'!K49:L49) -> 0.5371134 | ... Q20: ='Income Statement'!Q40/AVERAGE('Balance Sheet'!Q49:R49) -> 0.36129394 | T20: Infosys’ Pre-tax ROE declined from 43.98% in 2022 to 40.73% in 2024, before improving to 42.21% in 2025. This indicates some fluctuation in the company’s ability to generate pre-tax returns from shareholders’ equity, while remaining at a relatively strong level. In 2026, the ratio is projected to increase significantly to 72.05%. Thereafter, Pre-tax ROE is expected to decline gradually, reaching 37.15% by 2036. Despite this projected decline, the ratio remains above the historical level for most of the forecast period, indicating expectations of stronger pre-tax returns on shareholders’ equity compared with the earlier years.
B21: Tax Complement | C21: ='Income Statement'!C44/'Income Statement'!C40 -> 0.73550316 | D21: ='Income Statement'!D44/'Income Statement'!D40 -> 0.72348599 | E21: ='Income Statement'!E44/'Income Statement'!E40 -> 0.72935423 | F21: ='Income Statement'!F44/'Income Statement'!F40 -> 0.71128483 | G21: ='Income Statement'!G44/'Income Statement'!G40 -> 0.73694212 | H21: ='Income Statement'!H44/'Income Statement'!H40 -> 0.73394212 | I21: ='Income Statement'!I44/'Income Statement'!I40 -> 0.73094212 | J21: ='Income Statement'!J44/'Income Statement'!J40 -> 0.72794212 | ... Q21: ='Income Statement'!Q44/'Income Statement'!Q40 -> 0.70694212 | T21: Infosys’ Tax Complement remained relatively stable during the historical period, ranging between 0.71 and 0.74. It declined from 0.74 in 2022 to 0.71 in 2025, before improving slightly to 0.74 in 2026. From 2027 onwards, the Tax Complement is projected to gradually decline from 0.73 to 0.71 by 2036. Overall, the limited movement indicates a relatively stable relationship between after-tax and pre-tax earnings. The gradual decline in the forecast period is consistent with the projected increase in the effective tax rate, suggesting that a slightly larger portion of pre-tax earnings may be absorbed by taxes over time.
B22: ROE | D22: ='Income Statement'!D44/AVERAGE('Balance Sheet'!D49:E49) -> 0.31819232 | E22: ='Income Statement'!E44/AVERAGE('Balance Sheet'!E49:F49) -> 0.31959868 | F22: ='Income Statement'!F44/AVERAGE('Balance Sheet'!F49:G49) -> 0.28971537 | G22: ='Income Statement'!G44/AVERAGE('Balance Sheet'!G49:H49) -> 0.31107124 | H22: ='Income Statement'!H44/AVERAGE('Balance Sheet'!H49:I49) -> 0.48247803 | I22: ='Income Statement'!I44/AVERAGE('Balance Sheet'!I49:J49) -> 0.44851103 | J22: ='Income Statement'!J44/AVERAGE('Balance Sheet'!J49:K49) -> 0.41788781 | K22: ='Income Statement'!K44/AVERAGE('Balance Sheet'!K49:L49) -> 0.38937613 | ... Q22: ='Income Statement'!Q44/AVERAGE('Balance Sheet'!Q49:R49) -> 0.25541391 | T22: Infosys’ ROE increased slightly from 31.82% in 2022 to 31.96% in 2023, before declining to 28.97% in 2024 and recovering to 31.11% in 2025. This indicates some fluctuation in the company’s ability to generate returns from shareholders’ equity. In 2026, ROE is projected to rise significantly to 52.88%. Thereafter, it is expected to decline gradually, reaching 26.27% by 2036. Despite the projected decline, ROE remains relatively strong compared with the historical period for much of the forecast horizon, indicating higher projected returns on shareholders’ equity.
B23: Equity Retention | C23: =('Income Statement'!C44-'Income Statement'!C48)/'Income Statement'!C44 -> 0.4112255 | D23: =('Income Statement'!D44-'Income Statement'!D48)/'Income Statement'!D44 -> 0.41085947 | E23: =('Income Statement'!E44-'Income Statement'!E48)/'Income Statement'!E44 -> 0.2725922 | F23: =('Income Statement'!F44-'Income Statement'!F48)/'Income Statement'!F44 -> 0.33405607 | G23: =('Income Statement'!G44-'Income Statement'!G48)/'Income Statement'!G44 -> 0.33327679 | H23: =('Income Statement'!H44-'Income Statement'!H48)/'Income Statement'!H44 -> 0.35240201 | I23: =('Income Statement'!I44-'Income Statement'!I48)/'Income Statement'!I44 -> 0.35240201 | J23: =('Income Statement'!J44-'Income Statement'!J48)/'Income Statement'!J44 -> 0.35240201 | ... Q23: =('Income Statement'!Q44-'Income Statement'!Q48)/'Income Statement'!Q44 -> 0.35240201 | T23: Infosys’ Equity Retention ratio remained stable at 0.41 in 2022 and 2023, before declining to 0.27 in 2024. It then recovered to 0.33 in 2025 and 2026, indicating an improvement in the proportion of earnings retained within the business. From 2027 onwards, the ratio is projected to remain constant at approximately 0.35 through 2036. This suggests that Infosys is expected to retain around 35% of its earnings for reinvestment and future growth, while the remaining portion may be distributed to shareholders or used for other purposes. Overall, the forecast indicates a stable equity retention policy.
B24: Reinvestment Rate | D24: =(FAS!D168-'Income Statement'!D29+('Working Capital'!D24))/('Income Statement'!D31*D21) -> -0.18336861 | E24: =(FAS!E168-'Income Statement'!E29+('Working Capital'!E24))/('Income Statement'!E31*E21) -> -0.29086831 | F24: =(FAS!F168-'Income Statement'!F29+('Working Capital'!F24))/('Income Statement'!F31*F21) -> 0.031120753 | G24: =(FAS!G168-'Income Statement'!G29+('Working Capital'!G24))/('Income Statement'!G31*G21) -> -0.077290519 | H24: =(FAS!H168-'Income Statement'!H29+('Working Capital'!H24))/('Income Statement'!H31*H21) -> 0.025887607 | I24: =(FAS!I168-'Income Statement'!I29+('Working Capital'!I24))/('Income Statement'!I31*I21) -> 0.059450387 | J24: =(FAS!J168-'Income Statement'!J29+('Working Capital'!J24))/('Income Statement'!J31*J21) -> 0.054382492 | K24: =(FAS!K168-'Income Statement'!K29+('Working Capital'!K24))/('Income Statement'!K31*K21) -> 0.050066821 | ... Q24: =(FAS!Q168-'Income Statement'!Q29+('Working Capital'!Q24))/('Income Statement'!Q31*Q21) -> 0.023539638 | T24: Infosys’ Reinvestment Rate was negative at -16.86% in 2022 and declined further to -25.33% in 2023, indicating that the company was not generating positive reinvestment during these years. It improved significantly to 2.82% in 2024, although it declined to -6.93% in 2025. In 2026, the rate turned positive at 2.23%. From 2027 onwards, it is projected to increase to 5.12%, before gradually declining to 2.03% by 2036. This suggests a shift toward positive reinvestment, with Infosys expected to allocate a modest portion of earnings toward future growth and business expansion.
B26: Liquidity Ratio
B27: Current ratio | C27: ='Balance Sheet'!D38/'Balance Sheet'!D69 -> 1.9993751 | D27: ='Balance Sheet'!E38/'Balance Sheet'!E69 -> 1.8088348 | E27: ='Balance Sheet'!F38/'Balance Sheet'!F69 -> 2.3053049 | F27: ='Balance Sheet'!G38/'Balance Sheet'!G69 -> 2.266021 | G27: ='Balance Sheet'!H38/'Balance Sheet'!H69 -> 1.9779252 | H27: ='Balance Sheet'!I38/'Balance Sheet'!I69 -> 2.1329822 | I27: ='Balance Sheet'!J38/'Balance Sheet'!J69 -> 2.3223867 | J27: ='Balance Sheet'!K38/'Balance Sheet'!K69 -> 2.5086608 | ... Q27: ='Balance Sheet'!R38/'Balance Sheet'!R69 -> 3.944733 | T27: Infosys’ Current Ratio stood at 2.00 in 2022 and declined to 1.81 in 2023, before improving to 2.31 in 2024 and 2.27 in 2025. It moderated to 1.98 in 2026, but remained comfortably above the 1.2 benchmark, indicating adequate short-term liquidity. From 2027 onwards, the ratio is projected to increase steadily from 2.17 to 4.22 by 2036. This indicates a significant strengthening in the company’s projected ability to meet its short-term obligations through current assets. Overall, the forecast suggests improving liquidity and a stronger short-term financial position over the projection period.
B28: Quick ratio | C28: =('Balance Sheet'!D31+'Balance Sheet'!D32)/'Balance Sheet'!D69 -> 1.195429 | D28: =('Balance Sheet'!E31+'Balance Sheet'!E32)/'Balance Sheet'!E69 -> 0.9594498 | E28: =('Balance Sheet'!F31+'Balance Sheet'!F32)/'Balance Sheet'!F69 -> 1.1594319 | F28: =('Balance Sheet'!G31+'Balance Sheet'!G32)/'Balance Sheet'!G69 -> 1.297853 | G28: =('Balance Sheet'!H31+'Balance Sheet'!H32)/'Balance Sheet'!H69 -> 1.0977218 | H28: =('Balance Sheet'!I31+'Balance Sheet'!I32)/'Balance Sheet'!I69 -> 1.207465 | I28: =('Balance Sheet'!J31+'Balance Sheet'!J32)/'Balance Sheet'!J69 -> 1.3972551 | J28: =('Balance Sheet'!K31+'Balance Sheet'!K32)/'Balance Sheet'!K69 -> 1.5838501 | ... Q28: =('Balance Sheet'!R31+'Balance Sheet'!R32)/'Balance Sheet'!R69 -> 3.0210085 | T28: Infosys’ Quick Ratio declined from 1.20 in 2022 to 0.96 in 2023, indicating a temporary weakening in its ability to meet short-term liabilities using its most liquid assets. It improved to 1.30 in 2025, although it moderated to 1.10 in 2026. From 2027 onwards, the ratio is projected to increase steadily from 1.24 to 3.30 by 2036. This indicates a significant improvement in the company’s immediate liquidity position, with quick assets increasingly providing stronger coverage of current liabilities. Overall, the forecast suggests improving short-term financial flexibility and a stronger capacity to meet obligations without relying on inventory.
B29: Cash Ratio | C29: ='Balance Sheet'!D32/'Balance Sheet'!D69 -> 0.51995358 | D29: ='Balance Sheet'!E32/'Balance Sheet'!E69 -> 0.31064666 | E29: ='Balance Sheet'!F32/'Balance Sheet'!F69 -> 0.38114141 | F29: ='Balance Sheet'!G32/'Balance Sheet'!G69 -> 0.57071179 | G29: ='Balance Sheet'!H32/'Balance Sheet'!H69 -> 0.42431482 | H29: ='Balance Sheet'!I32/'Balance Sheet'!I69 -> 0.52260657 | I29: ='Balance Sheet'!J32/'Balance Sheet'!J69 -> 0.71239667 | J29: ='Balance Sheet'!K32/'Balance Sheet'!K69 -> 0.89899166 | ... Q29: ='Balance Sheet'!R32/'Balance Sheet'!R69 -> 2.3361501 | T29: Infosys’ Cash Ratio declined from 0.52 in 2022 to 0.31 in 2023, indicating a temporary weakening in its ability to meet current liabilities using only cash and cash equivalents. It subsequently improved to 0.57 in 2025, before moderating to 0.42 in 2026. From 2027 onwards, the Cash Ratio is projected to rise steadily from 0.56 to 2.62 by 2036. This indicates a significant improvement in the company’s cash-based liquidity position. The projected increase suggests that Infosys is expected to maintain a growing level of cash relative to its short-term obligations, providing greater liquidity and financial flexibility over the forecast period.
B31: Leverage
B32: Asset/Equity | C32: ='Balance Sheet'!D40/'Balance Sheet'!D49 -> 1.5565253 | D32: ='Balance Sheet'!E40/'Balance Sheet'!E49 -> 1.6599512 | E32: ='Balance Sheet'!F40/'Balance Sheet'!F49 -> 1.5579069 | F32: ='Balance Sheet'!G40/'Balance Sheet'!G49 -> 1.5478 | G32: ='Balance Sheet'!H40/'Balance Sheet'!H49 -> 1.6717258 | H32: ='Balance Sheet'!I40/'Balance Sheet'!I49 -> 1.5944198 | I32: ='Balance Sheet'!J40/'Balance Sheet'!J49 -> 1.5556934 | J32: ='Balance Sheet'!K40/'Balance Sheet'!K49 -> 1.5207709 | ... Q32: ='Balance Sheet'!R40/'Balance Sheet'!R49 -> 1.3341254 | T32: Infosys’ Asset/Equity ratio increased from 1.56 in 2022 to 1.66 in 2023, indicating a temporary rise in financial leverage. It then declined gradually to 1.55 in 2025, before increasing slightly to 1.67 in 2026. From 2027 onwards, the ratio is projected to decline consistently from 1.58 to 1.31 by 2036. This downward trend indicates a gradual reduction in the proportion of assets supported by each unit of shareholders’ equity, suggesting lower financial leverage over the forecast period. Overall, the projections indicate a gradual strengthening of the equity base relative to total assets and reduced dependence on leverage.
B33: Debt/Equity | C33: =('Balance Sheet'!D53+'Balance Sheet'!D62)/'Balance Sheet'!D49 -> 0.072277385 | D33: =('Balance Sheet'!E53+'Balance Sheet'!E62)/'Balance Sheet'!E49 -> 0.10949271 | E33: =('Balance Sheet'!F53+'Balance Sheet'!F62)/'Balance Sheet'!F49 -> 0.094493619 | F33: =('Balance Sheet'!G53+'Balance Sheet'!G62)/'Balance Sheet'!G49 -> 0.085517084 | G33: =('Balance Sheet'!H53+'Balance Sheet'!H62)/'Balance Sheet'!H49 -> 0.098352573 | H33: =('Balance Sheet'!I53+'Balance Sheet'!I62)/'Balance Sheet'!I49 -> 0.091232033 | I33: =('Balance Sheet'!J53+'Balance Sheet'!J62)/'Balance Sheet'!J49 -> 0.085288275 | J33: =('Balance Sheet'!K53+'Balance Sheet'!K62)/'Balance Sheet'!K49 -> 0.079928345 | ... Q33: =('Balance Sheet'!R53+'Balance Sheet'!R62)/'Balance Sheet'!R49 -> 0.051281844 | T33: Infosys’ Debt/Equity ratio increased from 0.07 in 2022 to 0.11 in 2023, indicating a temporary increase in debt relative to shareholders’ equity. It then declined to 0.09 in 2024 and 2025, before increasing marginally to 0.10 in 2026. From 2027 onwards, the ratio is projected to decrease steadily from 0.09 to 0.05 by 2036. This indicates a gradual reduction in financial leverage and dependence on debt financing. The consistently low Debt/Equity ratio also indicates that the company’s equity base is substantially higher relative to its debt, while the forecast trend suggests a progressively stronger capital structure with lower debt exposure.
B35: Operating
B36: A/R Turnover | D36: ='Income Statement'!C11/AVERAGE('Balance Sheet'!D31:E31) -> 5.0555255 | E36: ='Income Statement'!D11/AVERAGE('Balance Sheet'!E31:F31) -> 5.2777748 | F36: ='Income Statement'!E11/AVERAGE('Balance Sheet'!F31:G31) -> 5.0095353 | G36: ='Income Statement'!F11/AVERAGE('Balance Sheet'!G31:H31) -> 4.9099289 | H36: ='Income Statement'!G11/AVERAGE('Balance Sheet'!H31:I31) -> 5.0047363 | I36: ='Income Statement'!H11/AVERAGE('Balance Sheet'!I31:J31) -> 4.8632738 | J36: ='Income Statement'!I11/AVERAGE('Balance Sheet'!J31:K31) -> 4.8846128 | K36: ='Income Statement'!J11/AVERAGE('Balance Sheet'!K31:L31) -> 4.9058786 | ... Q36: ='Income Statement'!P11/AVERAGE('Balance Sheet'!Q31:R31) -> 5.0335577 | T36: Infosys’ A/R Turnover ratio is projected to remain relatively stable during the forecast period, increasing from 5.06 in 2027 to 5.28 in 2028 before gradually moderating to 5.01 in 2029 and 4.91 in 2030. The ratio is expected to recover slightly to 5.03 by 2036. Overall, the relatively stable trend suggests consistent receivables management throughout the forecast period, with no significant improvement or deterioration in the efficiency of converting accounts receivable into revenue.
B37: A/P Turnover | D37: ='Income Statement'!C11/AVERAGE('Balance Sheet'!D63:E63) -> 30.414052 | E37: ='Income Statement'!D11/AVERAGE('Balance Sheet'!E63:F63) -> 37.531518 | F37: ='Income Statement'!E11/AVERAGE('Balance Sheet'!F63:G63) -> 37.849754 | G37: ='Income Statement'!F11/AVERAGE('Balance Sheet'!G63:H63) -> 36.594073 | H37: ='Income Statement'!G11/AVERAGE('Balance Sheet'!H63:I63) -> 35.607536 | I37: ='Income Statement'!H11/AVERAGE('Balance Sheet'!I63:J63) -> 33.239133 | J37: ='Income Statement'!I11/AVERAGE('Balance Sheet'!J63:K63) -> 33.38498 | K37: ='Income Statement'!J11/AVERAGE('Balance Sheet'!K63:L63) -> 33.530326 | ... Q37: ='Income Statement'!P11/AVERAGE('Balance Sheet'!Q63:R63) -> 34.402977 | T37: Infosys’ A/P Turnover increased from 30.41x in 2022 to 37.85x in 2024, indicating faster turnover of trade payables and a shorter implied payment cycle during the historical period. The ratio then moderated to 36.59x in 2025 and 35.61x in 2026, suggesting some normalization in the pace of payable settlement. Over the forecast period, A/P Turnover is projected to remain broadly stable, ranging from 33.24x in 2027 to 34.40x by 2036. This relative stability indicates that trade payables are expected to remain broadly aligned with the company’s revenue base. Overall, the projected trend suggests a consistent approach to managing supplier obligations, with no significant change expected in the company’s payable-management pattern.
B38: Fixed Asset Turnover | D38: ='Income Statement'!D14/AVERAGE(FAS!C160:D160) -> 7.0591602 | E38: ='Income Statement'!E14/AVERAGE(FAS!D160:E160) -> 7.2664082 | F38: ='Income Statement'!F14/AVERAGE(FAS!E160:F160) -> 7.9171322 | G38: ='Income Statement'!G14/AVERAGE(FAS!F160:G160) -> 8.4054766 | H38: ='Income Statement'!H14/AVERAGE(FAS!G160:H160) -> 8.3502935 | I38: ='Income Statement'!I14/AVERAGE(FAS!H160:I160) -> 8.8188104 | J38: ='Income Statement'!J14/AVERAGE(FAS!I160:J160) -> 9.2476124 | K38: ='Income Statement'!K14/AVERAGE(FAS!J160:K160) -> 9.6215871 | ... Q38: ='Income Statement'!Q14/AVERAGE(FAS!P160:Q160) -> 10.38835 | T38: Infosys’ Fixed Asset Turnover ratio increased consistently from 7.19 in 2022 to 8.87 in 2026, indicating improving efficiency in generating revenue from its fixed asset base. From 2027 onwards, the ratio is projected to continue rising, reaching 11.11 by 2034, before slightly declining to 11.04 in 2035. This upward trend suggests that Infosys is expected to generate progressively higher revenue for each unit invested in fixed assets. The improvement indicates better utilization of fixed assets and increasing operational efficiency over the forecast period. The slight decline in the final year suggests a marginal moderation in asset utilization efficiency.
B39: ROIC | D39: ='Income Statement'!C31*(1-'Cost Buildup'!D37)/AVERAGE(SUM('Balance Sheet'!E49,'Balance Sheet'!E53,'Balance Sheet'!E62)-'Balance Sheet'!E32,SUM('Balance Sheet'!D49,'Balance Sheet'!D53,'Balance Sheet'!D62)-'Balance Sheet'!D32) -> 0.29881482 | E39: ='Income Statement'!D31*(1-'Cost Buildup'!E37)/AVERAGE(SUM('Balance Sheet'!F49,'Balance Sheet'!F53,'Balance Sheet'!F62)-'Balance Sheet'!F32,SUM('Balance Sheet'!E49,'Balance Sheet'!E53,'Balance Sheet'!E62)-'Balance Sheet'!E32) -> 0.29282183 | F39: ='Income Statement'!E31*(1-'Cost Buildup'!F37)/AVERAGE(SUM('Balance Sheet'!G49,'Balance Sheet'!G53,'Balance Sheet'!G62)-'Balance Sheet'!G32,SUM('Balance Sheet'!F49,'Balance Sheet'!F53,'Balance Sheet'!F62)-'Balance Sheet'!F32) -> 0.27876426 | G39: ='Income Statement'!F31*(1-'Cost Buildup'!G37)/AVERAGE(SUM('Balance Sheet'!H49,'Balance Sheet'!H53,'Balance Sheet'!H62)-'Balance Sheet'!H32,SUM('Balance Sheet'!G49,'Balance Sheet'!G53,'Balance Sheet'!G62)-'Balance Sheet'!G32) -> 0.31661742 | H39: ='Income Statement'!G31*(1-'Cost Buildup'!H37)/AVERAGE(SUM('Balance Sheet'!I49,'Balance Sheet'!I53,'Balance Sheet'!I62)-'Balance Sheet'!I32,SUM('Balance Sheet'!H49,'Balance Sheet'!H53,'Balance Sheet'!H62)-'Balance Sheet'!H32) -> 0.3164032 | I39: ='Income Statement'!H31*(1-'Cost Buildup'!I37)/AVERAGE(SUM('Balance Sheet'!J49,'Balance Sheet'!J53,'Balance Sheet'!J62)-'Balance Sheet'!J32,SUM('Balance Sheet'!I49,'Balance Sheet'!I53,'Balance Sheet'!I62)-'Balance Sheet'!I32) -> 0.54117756 | J39: ='Income Statement'!I31*(1-'Cost Buildup'!J37)/AVERAGE(SUM('Balance Sheet'!K49,'Balance Sheet'!K53,'Balance Sheet'!K62)-'Balance Sheet'!K32,SUM('Balance Sheet'!J49,'Balance Sheet'!J53,'Balance Sheet'!J62)-'Balance Sheet'!J32) -> 0.55606006 | K39: ='Income Statement'!J31*(1-'Cost Buildup'!K37)/AVERAGE(SUM('Balance Sheet'!L49,'Balance Sheet'!L53,'Balance Sheet'!L62)-'Balance Sheet'!L32,SUM('Balance Sheet'!K49,'Balance Sheet'!K53,'Balance Sheet'!K62)-'Balance Sheet'!K32) -> 0.56881137 | ... Q39: ='Income Statement'!P31*(1-'Cost Buildup'!Q37)/AVERAGE(SUM('Balance Sheet'!R49,'Balance Sheet'!R53,'Balance Sheet'!R62)-'Balance Sheet'!R32,SUM('Balance Sheet'!Q49,'Balance Sheet'!Q53,'Balance Sheet'!Q62)-'Balance Sheet'!Q32) -> 0.60446218 | T39: Infosys’ ROIC is projected to increase from 62.88% in 2027 to 70.09% by 2036, indicating a sustained improvement in the company’s expected returns relative to its invested capital. The projected ROIC exceeds 66% by 2029 and approaches 70% toward the end of the forecast period, suggesting strong expected capital efficiency and the potential to generate attractive returns on invested capital. From a valuation perspective, the sustainability of these elevated returns will depend on Infosys’ ability to maintain operating profitability, manage reinvestment requirements efficiently, and deploy incremental capital at attractive rates of return. Overall, the forecast indicates strengthening capital efficiency; however, these projections should be evaluated against historical performance, industry conditions, and the long-term assumptions underlying the financial model.

Sheet Cash Flows
B2: ='Ratio Analysis'!B3 -> Infosys Limited
P6: (INR in Crores)
B7: Cash Flow Statement
B8: Particulars | C8: ='Balance Sheet'!D8 -> 2022 | D8: ='Balance Sheet'!E8 -> 2023 | E8: ='Balance Sheet'!F8 -> 2024 | F8: ='Balance Sheet'!G8 -> 2025 | G8: ='Balance Sheet'!H8 -> 2026 | H8: ='Balance Sheet'!I8 -> 2027 | I8: ='Balance Sheet'!J8 -> 2028 | J8: ='Balance Sheet'!K8 -> 2029 | ... Q8: ='Balance Sheet'!R8 -> 2036
C9: Audited | D9: Audited | E9: Audited | F9: Audited | G9: Audited | H9: Estimated | I9: Projected | J9: Projected | K9: Projected | L9: Projected | M9: Projected | N9: Projected | O9: Projected | P9: Projected | Q9: Projected
B11: Cashflows from Operating activities
B13: Profit before tax | D13: ='Income Statement'!D40 -> 33322 | E13: ='Income Statement'!E40 -> 35988 | F13: ='Income Statement'!F40 -> 37608 | G13: ='Income Statement'!G40 -> 39995 | H13: ='Income Statement'!H40 -> 67029.895 | I13: ='Income Statement'!I40 -> 73710.873 | J13: ='Income Statement'!J40 -> 80325.528 | K13: ='Income Statement'!K40 -> 86632.329 | ... Q13: ='Income Statement'!Q40 -> 114263.74
B14: Add:
B15: Depreciation & Amortisation | D15: ='Income Statement'!D29 -> 4225 | E15: ='Income Statement'!E29 -> 4678 | F15: ='Income Statement'!F29 -> 4812 | G15: ='Income Statement'!G29 -> 4902 | H15: ='Income Statement'!H29 -> 3083.6 | I15: ='Income Statement'!I29 -> 3083.6 | J15: ='Income Statement'!J29 -> 3083.6 | K15: ='Income Statement'!K29 -> 3206.944 | ... Q15: ='Income Statement'!Q29 -> 3468.6306
B16: Finance costs | D16: ='Income Statement'!D34 -> 284 | E16: ='Income Statement'!E34 -> 470 | F16: ='Income Statement'!F34 -> 416 | G16: ='Income Statement'!G34 -> 416 | H16: ='Income Statement'!H34 -> 8727.0051 | I16: ='Income Statement'!I34 -> 9558.5843 | J16: ='Income Statement'!J34 -> 10381.908 | K16: ='Income Statement'!K34 -> 11182.267 | ... Q16: ='Income Statement'!Q34 -> 14654.111
B17: Increase/(decrease) in Current Liabilities
B18: Lease liabilities | D18: ='Balance Sheet'!E62-'Balance Sheet'!D62 -> 370 | E18: ='Balance Sheet'!F62-'Balance Sheet'!E62 -> 717 | F18: ='Balance Sheet'!G62-'Balance Sheet'!F62 -> 496 | G18: ='Balance Sheet'!H62-'Balance Sheet'!G62 -> 705 | H18: ='Balance Sheet'!I62-'Balance Sheet'!H62 -> -766.48593 | I18: ='Balance Sheet'!J62-'Balance Sheet'!I62 -> 228.07327 | J18: ='Balance Sheet'!K62-'Balance Sheet'!J62 -> 225.80916 | K18: ='Balance Sheet'!L62-'Balance Sheet'!K62 -> 219.51042 | ... Q18: ='Balance Sheet'!R62-'Balance Sheet'!Q62 -> 95.749699
B19: Trade Payables | D19: ='Balance Sheet'!E63-'Balance Sheet'!D63 -> -269 | E19: ='Balance Sheet'!F63-'Balance Sheet'!E63 -> 91 | F19: ='Balance Sheet'!G63-'Balance Sheet'!F63 -> 208 | G19: ='Balance Sheet'!H63-'Balance Sheet'!G63 -> 580 | H19: ='Balance Sheet'!I63-'Balance Sheet'!H63 -> 546.39272 | I19: ='Balance Sheet'!J63-'Balance Sheet'!I63 -> 504.11118 | J19: ='Balance Sheet'!K63-'Balance Sheet'!J63 -> 499.10679 | K19: ='Balance Sheet'!L63-'Balance Sheet'!K63 -> 485.18467 | ... Q19: ='Balance Sheet'!R63-'Balance Sheet'!Q63 -> 211.6359
B20: Other Financial liabilities | D20: ='Balance Sheet'!E64-'Balance Sheet'!D64 -> 2721 | E20: ='Balance Sheet'!F64-'Balance Sheet'!E64 -> -1599 | F20: ='Balance Sheet'!G64-'Balance Sheet'!F64 -> 1179 | G20: ='Balance Sheet'!H64-'Balance Sheet'!G64 -> 3345 | H20: ='Balance Sheet'!I64-'Balance Sheet'!H64 -> 1952.4636 | I20: ='Balance Sheet'!J64-'Balance Sheet'!I64 -> 2233.1195 | J20: ='Balance Sheet'!K64-'Balance Sheet'!J64 -> 2210.951 | K20: ='Balance Sheet'!L64-'Balance Sheet'!K64 -> 2149.2786 | ... Q20: ='Balance Sheet'!R64-'Balance Sheet'!Q64 -> 937.508
B21: Other current liabilities | D21: ='Balance Sheet'!E65-'Balance Sheet'!D65 -> 1652 | E21: ='Balance Sheet'!F65-'Balance Sheet'!E65 -> -291 | F21: ='Balance Sheet'!G65-'Balance Sheet'!F65 -> 1226 | G21: ='Balance Sheet'!H65-'Balance Sheet'!G65 -> 4014 | H21: ='Balance Sheet'!I65-'Balance Sheet'!H65 -> -965.59324 | I21: ='Balance Sheet'!J65-'Balance Sheet'!I65 -> 1411.5406 | J21: ='Balance Sheet'!K65-'Balance Sheet'!J65 -> 1397.528 | K21: ='Balance Sheet'!L65-'Balance Sheet'!K65 -> 1358.5452 | ... Q21: ='Balance Sheet'!R65-'Balance Sheet'!Q65 -> 592.59281
B22: Provisions | D22: ='Balance Sheet'!E66-'Balance Sheet'!D66 -> 332 | E22: ='Balance Sheet'!F66-'Balance Sheet'!E66 -> 489 | F22: ='Balance Sheet'!G66-'Balance Sheet'!F66 -> -321 | G22: ='Balance Sheet'!H66-'Balance Sheet'!G66 -> 37 | H22: ='Balance Sheet'!I66-'Balance Sheet'!H66 -> 293.86169 | I22: ='Balance Sheet'!J66-'Balance Sheet'!I66 -> 172.07703 | J22: ='Balance Sheet'!K66-'Balance Sheet'!J66 -> 170.3688 | K22: ='Balance Sheet'!L66-'Balance Sheet'!K66 -> 165.61651 | ... Q22: ='Balance Sheet'!R66-'Balance Sheet'!Q66 -> 72.241361
B23: Current Tax Liabilities(net) | D23: ='Balance Sheet'!E67-'Balance Sheet'!D67 -> 777 | E23: ='Balance Sheet'!F67-'Balance Sheet'!E67 -> 201 | F23: ='Balance Sheet'!G67-'Balance Sheet'!F67 -> 1268 | G23: ='Balance Sheet'!H67-'Balance Sheet'!G67 -> 791 | H23: ='Balance Sheet'!I67-'Balance Sheet'!H67 -> -585.77891 | I23: ='Balance Sheet'!J67-'Balance Sheet'!I67 -> 481.988 | J23: ='Balance Sheet'!K67-'Balance Sheet'!J67 -> 477.20323 | K23: ='Balance Sheet'!L67-'Balance Sheet'!K67 -> 463.89209 | ... Q23: ='Balance Sheet'!R67-'Balance Sheet'!Q67 -> 202.34815
B24: Less:
B25: Other Income | D25: =-'Income Statement'!D12 -> 0 | E25: =-'Income Statement'!E12 -> 0 | F25: =-'Income Statement'!F12 -> 0 | G25: =-'Income Statement'!G12 -> 0 | H25: =-'Income Statement'!H12 -> 0 | I25: =-'Income Statement'!I12 -> 0 | J25: =-'Income Statement'!J12 -> 0 | K25: =-'Income Statement'!K12 -> 0 | ... Q25: =-'Income Statement'!Q12 -> 0
B26: Taxes paid | D26: =-'Income Statement'!D42 -> -9214 | E26: =-'Income Statement'!E42 -> -9740 | F26: =-'Income Statement'!F42 -> -10858 | G26: =-'Income Statement'!G42 -> -10521 | H26: =-'Income Statement'!H42 -> -17833.832 | I26: =-'Income Statement'!I42 -> -19832.491 | J26: =-'Income Statement'!J42 -> -21853.193 | K26: =-'Income Statement'!K42 -> -23828.905 | ... Q26: =-'Income Statement'!Q42 -> -33485.889
B27: Other non-cash adjustments
B28: Increase/(decrease) in Current Assets
B29: Investments | D29: =-('Balance Sheet'!E30-'Balance Sheet'!D30) -> -236 | E29: =-('Balance Sheet'!F30-'Balance Sheet'!E30) -> -6006 | F29: =-('Balance Sheet'!G30-'Balance Sheet'!F30) -> 433 | G29: =-('Balance Sheet'!H30-'Balance Sheet'!G30) -> -468 | H29: =-('Balance Sheet'!I30-'Balance Sheet'!H30) -> -168.63756 | I29: =-('Balance Sheet'!J30-'Balance Sheet'!I30) -> -1250.0493 | J29: =-('Balance Sheet'!K30-'Balance Sheet'!J30) -> -1237.6399 | K29: =-('Balance Sheet'!L30-'Balance Sheet'!K30) -> -1203.1171 | ... Q29: =-('Balance Sheet'!R30-'Balance Sheet'!Q30) -> -524.79558
B30: Trade Receivables | D30: =-('Balance Sheet'!E31-'Balance Sheet'!D31) -> -2726 | E30: =-('Balance Sheet'!F31-'Balance Sheet'!E31) -> -4769 | F30: =-('Balance Sheet'!G31-'Balance Sheet'!F31) -> -965 | G30: =-('Balance Sheet'!H31-'Balance Sheet'!G31) -> -4076 | H30: =-('Balance Sheet'!I31-'Balance Sheet'!H31) -> -924.37351 | I30: =-('Balance Sheet'!J31-'Balance Sheet'!I31) -> -3445.4607 | J30: =-('Balance Sheet'!K31-'Balance Sheet'!J31) -> -3411.2571 | K30: =-('Balance Sheet'!L31-'Balance Sheet'!K31) -> -3316.1032 | ... Q30: =-('Balance Sheet'!R31-'Balance Sheet'!Q31) -> -1446.473
B31: Other financial assets | D31: =-(('Balance Sheet'!E33+'Balance Sheet'!E34)-('Balance Sheet'!D33+'Balance Sheet'!D34)) -> -2918 | E31: =-(('Balance Sheet'!F33+'Balance Sheet'!F34)-('Balance Sheet'!E33+'Balance Sheet'!E34)) -> -440 | F31: =-(('Balance Sheet'!G33+'Balance Sheet'!G34)-('Balance Sheet'!F33+'Balance Sheet'!F34)) -> -1756 | G31: =-(('Balance Sheet'!H33+'Balance Sheet'!H34)-('Balance Sheet'!G33+'Balance Sheet'!G34)) -> -2035 | H31: =-(('Balance Sheet'!I33+'Balance Sheet'!I34)-('Balance Sheet'!H33+'Balance Sheet'!H34)) -> 98.557936 | I31: =-(('Balance Sheet'!J33+'Balance Sheet'!J34)-('Balance Sheet'!I33+'Balance Sheet'!I34)) -> -1504.7356 | J31: =-(('Balance Sheet'!K33+'Balance Sheet'!K34)-('Balance Sheet'!J33+'Balance Sheet'!J34)) -> -1489.7979 | K31: =-(('Balance Sheet'!L33+'Balance Sheet'!L34)-('Balance Sheet'!K33+'Balance Sheet'!K34)) -> -1448.2414 | ... Q31: =-(('Balance Sheet'!R33+'Balance Sheet'!R34)-('Balance Sheet'!Q33+'Balance Sheet'!Q34)) -> -631.71796
B32: Other current assets | D32: =-(('Balance Sheet'!E35+'Balance Sheet'!E36)-('Balance Sheet'!D35+'Balance Sheet'!D36)) -> -3115 | E32: =-(('Balance Sheet'!F35+'Balance Sheet'!F36)-('Balance Sheet'!E35+'Balance Sheet'!E36)) -> -4723 | F32: =-(('Balance Sheet'!G35+'Balance Sheet'!G36)-('Balance Sheet'!F35+'Balance Sheet'!F36)) -> 4290 | G32: =-(('Balance Sheet'!H35+'Balance Sheet'!H36)-('Balance Sheet'!G35+'Balance Sheet'!G36)) -> -2065 | H32: =-(('Balance Sheet'!I35+'Balance Sheet'!I36)-('Balance Sheet'!H35+'Balance Sheet'!H36)) -> -2740.3218 | I32: =-(('Balance Sheet'!J35+'Balance Sheet'!J36)-('Balance Sheet'!I35+'Balance Sheet'!I36)) -> -1879.1109 | J32: =-(('Balance Sheet'!K35+'Balance Sheet'!K36)-('Balance Sheet'!J35+'Balance Sheet'!J36)) -> -1860.4567 | K32: =-(('Balance Sheet'!L35+'Balance Sheet'!L36)-('Balance Sheet'!K35+'Balance Sheet'!K36)) -> -1808.561 | ... Q32: =-(('Balance Sheet'!R35+'Balance Sheet'!R36)-('Balance Sheet'!Q35+'Balance Sheet'!Q36)) -> -788.88815
B34: Net Cash generated from/(used in) Operating Activities (A) | D34: =SUM(D13:D32) -> 25205 | E34: =SUM(E13:E32) -> 15066 | F34: =SUM(F13:F32) -> 38036 | G34: =SUM(G13:G32) -> 35620 | H34: =SUM(H13:H32) -> 57746.753 | I34: =SUM(I13:I32) -> 63472.119 | J34: =SUM(J13:J32) -> 68919.659 | K34: =SUM(K13:K32) -> 74258.64 | ... Q34: =SUM(Q13:Q32) -> 97620.792
B36: Cashflows from Investing activities
B37: Add:
B38: Other Income | D38: ='Income Statement'!D12 -> 0 | E38: ='Income Statement'!E12 -> 0 | F38: ='Income Statement'!F12 -> 0 | G38: ='Income Statement'!G12 -> 0 | H38: ='Income Statement'!H12 -> 0 | I38: ='Income Statement'!I12 -> 0 | J38: ='Income Statement'!J12 -> 0 | K38: ='Income Statement'!K12 -> 0 | ... Q38: ='Income Statement'!Q12 -> 0
B39: Less:
B40: Capital Expenditure on PPE, ROU & Intangibles | D40: =-((('Balance Sheet'!E13+'Balance Sheet'!E14+'Balance Sheet'!E16+'Balance Sheet'!E17)-('Balance Sheet'!D13+'Balance Sheet'!D14+'Balance Sheet'!D16+'Balance Sheet'!D17))+'Income Statement'!D29) -> -7650 | E40: =-((('Balance Sheet'!F13+'Balance Sheet'!F14+'Balance Sheet'!F16+'Balance Sheet'!F17)-('Balance Sheet'!E13+'Balance Sheet'!E14+'Balance Sheet'!E16+'Balance Sheet'!E17))+'Income Statement'!E29) -> -3075 | F40: =-((('Balance Sheet'!G13+'Balance Sheet'!G14+'Balance Sheet'!G16+'Balance Sheet'!G17)-('Balance Sheet'!F13+'Balance Sheet'!F14+'Balance Sheet'!F16+'Balance Sheet'!F17))+'Income Statement'!F29) -> -8151 | G40: =-((('Balance Sheet'!H13+'Balance Sheet'!H14+'Balance Sheet'!H16+'Balance Sheet'!H17)-('Balance Sheet'!G13+'Balance Sheet'!G14+'Balance Sheet'!G16+'Balance Sheet'!G17))+'Income Statement'!G29) -> -7711 | H40: =-((('Balance Sheet'!I13+'Balance Sheet'!I14+'Balance Sheet'!I16+'Balance Sheet'!I17)-('Balance Sheet'!H13+'Balance Sheet'!H14+'Balance Sheet'!H16+'Balance Sheet'!H17))+'Income Statement'!H29) -> -3902.08 | I40: =-((('Balance Sheet'!J13+'Balance Sheet'!J14+'Balance Sheet'!J16+'Balance Sheet'!J17)-('Balance Sheet'!I13+'Balance Sheet'!I14+'Balance Sheet'!I16+'Balance Sheet'!I17))+'Income Statement'!I29) -> -3902.08 | J40: =-((('Balance Sheet'!K13+'Balance Sheet'!K14+'Balance Sheet'!K16+'Balance Sheet'!K17)-('Balance Sheet'!J13+'Balance Sheet'!J14+'Balance Sheet'!J16+'Balance Sheet'!J17))+'Income Statement'!J29) -> -3902.08 | K40: =-((('Balance Sheet'!L13+'Balance Sheet'!L14+'Balance Sheet'!L16+'Balance Sheet'!L17)-('Balance Sheet'!K13+'Balance Sheet'!K14+'Balance Sheet'!K16+'Balance Sheet'!K17))+'Income Statement'!K29) -> -4058.1632 | ... Q40: =-((('Balance Sheet'!R13+'Balance Sheet'!R14+'Balance Sheet'!R16+'Balance Sheet'!R17)-('Balance Sheet'!Q13+'Balance Sheet'!Q14+'Balance Sheet'!Q16+'Balance Sheet'!Q17))+'Income Statement'!Q29) -> -4389.3093
B41: Increase in Capital WIP | D41: =-('Balance Sheet'!E15-'Balance Sheet'!D15) -> 128 | E41: =-('Balance Sheet'!F15-'Balance Sheet'!E15) -> -5 | F41: =-('Balance Sheet'!G15-'Balance Sheet'!F15) -> -521 | G41: =-('Balance Sheet'!H15-'Balance Sheet'!G15) -> 288 | H41: =-('Balance Sheet'!I15-'Balance Sheet'!H15) -> -22 | I41: =-('Balance Sheet'!J15-'Balance Sheet'!I15) -> -22.11 | J41: =-('Balance Sheet'!K15-'Balance Sheet'!J15) -> -22.22055 | K41: =-('Balance Sheet'!L15-'Balance Sheet'!K15) -> -22.331653 | ... Q41: =-('Balance Sheet'!R15-'Balance Sheet'!Q15) -> -23.010033
B42: Less:
B43: Increase/(decrease) in Non- Current Assets
B44: Investments | D44: =-('Balance Sheet'!E19-'Balance Sheet'!D19) -> 1082 | E44: =-('Balance Sheet'!F19-'Balance Sheet'!E19) -> 861 | F44: =-('Balance Sheet'!G19-'Balance Sheet'!F19) -> 649 | G44: =-('Balance Sheet'!H19-'Balance Sheet'!G19) -> 2129 | H44: =-('Balance Sheet'!I19-'Balance Sheet'!H19) -> -6414.305 | I44: =-('Balance Sheet'!J19-'Balance Sheet'!I19) -> -1462.1288 | J44: =-('Balance Sheet'!K19-'Balance Sheet'!J19) -> -1447.614 | K44: =-('Balance Sheet'!L19-'Balance Sheet'!K19) -> -1407.2342 | ... Q44: =-('Balance Sheet'!R19-'Balance Sheet'!Q19) -> -613.83077
B45: Other financial assets | D45: =-(('Balance Sheet'!E20+'Balance Sheet'!E21)-('Balance Sheet'!D20+'Balance Sheet'!D21)) -> -1343 | E45: =-(('Balance Sheet'!F20+'Balance Sheet'!F21)-('Balance Sheet'!E20+'Balance Sheet'!E21)) -> -302 | F45: =-(('Balance Sheet'!G20+'Balance Sheet'!G21)-('Balance Sheet'!F20+'Balance Sheet'!F21)) -> -388 | G45: =-(('Balance Sheet'!H20+'Balance Sheet'!H21)-('Balance Sheet'!G20+'Balance Sheet'!G21)) -> 745 | H45: =-(('Balance Sheet'!I20+'Balance Sheet'!I21)-('Balance Sheet'!H20+'Balance Sheet'!H21)) -> -683.41348 | I45: =-(('Balance Sheet'!J20+'Balance Sheet'!J21)-('Balance Sheet'!I20+'Balance Sheet'!I21)) -> -329.64075 | J45: =-(('Balance Sheet'!K20+'Balance Sheet'!K21)-('Balance Sheet'!J20+'Balance Sheet'!J21)) -> -326.36835 | K45: =-(('Balance Sheet'!L20+'Balance Sheet'!L21)-('Balance Sheet'!K20+'Balance Sheet'!K21)) -> -317.26461 | ... Q45: =-(('Balance Sheet'!R20+'Balance Sheet'!R21)-('Balance Sheet'!Q20+'Balance Sheet'!Q21)) -> -138.38974
B46: Deferred Tax Assets(net) | D46: =-('Balance Sheet'!E22-'Balance Sheet'!D22) -> -33 | E46: =-('Balance Sheet'!F22-'Balance Sheet'!E22) -> 791 | F46: =-('Balance Sheet'!G22-'Balance Sheet'!F22) -> -654 | G46: =-('Balance Sheet'!H22-'Balance Sheet'!G22) -> -1156 | H46: =-('Balance Sheet'!I22-'Balance Sheet'!H22) -> 663.6774 | I46: =-('Balance Sheet'!J22-'Balance Sheet'!I22) -> -152.49161 | J46: =-('Balance Sheet'!K22-'Balance Sheet'!J22) -> -150.9778 | K46: =-('Balance Sheet'!L22-'Balance Sheet'!K22) -> -146.76642 | ... Q46: =-('Balance Sheet'!R22-'Balance Sheet'!Q22) -> -64.019013
B47: Income tax assets (net) | D47: =-('Balance Sheet'!E23-'Balance Sheet'!D23) -> -355 | E47: =-('Balance Sheet'!F23-'Balance Sheet'!E23) -> 3408 | F47: =-('Balance Sheet'!G23-'Balance Sheet'!F23) -> 1423 | G47: =-('Balance Sheet'!H23-'Balance Sheet'!G23) -> 956 | H47: =-('Balance Sheet'!I23-'Balance Sheet'!H23) -> -4329.8881 | I47: =-('Balance Sheet'!J23-'Balance Sheet'!I23) -> -476.04841 | J47: =-('Balance Sheet'!K23-'Balance Sheet'!J23) -> -471.32261 | K47: =-('Balance Sheet'!L23-'Balance Sheet'!K23) -> -458.1755 | ... Q47: =-('Balance Sheet'!R23-'Balance Sheet'!Q23) -> -199.85459
B48: Other non-current assets | D48: =-('Balance Sheet'!E24-'Balance Sheet'!D24) -> -289 | E48: =-('Balance Sheet'!F24-'Balance Sheet'!E24) -> 197 | F48: =-('Balance Sheet'!G24-'Balance Sheet'!F24) -> -592 | G48: =-('Balance Sheet'!H24-'Balance Sheet'!G24) -> -827 | H48: =-('Balance Sheet'!I24-'Balance Sheet'!H24) -> 300.46426 | I48: =-('Balance Sheet'!J24-'Balance Sheet'!I24) -> -308.68903 | J48: =-('Balance Sheet'!K24-'Balance Sheet'!J24) -> -305.62462 | K48: =-('Balance Sheet'!L24-'Balance Sheet'!K24) -> -297.09951 | ... Q48: =-('Balance Sheet'!R24-'Balance Sheet'!Q24) -> -129.59379
B50: Net Cash generated from/(used in) Investing Activities (B) | D50: =SUM(D36:D48) -> -8460 | E50: =SUM(E36:E48) -> 1875 | F50: =SUM(F36:F48) -> -8234 | G50: =SUM(G36:G48) -> -5576 | H50: =SUM(H36:H48) -> -14387.545 | I50: =SUM(I36:I48) -> -6653.1886 | J50: =SUM(J36:J48) -> -6626.208 | K50: =SUM(K36:K48) -> -6707.0351 | ... Q50: =SUM(Q36:Q48) -> -5558.0073
B52: Cashflows from Financing activities
B54: Increase in non-current liabilities
B55: Lease Liabilities | D55: ='Balance Sheet'!E53-'Balance Sheet'!D53 -> 2455 | E55: ='Balance Sheet'!F53-'Balance Sheet'!E53 -> -657 | F55: ='Balance Sheet'!G53-'Balance Sheet'!F53 -> -628 | G55: ='Balance Sheet'!H53-'Balance Sheet'!G53 -> 244 | H55: ='Balance Sheet'!I53-'Balance Sheet'!H53 -> 1683.8316 | I55: ='Balance Sheet'!J53-'Balance Sheet'!I53 -> 733.70189 | J55: ='Balance Sheet'!K53-'Balance Sheet'!J53 -> 726.41833 | K55: ='Balance Sheet'!L53-'Balance Sheet'!K53 -> 706.15556 | ... Q55: ='Balance Sheet'!R53-'Balance Sheet'!Q53 -> 308.02265
B56: Other Financial Assets | D56: =('Balance Sheet'!E54+'Balance Sheet'!E55)-('Balance Sheet'!D54+'Balance Sheet'!D55) -> -230 | E56: =('Balance Sheet'!F54+'Balance Sheet'!F55)-('Balance Sheet'!E54+'Balance Sheet'!E55) -> -193 | F56: =('Balance Sheet'!G54+'Balance Sheet'!G55)-('Balance Sheet'!F54+'Balance Sheet'!F55) -> -9 | G56: =('Balance Sheet'!H54+'Balance Sheet'!H55)-('Balance Sheet'!G54+'Balance Sheet'!G55) -> 297 | H56: =('Balance Sheet'!I54+'Balance Sheet'!I55)-('Balance Sheet'!H54+'Balance Sheet'!H55) -> 676.88145 | I56: =('Balance Sheet'!J54+'Balance Sheet'!J55)-('Balance Sheet'!I54+'Balance Sheet'!I55) -> 317.29789 | J56: =('Balance Sheet'!K54+'Balance Sheet'!K55)-('Balance Sheet'!J54+'Balance Sheet'!J55) -> 314.14803 | K56: =('Balance Sheet'!L54+'Balance Sheet'!L55)-('Balance Sheet'!K54+'Balance Sheet'!K55) -> 305.38516 | ... Q56: =('Balance Sheet'!R54+'Balance Sheet'!R55)-('Balance Sheet'!Q54+'Balance Sheet'!Q55) -> 133.20797
B57: Provisions | D57: 0 | E57: 0 | F57: 0 | G57: 0 | H57: 0 | I57: 0 | J57: 0 | K57: 0 | L57: 0 | M57: 0 | N57: 0 | O57: 0 | P57: 0 | Q57: 0
B58: Deferred Tax Liability | D58: ='Balance Sheet'!E56-'Balance Sheet'!D56 -> 64 | E58: ='Balance Sheet'!F56-'Balance Sheet'!E56 -> 574 | F58: ='Balance Sheet'!G56-'Balance Sheet'!F56 -> -72 | G58: ='Balance Sheet'!H56-'Balance Sheet'!G56 -> -43 | H58: ='Balance Sheet'!I56-'Balance Sheet'!H56 -> 257.34145 | I58: ='Balance Sheet'!J56-'Balance Sheet'!I56 -> 184.51019 | J58: ='Balance Sheet'!K56-'Balance Sheet'!J56 -> 182.67853 | K58: ='Balance Sheet'!L56-'Balance Sheet'!K56 -> 177.58288 | ... Q58: ='Balance Sheet'!R56-'Balance Sheet'!Q56 -> 77.461049
B59: Changes in other equity | D59: =('Balance Sheet'!E46-'Balance Sheet'!D46)-'Income Statement'!D44 -> -24022 | E59: =('Balance Sheet'!F46-'Balance Sheet'!E46)-'Income Statement'!E44 -> -13541 | F59: =('Balance Sheet'!G46-'Balance Sheet'!F46)-'Income Statement'!F44 -> -19050 | G59: =('Balance Sheet'!H46-'Balance Sheet'!G46)-'Income Statement'!G44 -> -32391 | H59: =('Balance Sheet'!I46-'Balance Sheet'!H46)-'Income Statement'!H44 -> -31859.272 | I59: =('Balance Sheet'!J46-'Balance Sheet'!I46)-'Income Statement'!I44 -> -34891.532 | J59: =('Balance Sheet'!K46-'Balance Sheet'!J46)-'Income Statement'!J44 -> -37866.567 | K59: =('Balance Sheet'!L46-'Balance Sheet'!K46)-'Income Statement'!K44 -> -40671.372 | ... Q59: =('Balance Sheet'!R46-'Balance Sheet'!Q46)-'Income Statement'!Q44 -> -52311.573
B60: Changes in NCI | D60: ='Balance Sheet'!E47-'Balance Sheet'!D47 -> 2 | E60: ='Balance Sheet'!F47-'Balance Sheet'!E47 -> -43 | F60: ='Balance Sheet'!G47-'Balance Sheet'!F47 -> 40 | G60: ='Balance Sheet'!H47-'Balance Sheet'!G47 -> 60 | H60: ='Balance Sheet'!I47-'Balance Sheet'!H47 -> 0 | I60: ='Balance Sheet'!J47-'Balance Sheet'!I47 -> 0 | J60: ='Balance Sheet'!K47-'Balance Sheet'!J47 -> 0 | K60: ='Balance Sheet'!L47-'Balance Sheet'!K47 -> 0 | ... Q60: ='Balance Sheet'!R47-'Balance Sheet'!Q47 -> 0
B61: Issue of Equity shares | D61: ='Balance Sheet'!E45-'Balance Sheet'!D45 -> -29 | E61: ='Balance Sheet'!F45-'Balance Sheet'!E45 -> 2 | F61: ='Balance Sheet'!G45-'Balance Sheet'!F45 -> 2 | G61: ='Balance Sheet'!H45-'Balance Sheet'!G45 -> -49 | H61: ='Balance Sheet'!I45-'Balance Sheet'!H45 -> 0 | I61: ='Balance Sheet'!J45-'Balance Sheet'!I45 -> 0 | J61: ='Balance Sheet'!K45-'Balance Sheet'!J45 -> 0 | K61: ='Balance Sheet'!L45-'Balance Sheet'!K45 -> 0 | ... Q61: ='Balance Sheet'!R45-'Balance Sheet'!Q45 -> 0
B62: Less:
B63: Interest paid | D63: =-'Income Statement'!D34 -> -284 | E63: =-'Income Statement'!E34 -> -470 | F63: =-'Income Statement'!F34 -> -416 | G63: =-'Income Statement'!G34 -> -416 | H63: =-'Income Statement'!H34 -> -8727.0051 | I63: =-'Income Statement'!I34 -> -9558.5843 | J63: =-'Income Statement'!J34 -> -10381.908 | K63: =-'Income Statement'!K34 -> -11182.267 | ... Q63: =-'Income Statement'!Q34 -> -14654.111
B65: Net Cash generated from/(used in) Financing Activities (C) | D65: =SUM(D52:D63) -> -22044 | E65: =SUM(E52:E63) -> -14328 | F65: =SUM(F52:F63) -> -20133 | G65: =SUM(G52:G63) -> -32298 | H65: =SUM(H52:H63) -> -37968.223 | I65: =SUM(I52:I63) -> -43214.606 | J65: =SUM(J52:J63) -> -47025.23 | K65: =SUM(K52:K63) -> -50664.515 | ... Q65: =SUM(Q52:Q63) -> -66446.993
B66: Effect of exchange rate changes on cash
B67: Net Cashflows during the year | D67: =D34+D50+D65+D66 -> -5299 | E67: =E34+E50+E65+E66 -> 2613 | F67: =F34+F50+F65+F66 -> 9669 | G67: =G34+G50+G65+G66 -> -2254 | H67: =H34+H50+H65+H66 -> 5390.9859 | I67: =I34+I50+I65+I66 -> 13604.324 | J67: =J34+J50+J65+J66 -> 15268.22 | K67: =K34+K50+K65+K66 -> 16887.09 | ... Q67: =Q34+Q50+Q65+Q66 -> 25615.792
B68: Opening Cash & Cash equivalents | D68: ='Balance Sheet'!D32 -> 17472 | E68: =D69 -> 12173 | F68: =E69 -> 14786 | G68: =F69 -> 24455 | H68: =G69 -> 22201 | I68: =H69 -> 27591.986 | J68: =I69 -> 41196.31 | K68: =J69 -> 56464.53 | L68: =K69 -> 73351.621 | ... Q68: =P69 -> 181495.17
B69: Closing Cash & Cash equivalents | D69: =D67+D68 -> 12173 | E69: =E67+E68 -> 14786 | F69: =F67+F68 -> 24455 | G69: =G67+G68 -> 22201 | H69: =H67+H68 -> 27591.986 | I69: =I67+I68 -> 41196.31 | J69: =J67+J68 -> 56464.53 | K69: =K67+K68 -> 73351.621 | ... Q69: =Q67+Q68 -> 207110.96
B71: Working Capital Reconciliation (per Balance Sheet movements used above)
B72: Trade Receivables | D72: =D30 -> -2726 | E72: =E30 -> -4769 | F72: =F30 -> -965 | G72: =G30 -> -4076 | H72: =H30 -> -924.37351 | I72: =I30 -> -3445.4607 | J72: =J30 -> -3411.2571 | K72: =K30 -> -3316.1032 | ... Q72: =Q30 -> -1446.473
B73: Trade Payables | D73: =D19 -> -269 | E73: =E19 -> 91 | F73: =F19 -> 208 | G73: =G19 -> 580 | H73: =H19 -> 546.39272 | I73: =I19 -> 504.11118 | J73: =J19 -> 499.10679 | K73: =K19 -> 485.18467 | ... Q73: =Q19 -> 211.6359
B74: Provisions | D74: =D22 -> 332 | E74: =E22 -> 489 | F74: =F22 -> -321 | G74: =G22 -> 37 | H74: =H22 -> 293.86169 | I74: =I22 -> 172.07703 | J74: =J22 -> 170.3688 | K74: =K22 -> 165.61651 | ... Q74: =Q22 -> 72.241361
B75: Other financial and non-financial liabilities (Current) | D75: =D20+D21 -> 4373 | E75: =E20+E21 -> -1890 | F75: =F20+F21 -> 2405 | G75: =G20+G21 -> 7359 | H75: =H20+H21 -> 986.87034 | I75: =I20+I21 -> 3644.6601 | J75: =J20+J21 -> 3608.479 | K75: =K20+K21 -> 3507.8238 | ... Q75: =Q20+Q21 -> 1530.1008
B76: Other financial and non-financial liabilities (Non-current) | D76: =D56 -> -230 | E76: =E56 -> -193 | F76: =F56 -> -9 | G76: =G56 -> 297 | H76: =H56 -> 676.88145 | I76: =I56 -> 317.29789 | J76: =J56 -> 314.14803 | K76: =K56 -> 305.38516 | ... Q76: =Q56 -> 133.20797
B77: Other financial assets, excl. Loans (Current) | D77: =-('Balance Sheet'!E34-'Balance Sheet'!D34) -> -2877 | E77: =-('Balance Sheet'!F34-'Balance Sheet'!E34) -> -481 | F77: =-('Balance Sheet'!G34-'Balance Sheet'!F34) -> -1755 | G77: =-('Balance Sheet'!H34-'Balance Sheet'!G34) -> -2050 | H77: =-('Balance Sheet'!I34-'Balance Sheet'!H34) -> 98.557936 | I77: =-('Balance Sheet'!J34-'Balance Sheet'!I34) -> -1504.7356 | J77: =-('Balance Sheet'!K34-'Balance Sheet'!J34) -> -1489.7979 | K77: =-('Balance Sheet'!L34-'Balance Sheet'!K34) -> -1448.2414 | ... Q77: =-('Balance Sheet'!R34-'Balance Sheet'!Q34) -> -631.71796
B78: Other current assets, excl. Income tax assets (Current) | D78: =-('Balance Sheet'!E36-'Balance Sheet'!D36) -> -3163 | E78: =-('Balance Sheet'!F36-'Balance Sheet'!E36) -> 1668 | F78: =-('Balance Sheet'!G36-'Balance Sheet'!F36) -> 868 | G78: =-('Balance Sheet'!H36-'Balance Sheet'!G36) -> -3205 | H78: =-('Balance Sheet'!I36-'Balance Sheet'!H36) -> -1809.5444 | I78: =-('Balance Sheet'!J36-'Balance Sheet'!I36) -> -1615.5654 | J78: =-('Balance Sheet'!K36-'Balance Sheet'!J36) -> -1599.5274 | K78: =-('Balance Sheet'!L36-'Balance Sheet'!K36) -> -1554.9101 | ... Q78: =-('Balance Sheet'!R36-'Balance Sheet'!Q36) -> -678.24649
B79: Other financial assets, excl. Loans (Non-current) | D79: =-('Balance Sheet'!E21-'Balance Sheet'!D21) -> -1338 | E79: =-('Balance Sheet'!F21-'Balance Sheet'!E21) -> -307 | F79: =-('Balance Sheet'!G21-'Balance Sheet'!F21) -> -406 | G79: =-('Balance Sheet'!H21-'Balance Sheet'!G21) -> 735 | H79: =-('Balance Sheet'!I21-'Balance Sheet'!H21) -> -683.41348 | I79: =-('Balance Sheet'!J21-'Balance Sheet'!I21) -> -329.64075 | J79: =-('Balance Sheet'!K21-'Balance Sheet'!J21) -> -326.36835 | K79: =-('Balance Sheet'!L21-'Balance Sheet'!K21) -> -317.26461 | ... Q79: =-('Balance Sheet'!R21-'Balance Sheet'!Q21) -> -138.38974
B80: Other non-current assets | D80: =D48 -> -289 | E80: =E48 -> 197 | F80: =F48 -> -592 | G80: =G48 -> -827 | H80: =H48 -> 300.46426 | I80: =I48 -> -308.68903 | J80: =J48 -> -305.62462 | K80: =K48 -> -297.09951 | ... Q80: =Q48 -> -129.59379
B81: Net Change in Working Capital (per Cash Flow Statement) | D81: =SUM(D72:D80) -> -6187 | E81: =SUM(E72:E80) -> -5195 | F81: =SUM(F72:F80) -> -567 | G81: =SUM(G72:G80) -> -1150 | H81: =SUM(H72:H80) -> -514.30294 | I81: =SUM(I72:I80) -> -2565.9453 | J81: =SUM(J72:J80) -> -2540.4728 | K81: =SUM(K72:K80) -> -2469.6087 | ... Q81: =SUM(Q72:Q80) -> -1077.2349

Sheet Summary
A1: ='Cash Flows'!B2 -> Infosys Limited
A2: Valuation Summary - Football Field
